Workbook

Sheet Resumen
A1: Resumen de la búsqueda de repositorios
A3: Categoría | B3: Total | C3: Alta | D3: Media | E3: Baja | F3: En pila
A4: Excel | B4: =COUNTIFS(Catalogo!$D$5:$D$127,"*Excel*") -> 26 | C4: =COUNTIFS(Catalogo!$D$5:$D$127,"*Excel*",Catalogo!$K$5:$K$127,"Alta") -> 8 | D4: =COUNTIFS(Catalogo!$D$5:$D$127,"*Excel*",Catalogo!$K$5:$K$127,"Media") -> 5 | E4: =COUNTIFS(Catalogo!$D$5:$D$127,"*Excel*",Catalogo!$K$5:$K$127,"Baja") -> 13 | F4: =COUNTIFS(Catalogo!$D$5:$D$127,"*Excel*",Catalogo!$L$5:$L$127,"Sí") -> 8
A5: PowerPoint | B5: =COUNTIFS(Catalogo!$D$5:$D$127,"*PowerPoint*") -> 24 | C5: =COUNTIFS(Catalogo!$D$5:$D$127,"*PowerPoint*",Catalogo!$K$5:$K$127,"Alta") -> 6 | D5: =COUNTIFS(Catalogo!$D$5:$D$127,"*PowerPoint*",Catalogo!$K$5:$K$127,"Media") -> 6 | E5: =COUNTIFS(Catalogo!$D$5:$D$127,"*PowerPoint*",Catalogo!$K$5:$K$127,"Baja") -> 12 | F5: =COUNTIFS(Catalogo!$D$5:$D$127,"*PowerPoint*",Catalogo!$L$5:$L$127,"Sí") -> 7
A6: Evaluación económica | B6: =COUNTIFS(Catalogo!$D$5:$D$127,"*Evaluación económica*") -> 22 | C6: =COUNTIFS(Catalogo!$D$5:$D$127,"*Evaluación económica*",Catalogo!$K$5:$K$127,"Alta") -> 5 | D6: =COUNTIFS(Catalogo!$D$5:$D$127,"*Evaluación económica*",Catalogo!$K$5:$K$127,"Media") -> 6 | E6: =COUNTIFS(Catalogo!$D$5:$D$127,"*Evaluación económica*",Catalogo!$K$5:$K$127,"Baja") -> 11 | F6: =COUNTIFS(Catalogo!$D$5:$D$127,"*Evaluación económica*",Catalogo!$L$5:$L$127,"Sí") -> 3
A7: Riesgo | B7: =COUNTIFS(Catalogo!$D$5:$D$127,"*Riesgo*") -> 27 | C7: =COUNTIFS(Catalogo!$D$5:$D$127,"*Riesgo*",Catalogo!$K$5:$K$127,"Alta") -> 5 | D7: =COUNTIFS(Catalogo!$D$5:$D$127,"*Riesgo*",Catalogo!$K$5:$K$127,"Media") -> 10 | E7: =COUNTIFS(Catalogo!$D$5:$D$127,"*Riesgo*",Catalogo!$K$5:$K$127,"Baja") -> 12 | F7: =COUNTIFS(Catalogo!$D$5:$D$127,"*Riesgo*",Catalogo!$L$5:$L$127,"Sí") -> 6
A8: Oil & Gas y logística | B8: =COUNTIFS(Catalogo!$D$5:$D$127,"*Oil & Gas y logística*") -> 29 | C8: =COUNTIFS(Catalogo!$D$5:$D$127,"*Oil & Gas y logística*",Catalogo!$K$5:$K$127,"Alta") -> 4 | D8: =COUNTIFS(Catalogo!$D$5:$D$127,"*Oil & Gas y logística*",Catalogo!$K$5:$K$127,"Media") -> 7 | E8: =COUNTIFS(Catalogo!$D$5:$D$127,"*Oil & Gas y logística*",Catalogo!$K$5:$K$127,"Baja") -> 18 | F8: =COUNTIFS(Catalogo!$D$5:$D$127,"*Oil & Gas y logística*",Catalogo!$L$5:$L$127,"Sí") -> 2
A9: Repositorios únicos | B9: =COUNTA(Catalogo!$B$5:$B$127) -> 123 | C9: =COUNTIF(Catalogo!$K$5:$K$127,"Alta") -> 24 | D9: =COUNTIF(Catalogo!$K$5:$K$127,"Media") -> 33 | E9: =COUNTIF(Catalogo!$K$5:$K$127,"Baja") -> 66 | F9: =COUNTIF(Catalogo!$L$5:$L$127,"Sí") -> 22
A10: Nota: un repo puede aparecer en varias categorías; por eso la suma por categoría supera el total único.
A12: Tus decisiones
A13: Sí | B13: =COUNTIF(Catalogo!$P$5:$P$127,"Sí") -> 0
A14: No | B14: =COUNTIF(Catalogo!$P$5:$P$127,"No") -> 0
A15: Revisar | B15: =COUNTIF(Catalogo!$P$5:$P$127,"Revisar") -> 0
A16: Pendientes | B16: =COUNTA(Catalogo!$B$5:$B$127)-SUM(B13:B15) -> 123
A18: Hallazgos clave
A19: • No existe en GitHub un modelo listo de 'movilización de taladro: lump sum vs. contratación directa'; se construye a medida con las piezas de la pila.
A20: • No hay datasets públicos de tarifas de rig move ni de transporte pesado: tarifas y duraciones deben venir de tus datos (facturas, DDR, cotizaciones).
A21: • Varios repos de dominio (RigGo, Well-Costing, Chaimurat) no tienen licencia: se usa solo su estructura como referencia, no su código.
A22: • Las skills xlsx y pptx de Claude ya están disponibles en esta sesión; LibreOffice permite recalcular y revisar visualmente.
A23: • XLRisk permitiría que tú mismo corras Monte Carlo dentro de tu Excel de escritorio (Windows/Mac).

Sheet Catalogo
A1: Catálogo de repositorios GitHub – Evaluación de movilización (lump sum vs. tercerizado)
A2: Edita solo las columnas amarillas (Tu decisión: Sí / No / Revisar; Comentarios). Fuente: 5 agentes buscadores, 12-oct-2026; estrellas y fechas verificadas en GitHub/PyPI.
A4: ID | B4: Repositorio | C4: URL | D4: Categoría(s) | E4: Lenguaje | F4: Estrellas | G4: Última actividad | H4: Licencia | I4: Qué hace | J4: Cómo ayuda a la evaluación | K4: Prioridad | L4: En pila propuesta | M4: Capa (propuesta) | N4: Rol en la pila | O4: Nota | P4: Tu decisión | Q4: Comentarios
A5: 1 | B5: NLRWindSystems/LandBOSSE | C5: https://github.com/NLRWindSystems/LandBOSSE | D5: Evaluación económica | E5: Python | F5: ~17 | G5: 2026-07-28 | H5: Apache-2.0 | I5: Costos BOS eólicos: transporte, grúas, gestión, demoras por clima | J5: Análogo más cercano a mover equipo pesado; estructura de rubros de B | K5: Alta | L5: Sí | M5: 3. Evaluación económica | N5: Referencia de rubros: transporte, grúas, gestión, demoras por clima
A6: 2 | B6: numpy/numpy-financial | C6: https://github.com/numpy/numpy-financial | D6: Evaluación económica | E6: Python | F6: ~411 | G6: 2026-10-05 | H6: BSD-3 | I6: npv, irr, pmt estilo Excel | J6: Verificar VPN/TIR del Excel (ojo convención t=0 vs t=1) | K6: Alta | L6: Sí | M6: 3. Evaluación económica | N6: Verificar VPN/TIR si se usan flujos en el tiempo
A7: 3 | B7: PhilipGriffith/AHPy | C7: https://github.com/PhilipGriffith/AHPy | D7: Evaluación económica | E7: Python | F7: ~154 | G7: 2025-09-18 | H7: MIT | I7: AHP con razón de consistencia | J7: Pesos de criterios cualitativos (control, HSE, responsabilidad) | K7: Alta | L7: Sí | M7: 3. Evaluación económica | N7: Pesos de criterios cualitativos con consistencia (se replica en Excel)
A8: 4 | B8: SilverDecisions/SilverDecisions | C8: https://github.com/SilverDecisions/SilverDecisions | D8: Evaluación económica | E8: JavaScript | F8: ~139 | G8: 2023-03-04 | H8: LGPL-3.0 | I8: Árboles de decisión con valor esperado y sensibilidad | J8: Árbol A vs B con ramas de demora; gráfico para PPT | K8: Alta | L8: No
A9: 5 | B9: Valdecy/pyDecision | C9: https://github.com/Valdecy/pyDecision | D9: Evaluación económica | E9: Python | F9: ~366 | G9: 2026-06-03 | H9: Otra (ver LICENSE) | I9: MCDA: AHP, TOPSIS, ELECTRE, PROMETHEE | J9: Robustez del ranking A vs B | K9: Alta | L9: No | O9: Revisar licencia
A10: 6 | B10: anthropics/financial-services | C10: https://github.com/anthropics/financial-services | D10: Excel; PowerPoint | E10: Markdown/YAML/Python | F10: ~39.4k | G10: no visible | H10: Apache-2.0 | I10: Skills financieras: audit-xls, xlsx-author, DCF/3 estados | J10: Checklist de auditoría y convenciones (insumos vs cálculos, sin valores fijos) | Buenas prácticas de modelo y deck | K10: Alta | L10: Sí | M10: 2. Validar el Excel | N10: Checklist de auditoría (audit-xls) y convenciones de modelado
A11: 7 | B11: anthropics/skills (xlsx/recalc.py) | C11: https://github.com/anthropics/skills/tree/main/skills/xlsx | D11: Excel | E11: Python | F11: ~181k (repo) | G11: no visible | H11: Source-available | I11: Recalcula con LibreOffice headless y reporta en JSON los errores de fórmula | J11: QA automático: valores en caché y cero errores antes de entregar | K11: Alta | L11: Sí | M11: 2. Validar el Excel | N11: Recalcular con LibreOffice y garantizar cero errores (ya disponible)
A12: 8 | B12: jmcnamara/XlsxWriter | C12: https://github.com/jmcnamara/XlsxWriter | D12: Excel | E12: Python | F12: ~4.0k | G12: 2025-09-16 (PyPI 3.2.9) | H12: BSD-2-Clause | I12: Crea .xlsx con fórmulas, nombres, validación, formato condicional, gráficos nativos, tablas, protección | J12: Genera el libro desde cero: supuestos con listas, cálculos A vs B con fórmulas vivas, tornado/cascada, semáforos | K12: Alta | L12: Sí | M12: 1. Construir el Excel | N12: Escribir el libro con fórmulas vivas, nombres, validaciones y gráficos nativos
A13: 9 | B13: openpyxl | C13: https://foss.heptapod.net/openpyxl/openpyxl | D13: Excel | E13: Python | F13: n/d | G13: 2024-06-28 (PyPI 3.1.5) | H13: MIT | I13: Lee/escribe xlsx con fórmulas, nombres, validación, gráficos; edita libros existentes | J13: Releer y verificar el libro generado; editarlo después; base de recalc.py | K13: Alta | L13: Sí | M13: 1. Construir el Excel | N13: Releer, verificar y editar el libro (ya instalado) | O13: No está en GitHub; confirmado en PyPI
A14: 10 | B14: SALib/SALib | C14: https://github.com/SALib/SALib | D14: Excel; Riesgo | E14: Python | F14: ~1.0k | G14: 2026-09-19 (PyPI 1.6.0) | H14: MIT | I14: Sensibilidad global (Sobol, Morris, FAST) | J14: Qué supuestos pesan más en la diferencia A−B | Variable que domina A vs B; alimenta tornado | K14: Alta | L14: Sí | M14: 4. Riesgo y sensibilidad | N14: Ranking de variables que mueven la diferencia A − B | O14: También en Riesgo
A15: 11 | B15: scanny/python-pptx | C15: https://github.com/scanny/python-pptx | D15: Excel; PowerPoint | E15: Python | F15: ~3.6k | G15: 2024-08-07 (PyPI 1.0.2) | H15: MIT | I15: Crea PowerPoint con gráficos nativos, tablas, texto | J15: Presentación con gráficos editables alimentados por el modelo | Motor del deck con gráficos editables sobre plantilla corporativa | K15: Alta | L15: Sí | M15: 5. Presentación | N15: Generar el deck con gráficos nativos editables | O15: También en PowerPoint
A16: 12 | B16: scottshambaugh/monaco | C16: https://github.com/scottshambaugh/monaco | D16: Excel; Riesgo | E16: Python | F16: ~157 | G16: 2026-06-19 (PyPI 0.21.0) | H16: MIT | I16: Monte Carlo para incertidumbre y sensibilidades | J16: P10/P50/P90 de demoras y sobrecostos de B | Motor Python para costo y plazo; percentiles | K16: Alta | L16: Sí | M16: 4. Riesgo y sensibilidad | N16: Monte Carlo de costo y plazo: P10/P50/P90 y P(B < A) | O16: También en Riesgo
A17: 13 | B17: vinci1it2000/formulas | C17: https://github.com/vinci1it2000/formulas | D17: Excel | E17: Python | F17: ~501 | G17: 2026-03-11 (PyPI 1.3.4) | H17: EUPL-1.1+ | I17: Interpreta fórmulas Excel y ejecuta libros completos sin Excel | J17: Recalcular el modelo en Linux y correr escenarios cambiando entradas | K17: Alta | L17: Sí | M17: 2. Validar el Excel | N17: Segundo motor: recalcular sin Excel y probar celdas clave
A18: 14 | B18: Chaimurat/exploration-campaign-optimizer | C18: https://github.com/Chaimurat/exploration-campaign-optimizer | D18: Oil & Gas y logística | E18: Python (OR-Tools) | F18: 0 | G18: 2026-10-07 | H18: Sin licencia | I18: Campaña de 20 pozos con 3 taladros y tiempos de movilización por secuencia | J18: Rig move como días no productivos según distancia; justifica standby | K18: Alta | L18: No | O18: Sin licencia
A19: 15 | B19: juansecorreapaez/RigGo | C19: https://github.com/juansecorreapaez/RigGo | D19: Oil & Gas y logística | E19: JS/HTML (PWA + Supabase) | F19: 0 | G19: 2026-10-02 | H19: Sin licencia | I19: Planea y ejecuta rig moves: plan desde Excel, cargas, flat time, plan vs real | J19: Plantilla Excel en español (Rig Down / Transporte / Rig Up) para el inventario de cargas de B | K19: Alta | L19: Sí | M19: 3. Evaluación económica | N19: Estructura del inventario de cargas (solo estructura; sin licencia) | O19: Replicar estructura, no copiar código
A20: 16 | B20: praveen-christuraj/Well-Costing | C20: https://github.com/praveen-christuraj/Well-Costing | D20: Oil & Gas y logística | E20: Python + Vue | F20: 1 | G20: 2026-08-31 | H20: Sin licencia | I20: AFE, costo diario, AFE vs real; rate card hora/día/único | J20: Estructura de líneas de costo A vs B | K20: Alta | L20: Sí | M20: 3. Evaluación económica | N20: Estructura de rate card hora/día/único (solo estructura; sin licencia) | O20: Sin licencia
A21: 17 | B21: samarioexplorer/Guyana_Offshore_Drilling_Analytics | C21: https://github.com/samarioexplorer/Guyana_Offshore_Drilling_Analytics | D21: Oil & Gas y logística | E21: Python + SQL + Power BI | F21: 0 | G21: 2026-10-07 | H21: MIT | I21: NPT, KPIs e impacto económico | J21: Costo taladro = horas × tarifa/24 + producción diferida | K21: Alta | L21: No
A22: 18 | B22: anthropics/skills | C22: https://github.com/anthropics/skills | D22: PowerPoint | E22: Markdown/Python | F22: ~180k | G22: 2026-10-09 | H22: Mixta (pptx/xlsx source-available) | I22: Skills oficiales de Claude (pptx, xlsx) | J22: Cómo Claude crea y valida pptx/xlsx | K22: Alta | L22: Sí | M22: 5. Presentación | N22: Skill pptx de Claude: creación y QA visual (ya disponible) | O22: Ya disponibles en esta sesión
A23: 19 | B23: Belval/pdf2image | C23: https://github.com/Belval/pdf2image | D23: PowerPoint | E23: Python | F23: ~2.0k | G23: 2024-01-07 | H23: MIT | I23: PDF a imágenes | J23: QA visual por diapositiva | K23: Alta | L23: Sí | M23: 6. Control de calidad | N23: PDF a imágenes para revisar cada diapositiva
A24: 20 | B24: LibreOffice/core | C24: https://github.com/LibreOffice/core | D24: PowerPoint | E24: C++ | F24: ~4.5k | G24: 2026-10-11 | H24: GPL/LGPL/MPL | I24: soffice headless: pptx/xlsx a PDF, recálculo | J24: QA: render del deck y recálculo del Excel | K24: Alta | L24: Sí | M24: 6. Control de calidad | N24: Convertir pptx/xlsx a PDF para revisión
A25: 21 | B25: likaku/Mck-ppt-design-skill | C25: https://github.com/likaku/Mck-ppt-design-skill | D25: PowerPoint | E25: Python | F25: ~299 | G25: 2026-05-10 | H25: Apache-2.0 | I25: Sistema de diseño estilo consultora (~70 layouts) | J25: Resumen ejecutivo, comparativas, titulares de acción | K25: Alta | L25: Sí | M25: 5. Presentación | N25: Patrones de diseño estilo consultora para gerencia
A26: 22 | B26: matplotlib/matplotlib | C26: https://github.com/matplotlib/matplotlib | D26: Riesgo | E26: Python | F26: ~23.4k | G26: 2026-09-11 (PyPI) | H26: Matplotlib (PSF) | I26: Gráficos estáticos | J26: Matriz 5×5, histograma P10/P50/P90, tornado en PNG | K26: Alta | L26: Sí | M26: 5. Presentación | N26: Matriz de riesgos 5×5 e histogramas como imagen
A27: 23 | B27: Netflix-Skunkworks/riskquant | C27: https://github.com/Netflix-Skunkworks/riskquant | D27: Riesgo | E27: Python | F27: 653 | G27: 2025-03-11 (commit) | H27: Apache-2.0 | I27: Pérdida esperada y curvas de excedencia desde CSV (lognormal/PERT) | J27: Registro de riesgos de B en dinero | K27: Alta | L27: Sí | M27: 4. Riesgo y sensibilidad | N27: Patrón para convertir el registro de riesgos en dinero
A28: 24 | B28: pyscripter/XLRisk | C28: https://github.com/pyscripter/XLRisk | D28: Riesgo | E28: VBA (complemento Excel) | F28: 147 | G28: 2025-03-19 (commit) | H28: MIT | I28: Monte Carlo gratuito en Excel (Win/Mac), Latin Hypercube, correlación Iman-Conover, gráficos | J28: Monte Carlo dentro del Excel con fórmulas vivas: P10/P50/P90 de A vs B | K28: Alta | L28: Sí | M28: 4. Riesgo y sensibilidad | N28: Opcional: que tú corras el Monte Carlo dentro de tu Excel de escritorio | O28: Requiere Excel de escritorio
A29: 25 | B29: Anexen/pyxirr | C29: https://github.com/Anexen/pyxirr | D29: Evaluación económica | E29: Rust/Python | F29: ~221 | G29: 2025-11-03 | H29: Unlicense | I29: XIRR/XNPV con fechas irregulares | J29: Flujos con fechas reales de movilización | K29: Media | L29: No
A30: 26 | B30: daniel-fink/rangekeeper | C30: https://github.com/daniel-fink/rangekeeper | D30: Evaluación económica | E30: Jupyter | F30: ~45 | G30: 2026-10-03 | H30: MPL-2.0 | I30: Modelado financiero con escenarios | J30: Estructura base/optimista/pesimista | K30: Media | L30: No
A31: 27 | B31: eikeluedeling/decisionSupport | C31: https://github.com/eikeluedeling/decisionSupport | D31: Evaluación económica | E31: R | F31: ~6 | G31: 2026-02-27 | H31: no declarada | I31: Análisis de decisiones con Monte Carlo y VOI | J31: Valor de reducir la incertidumbre de demoras | K31: Media | L31: No
A32: 28 | B32: NLRWindSystems/ORBIT | C32: https://github.com/NLRWindSystems/ORBIT | D32: Evaluación económica | E32: Python | F32: ~23 | G32: 2026-05-07 | H32: Apache-2.0 | I32: Instalación offshore: tarifa diaria, logística, clima | J32: Patrón tarifa diaria × tiempo + demoras | K32: Media | L32: No
A33: 29 | B33: pbtamarona/OpenPyTEA | C33: https://github.com/pbtamarona/OpenPyTEA | D33: Evaluación económica | E33: Jupyter | F33: ~37 | G33: 2026-10-08 | H33: MIT | I33: Evaluación tecno-económica con tornado y Monte Carlo | J33: Plantilla de encadenamiento costos → riesgo | K33: Media | L33: No
A34: 30 | B34: quatrope/scikit-criteria | C34: https://github.com/quatrope/scikit-criteria | D34: Evaluación económica | E34: Python | F34: ~105 | G34: 2026-09-01 | H34: BSD-3 | I34: MCDA sobre pandas | J34: Matriz de decisión auditable | K34: Media | L34: No
A35: 31 | B35: bradbase/xlcalculator | C35: https://github.com/bradbase/xlcalculator | D35: Excel | E35: Python | F35: ~163 | G35: 2023-02-06 (PyPI 0.5.0) | H35: MIT | I35: Traduce y evalúa fórmulas Excel; nombres definidos | J35: Verificador ligero para pruebas unitarias del modelo | K35: Media | L35: No
A36: 32 | B36: dgorissen/pycel | C36: https://github.com/dgorissen/pycel | D36: Excel | E36: Python | F36: ~632 | G36: 2021-10-13 (PyPI 1.0b30) | H36: GPL-3.0 | I36: Compila hojas de Excel a Python; grafo de dependencias | J36: Alternativa a formulas; auditoría por grafo | K36: Media | L36: No
A37: 33 | B37: ironcalc/IronCalc | C37: https://github.com/ironcalc/IronCalc | D37: Excel | E37: Rust (+Python) | F37: ~4.2k | G37: 2026-07-31 (PyPI 0.8.3) | H37: MIT/Apache-2.0 | I37: Motor de hojas de cálculo que lee, calcula y escribe xlsx | J37: Tercer motor para validar fórmulas | K37: Media | L37: No
A38: 34 | B38: na-ka-na/ExcelCompare | C38: https://github.com/na-ka-na/ExcelCompare | D38: Excel | E38: Java | F38: ~860 | G38: no visible | H38: MIT | I38: Compara celda por celda dos hojas de cálculo | J38: Regresión entre versiones del modelo | K38: Media | L38: No
A39: 35 | B39: unoconv/unoserver | C39: https://github.com/unoconv/unoserver | D39: Excel; PowerPoint | E39: Python | F39: ~939 | G39: no visible | H39: MIT | I39: LibreOffice como servidor de conversión UNO | J39: Recalcular/convertir xlsx→pdf | Conversiones más estables en iteraciones | K39: Media | L39: No
A40: 36 | B40: chinmoypaul8897/drillscribe | C40: https://github.com/chinmoypaul8897/drillscribe | D40: Oil & Gas y logística | E40: Python | F40: 1 | G40: 2026-08-08 | H40: MIT (datos CC-BY) | I40: NLP de reportes diarios (DDR) a libro de NPT | J40: Extraer duraciones históricas de moves de los DDR | K40: Media | L40: No
A41: 37 | B41: hzjken/multimodal-transportation-optimization | C41: https://github.com/hzjken/multimodal-transportation-optimization | D41: Oil & Gas y logística | E41: Python (docplex) | F41: 298 | G41: 2020-02-27 | H41: Sin licencia | I41: Minimización de costo de transporte con PE | J41: Costo fijo por viaje + distancia + tiempo | K41: Media | L41: No
A42: 38 | B42: moheavyai/truckeros | C42: https://github.com/moheavyai/truckeros | D42: Oil & Gas y logística | E42: TypeScript + OR-Tools | F42: 0 | G42: 2026-09-02 | H42: Private en README | I42: Permisos para carga extradimensionada: corredores, escoltas, ejes | J42: Checklist de rubros de B (permisos, escoltas) | K42: Media | L42: No | O42: Normativa EE. UU.
A43: 39 | B43: NatLabRockies/T3CO | C43: https://github.com/NatLabRockies/T3CO | D43: Oil & Gas y logística | E43: Python | F43: 17 | G43: 2026-09-30 | H43: BSD-3 | I43: TCO de vehículos comerciales (NREL) | J43: Costo por km de tractomula/cama baja vs tarifas | K43: Media | L43: No
A44: 40 | B44: PyVRP/PyVRP | C44: https://github.com/PyVRP/PyVRP | D44: Oil & Gas y logística | E44: Python/C++ | F44: 710 | G44: 2026-10-09 | H44: MIT | I44: Ruteo de vehículos con capacidades y ventanas | J44: Opcional: dimensionar flota de B | K44: Media | L44: No
A45: 41 | B45: shivanireddyk/tcokit | C45: https://github.com/shivanireddyk/tcokit | D45: Oil & Gas y logística | E45: Python | F45: 0 | G45: 2026-08-19 | H45: MIT | I45: TCO de camiones pesados con escenario Colombia | J45: Costo por distancia adaptable a COP/km | K45: Media | L45: No
A46: 42 | B46: son-n-pham/drillcost | C46: https://github.com/son-n-pham/drillcost | D46: Oil & Gas y logística | E46: TypeScript/React | F46: 0 | G46: 2026-08-25 | H46: MIT | I46: Comparación de escenarios de costo de perforación | J46: Patrón de lámina A vs B lado a lado | K46: Media | L46: No
A47: 43 | B47: gitbrent/PptxGenJS | C47: https://github.com/gitbrent/PptxGenJS | D47: PowerPoint | E47: JavaScript/TypeScript | F47: ~6.3k | G47: 2025-06-26 (commit) | H47: MIT | I47: PowerPoint con JS/Node, gráficos nativos, masters | J47: Alternativa Node con API de gráficos más rica | K47: Media | L47: No
A48: 44 | B48: m3dev/pptx-template | C48: https://github.com/m3dev/pptx-template | D48: PowerPoint | E48: Python | F48: ~119 | G48: 2025-12-26 | H48: Apache-2.0 | I48: pptx desde plantilla + datos JSON/CSV | J48: Regenerar el deck si cambian los supuestos | K48: Media | L48: No
A49: 45 | B49: MartinPacker/md2pptx | C49: https://github.com/MartinPacker/md2pptx | D49: PowerPoint | E49: Python | F49: ~514 | G49: 2026-08-31 | H49: MIT | I49: Markdown a PowerPoint con python-pptx | J49: Borrador rápido del deck sobre la plantilla | K49: Media | L49: No
A50: 46 | B50: microsoft/markitdown | C50: https://github.com/microsoft/markitdown | D50: PowerPoint | E50: Python | F50: ~189.6k | G50: 2026-10-04 | H50: MIT | I50: Office a Markdown | J50: Verificar que cifras del deck = Excel | K50: Media | L50: Sí | M50: 6. Control de calidad | N50: Cruzar cifras del deck contra el Excel
A51: 47 | B51: singerla/pptx-automizer | C51: https://github.com/singerla/pptx-automizer | D51: PowerPoint | E51: TypeScript | F51: ~249 | G51: 2026-09-28 | H51: MIT | I51: Rellena y combina plantillas .pptx existentes | J51: Cambiar solo datos en plantilla corporativa con gráficos ya diseñados | K51: Media | L51: No
A52: 48 | B52: Derive-Risk/pyfair | C52: https://github.com/Derive-Risk/pyfair | D52: Riesgo | E52: Python | F52: 113 | G52: 2026-05-22 (commit) | H52: MIT | I52: Monte Carlo FAIR (frecuencia × severidad) | J52: Cuantificar cada evento de riesgo de B | K52: Media | L52: No | O52: Antes Hive-Systems/pyfair
A53: 49 | B53: eggzec/mcerp | C53: https://github.com/eggzec/mcerp | D53: Riesgo | E53: Python | F53: 86 | G53: 2026-08-19 (PyPI) | H53: BSD-3-Clause | I53: Monte Carlo con variables inciertas tipo hoja de cálculo (LHS) | J53: Fórmulas de A y B con incertidumbre | K53: Media | L53: No | O53: Antes tisimst/mcerp
A54: 50 | B54: johan162/mcprojsim | C54: https://github.com/johan162/mcprojsim | D54: Riesgo | E54: Python | F54: 1 | G54: 2026-05-05 (commit) | H54: MIT | I54: Monte Carlo de cronogramas con dependencias y riesgos | J54: Duración del traslado y probabilidad de cumplir el spud | K54: Media | L54: No
A55: 51 | B55: MatthewReid854/reliability | C55: https://github.com/MatthewReid854/reliability | D55: Riesgo | E55: Python | F55: 434 | G55: 2025-03-07 (PyPI) | H55: LGPL-3.0 | I55: Ajuste Weibull/lognormal de fallas | J55: Distribuciones de tiempos históricos de traslado | K55: Media | L55: No
A56: 52 | B56: paulgovan/PRA | C56: https://github.com/paulgovan/PRA | D56: Riesgo | E56: R | F56: 4 | G56: 2026-09-21 (commit) | H56: MIT | I56: Project Risk Analysis: Monte Carlo, contingencia, sensibilidad, Bayes | J56: Referencia metodológica QCRA/QSRA | K56: Media | L56: No
A57: 53 | B57: peterhurford/squigglepy | C57: https://github.com/peterhurford/squigglepy | D57: Riesgo | E57: Python | F57: 84 | G57: 2026-06-08 (PyPI) | H57: MIT | I57: Estimación probabilística estilo Squiggle | J57: Prototipo evento de demora × standby | K57: Media | L57: No | O57: Antes rethinkpriorities/squigglepy
A58: 54 | B58: pgmpy/pgmpy | C58: https://github.com/pgmpy/pgmpy | D58: Riesgo | E58: Python | F58: ~3.4k | G58: 2026-04-30 (PyPI) | H58: MIT | I58: Redes bayesianas | J58: Cadena clima → permisos → demora → standby | K58: Media | L58: No
A59: 55 | B59: plotly/plotly.py | C59: https://github.com/plotly/plotly.py | D59: Riesgo | E59: Python | F59: ~18.8k | G59: 2026-09-15 (PyPI) | H59: MIT | I59: Gráficos interactivos exportables | J59: Tornado, spider, curva S, matriz | K59: Media | L59: No
A60: 56 | B60: pymc-devs/pymc | C60: https://github.com/pymc-devs/pymc | D60: Riesgo | E60: Python | F60: ~9.8k | G60: 2026-09-08 (PyPI) | H60: Apache-2.0 | I60: Modelado bayesiano | J60: Probabilidad de demora con históricos + juicio experto | K60: Media | L60: No
A61: 57 | B61: tadamcz/betapert | C61: https://github.com/tadamcz/betapert | D61: Riesgo | E61: Python | F61: 1 | G61: 2024-01-05 (commit) | H61: no visible | I61: Distribución Beta-PERT compatible con scipy | J61: Estimaciones de 3 puntos | K61: Media | L61: Sí | M61: 4. Riesgo y sensibilidad | N61: Distribuciones PERT de 3 puntos (mín/probable/máx)
A62: 58 | B62: ahmed-khalil-hafsi/P2Predict | C62: https://github.com/ahmed-khalil-hafsi/P2Predict | D62: Evaluación económica | E62: Python | F62: ~1 | G62: 2026-07-08 | H62: Otra | I62: Should-cost paramétrico para compras | J62: Validar tarifa lump sum vs mercado | K62: Baja | L62: No
A63: 59 | B63: AnniceNajafi/RMCDA | C63: https://github.com/AnniceNajafi/RMCDA | D63: Evaluación económica | E63: R | F63: ~8 | G63: 2026-05-01 | H63: MIT | I63: MCDA en R | J63: Solo si se usa R | K63: Baja | L63: No
A64: 60 | B64: causalincentives/pycid | C64: https://github.com/causalincentives/pycid | D64: Evaluación económica | E64: Python | F64: ~115 | G64: 2023-09-19 | H64: Apache-2.0 | I64: Diagramas de influencia | J64: Formalización avanzada | K64: Baja | L64: No
A65: 61 | B65: CWWhitney/Decision_Analysis_Course | C65: https://github.com/CWWhitney/Decision_Analysis_Course | D65: Evaluación económica | E65: HTML/R | F65: ~27 | G65: 2026-06-24 | H65: MIT | I65: Curso de análisis de decisiones (Univ. Bonn) | J65: Metodología citable | K65: Baja | L65: No
A66: 62 | B66: domokane/FinancePy | C66: https://github.com/domokane/FinancePy | D66: Evaluación económica | E66: Python | F66: ~3.2k | G66: 2026-09-30 | H66: GPL-3.0 | I66: Derivados y riesgo financiero | J66: Solo para cobertura cambiaria | K66: Baja | L66: No
A67: 63 | B67: energyinpython/pyrepo-mcda | C67: https://github.com/energyinpython/pyrepo-mcda | D67: Evaluación económica | E67: Python | F67: ~13 | G67: 2026-08-17 | H67: MIT | I67: MCDA con sensibilidad de pesos | J67: Cuánto debe cambiar un peso para invertir la decisión | K67: Baja | L67: No
A68: 64 | B68: ManosV18/managers-lab | C68: https://github.com/ManosV18/managers-lab | D68: Evaluación económica | E68: Python | F68: 0 | G68: 2026-10-04 | H68: MIT | I68: Punto de equilibrio y costos | J68: Ejemplo sencillo | K68: Baja | L68: No
A69: 65 | B69: NatLabRockies/GEOPHIRES-X | C69: https://github.com/NatLabRockies/GEOPHIRES-X | D69: Evaluación económica | E69: Python | F69: ~61 | G69: 2026-09-30 | H69: MIT | I69: Tecno-económica geotérmica con costos de perforación | J69: Referencia de economía de perforación | K69: Baja | L69: No
A70: 66 | B70: NatLabRockies/SAM | C70: https://github.com/NatLabRockies/SAM | D70: Evaluación económica | E70: C++ | F70: ~489 | G70: 2026-10-06 | H70: BSD-3 | I70: Modelos financieros de proyectos de energía | J70: Metodología de flujo de caja | K70: Baja | L70: No
A71: 67 | B71: Pegah-Ardehkhani/Multi-Criteria-Decision-Making | C71: https://github.com/Pegah-Ardehkhani/Multi-Criteria-Decision-Making | D71: Evaluación económica | E71: Jupyter | F71: ~4 | G71: 2024-12-28 | H71: MIT | I71: Notebooks didácticos MCDM | J71: Replicar AHP/TOPSIS en Excel | K71: Baja | L71: No
A72: 68 | B72: SURGroup/UQpy | C72: https://github.com/SURGroup/UQpy | D72: Evaluación económica | E72: Python | F72: ~362 | G72: 2026-08-27 | H72: MIT | I72: Cuantificación de incertidumbre general | J72: Probablemente excesivo | K72: Baja | L72: No
A73: 69 | B73: anthill/koala | C73: https://github.com/anthill/koala | D73: Excel | E73: Python | F73: ~159 | G73: 2019-06-19 | H73: GPL-3.0 | I73: Convierte cálculos de Excel a Python | J73: Solo referencia; desactualizado | K73: Baja | L73: No
... A81: 77 | B81: rhannay/pyproforma | C81: https://github.com/rhannay/pyproforma | D81: Excel | E81: Python | F81: ~2 | G81: 2026-09-13 | H81: MIT | I81: Modelado financiero en código | J81: Referencia code-first | K81: Baja | L81: No
A82: 78 | B82: SheetJS/sheetjs | C82: https://github.com/SheetJS/sheetjs | D82: Excel | E82: JavaScript | F82: ~36.3k | G82: no visible | H82: Apache-2.0 | I82: Leer/generar hojas en JS | J82: Visor web | K82: Baja | L82: No | O82: Espejo; repo vivo en git.sheetjs.com
A83: 79 | B83: stephenrauch/pycel | C83: https://github.com/stephenrauch/pycel | D83: Excel | E83: Python | F83: ~31 | G83: 2021-10-13 | H83: GPL-3.0 | I83: Fork activo de pycel publicado en PyPI | J83: Igual que pycel | K83: Baja | L83: No
A84: 80 | B84: xlwings/git-xl | C84: https://github.com/xlwings/git-xl | D84: Excel | E84: Python | F84: ~608 | G84: no visible | H84: MIT | I84: Diff de VBA en libros Excel | J84: Solo si hay macros | K84: Baja | L84: No
A85: 81 | B85: xlwings/xlwings | C85: https://github.com/xlwings/xlwings | D85: Excel | E85: Python | F85: ~3.4k | G85: 2026-09-27 (PyPI 0.37.5) | H85: BSD (PRO aparte) | I85: Puente Python-Excel; requiere Excel instalado | J85: Útil en Windows con Excel; poco en Linux | K85: Baja | L85: No
A86: 82 | B86: al-tabb/routingAPI | C86: https://github.com/al-tabb/routingAPI | D86: Oil & Gas y logística | E86: PHP | F86: n/d | G86: 2020-12-18 | H86: Sin licencia | I86: Rutas con restricción de altura y peso | J86: Idea de restricciones viales | K86: Baja | L86: No
A87: 83 | B87: aligulhalepoto309-debug/DrillWise-AI | C87: https://github.com/aligulhalepoto309-debug/DrillWise-AI | D87: Oil & Gas y logística | E87: Python | F87: n/d | G87: 2026-09-30 | H87: MIT | I87: NPT + tiempo ineficiente (ILT) | J87: Concepto ILT para flat time del move | K87: Baja | L87: No
A88: 84 | B88: amandeepsinghs-cyber/rig-management | C88: https://github.com/amandeepsinghs-cyber/rig-management | D88: Oil & Gas y logística | E88: Documentos | F88: 0 | G88: 2026-09-24 | H88: MIT (solo badge) | I88: Concepto de agente para flota de taladros, sin código | J88: Solo planteamiento | K88: Baja | L88: No
A89: 85 | B89: APMonitor/drilling | C89: https://github.com/APMonitor/drilling | D89: Oil & Gas y logística | E89: MATLAB/Python | F89: 56 | G89: 2019-12-19 | H89: MIT | I89: Modelos de procesos de perforación | J89: Marginal | K89: Baja | L89: No
A90: 86 | B90: bayuraka/well-intervention-scheduling | C90: https://github.com/bayuraka/well-intervention-scheduling | D90: Oil & Gas y logística | E90: Jupyter | F90: n/d | G90: 2026-10-06 | H90: Sin licencia | I90: Notebook original con CSV de taladros y pozos | J90: Datos de ejemplo | K90: Baja | L90: No
A91: 87 | B91: bysarmad/Well-Data-Management-and-Visualization | C91: https://github.com/bysarmad/Well-Data-Management-and-Visualization | D91: Oil & Gas y logística | E91: Python | F91: n/d | G91: 2019-05-29 | H91: Sin licencia | I91: Parser de DDR de Volve | J91: DDR públicos | K91: Baja | L91: No
A92: 88 | B92: CataBulu/FleetRoute | C92: https://github.com/CataBulu/FleetRoute | D92: Oil & Gas y logística | E92: Python + React | F92: 1 | G92: 2026-09-28 | H92: MIT | I92: Rutas de flota con horas de conducción | J92: Ventanas diurnas del convoy | K92: Baja | L92: No
A93: 89 | B93: cog-imperial/drill-scheduling | C93: https://github.com/cog-imperial/drill-scheduling | D93: Oil & Gas y logística | E93: Python (Pyomo) | F93: 0 | G93: 2021-03-09 | H93: MIT | I93: Caso académico de programación de perforación | J93: Referencia de modelado | K93: Baja | L93: No
A94: 90 | B94: Ero-Renaissance/drilling_sequence | C94: https://github.com/Ero-Renaissance/drilling_sequence | D94: Oil & Gas y logística | E94: Python + React | F94: 0 | G94: 2026-09-18 | H94: Sin licencia | I94: Secuencia de perforación con flujo de aprobación | J94: Cómo una operadora formaliza la secuencia | K94: Baja | L94: No
... A121: 117 | B121: jonathf/chaospy | C121: https://github.com/jonathf/chaospy | D121: Riesgo | E121: Python | F121: 480 | G121: 2025-08-29 (PyPI) | H121: MIT | I121: Caos polinomial y muestreo avanzado | J121: Probablemente excesivo | K121: Baja | L121: No
A122: 118 | B122: JustinTervala/ProjectPredict | C122: https://github.com/JustinTervala/ProjectPredict | D122: Riesgo | E122: Python | F122: 2 | G122: 2018-05 (PyPI) | H122: MIT | I122: Cronograma con redes bayesianas y PERT | J122: Solo referencia | K122: Baja | L122: No | O122: Sin mantenimiento
A123: 119 | B123: leliel12/pert | C123: https://github.com/leliel12/pert | D123: Riesgo | E123: Python | F123: 3 | G123: 2019-11 (PyPI) | H123: BSD-3-Clause | I123: Técnica PERT clásica | J123: Referencia simple | K123: Baja | L123: No
A124: 120 | B124: lmfit/uncertainties | C124: https://github.com/lmfit/uncertainties | D124: Riesgo | E124: Python | F124: 680 | G124: 2025-04-21 (PyPI) | H124: BSD | I124: Propagación lineal de incertidumbres | J124: Contraste con Monte Carlo | K124: Baja | L124: No
A125: 121 | B125: openturns/openturns | C125: https://github.com/openturns/openturns | D125: Riesgo | E125: C++/Python | F125: 352 | G125: 2026-06-19 (PyPI) | H125: LGPL-3.0+ | I125: Tratamiento industrial de incertidumbres, cópulas, confiabilidad | J125: Correlaciones formales | K125: Baja | L125: No
A126: 122 | B126: quantified-uncertainty/squiggle | C126: https://github.com/quantified-uncertainty/squiggle | D126: Riesgo | E126: TypeScript | F126: 221 | G126: 2026-09-13 (commit) | H126: MIT | I126: Lenguaje de estimación probabilística con playground web | J126: Demo interactiva a gerencia | K126: Baja | L126: No
A127: 123 | B127: rodmonic/Campagna | C127: https://github.com/rodmonic/Campagna | D127: Riesgo | E127: C#/Excel-DNA | F127: 0 | G127: 2024-04-09 (commit) | H127: MIT | I127: Monte Carlo para Excel (triangular, Bernoulli, Iman-Conover) | J127: Alternativa menor a XLRisk | K127: Baja | L127: No

Sheet Pila propuesta
A1: Pila de herramientas propuesta (para tu aprobación)
A2: Los datos se leen del Catálogo con fórmulas. Marca tu decisión en la hoja Catalogo, columna P.
A4: Capa | B4: Repositorio | C4: Rol en la pila | D4: Licencia | E4: Prioridad | F4: Tu decisión
A5: 1. Construir el Excel | B5: jmcnamara/XlsxWriter | C5: =INDEX(Catalogo!$N$5:$N$127,MATCH($B5,Catalogo!$B$5:$B$127,0)) -> Escribir el libro con fórmulas vivas, nombres, validaciones y gráficos nativos | D5: =INDEX(Catalogo!$H$5:$H$127,MATCH($B5,Catalogo!$B$5:$B$127,0)) -> BSD-2-Clause | E5: =INDEX(Catalogo!$K$5:$K$127,MATCH($B5,Catalogo!$B$5:$B$127,0)) -> Alta | F5: =IF(INDEX(Catalogo!$P$5:$P$127,MATCH($B5,Catalogo!$B$5:$B$127,0))="","Pendiente",INDEX(Catalogo!$P$5:$P$127,MATCH($B5,Catalogo!$B$5:$B$127,0))) -> Pendiente
A6: 1. Construir el Excel | B6: openpyxl | C6: =INDEX(Catalogo!$N$5:$N$127,MATCH($B6,Catalogo!$B$5:$B$127,0)) -> Releer, verificar y editar el libro (ya instalado) | D6: =INDEX(Catalogo!$H$5:$H$127,MATCH($B6,Catalogo!$B$5:$B$127,0)) -> MIT | E6: =INDEX(Catalogo!$K$5:$K$127,MATCH($B6,Catalogo!$B$5:$B$127,0)) -> Alta | F6: =IF(INDEX(Catalogo!$P$5:$P$127,MATCH($B6,Catalogo!$B$5:$B$127,0))="","Pendiente",INDEX(Catalogo!$P$5:$P$127,MATCH($B6,Catalogo!$B$5:$B$127,0))) -> Pendiente
A7: 2. Validar el Excel | B7: anthropics/financial-services | C7: =INDEX(Catalogo!$N$5:$N$127,MATCH($B7,Catalogo!$B$5:$B$127,0)) -> Checklist de auditoría (audit-xls) y convenciones de modelado | D7: =INDEX(Catalogo!$H$5:$H$127,MATCH($B7,Catalogo!$B$5:$B$127,0)) -> Apache-2.0 | E7: =INDEX(Catalogo!$K$5:$K$127,MATCH($B7,Catalogo!$B$5:$B$127,0)) -> Alta | F7: =IF(INDEX(Catalogo!$P$5:$P$127,MATCH($B7,Catalogo!$B$5:$B$127,0))="","Pendiente",INDEX(Catalogo!$P$5:$P$127,MATCH($B7,Catalogo!$B$5:$B$127,0))) -> Pendiente
A8: 2. Validar el Excel | B8: anthropics/skills (xlsx/recalc.py) | C8: =INDEX(Catalogo!$N$5:$N$127,MATCH($B8,Catalogo!$B$5:$B$127,0)) -> Recalcular con LibreOffice y garantizar cero errores (ya disponible) | D8: =INDEX(Catalogo!$H$5:$H$127,MATCH($B8,Catalogo!$B$5:$B$127,0)) -> Source-available | E8: =INDEX(Catalogo!$K$5:$K$127,MATCH($B8,Catalogo!$B$5:$B$127,0)) -> Alta | F8: =IF(INDEX(Catalogo!$P$5:$P$127,MATCH($B8,Catalogo!$B$5:$B$127,0))="","Pendiente",INDEX(Catalogo!$P$5:$P$127,MATCH($B8,Catalogo!$B$5:$B$127,0))) -> Pendiente
A9: 2. Validar el Excel | B9: vinci1it2000/formulas | C9: =INDEX(Catalogo!$N$5:$N$127,MATCH($B9,Catalogo!$B$5:$B$127,0)) -> Segundo motor: recalcular sin Excel y probar celdas clave | D9: =INDEX(Catalogo!$H$5:$H$127,MATCH($B9,Catalogo!$B$5:$B$127,0)) -> EUPL-1.1+ | E9: =INDEX(Catalogo!$K$5:$K$127,MATCH($B9,Catalogo!$B$5:$B$127,0)) -> Alta | F9: =IF(INDEX(Catalogo!$P$5:$P$127,MATCH($B9,Catalogo!$B$5:$B$127,0))="","Pendiente",INDEX(Catalogo!$P$5:$P$127,MATCH($B9,Catalogo!$B$5:$B$127,0))) -> Pendiente
A10: 3. Evaluación económica | B10: juansecorreapaez/RigGo | C10: =INDEX(Catalogo!$N$5:$N$127,MATCH($B10,Catalogo!$B$5:$B$127,0)) -> Estructura del inventario de cargas (solo estructura; sin licencia) | D10: =INDEX(Catalogo!$H$5:$H$127,MATCH($B10,Catalogo!$B$5:$B$127,0)) -> Sin licencia | E10: =INDEX(Catalogo!$K$5:$K$127,MATCH($B10,Catalogo!$B$5:$B$127,0)) -> Alta | F10: =IF(INDEX(Catalogo!$P$5:$P$127,MATCH($B10,Catalogo!$B$5:$B$127,0))="","Pendiente",INDEX(Catalogo!$P$5:$P$127,MATCH($B10,Catalogo!$B$5:$B$127,0))) -> Pendiente
A11: 3. Evaluación económica | B11: NLRWindSystems/LandBOSSE | C11: =INDEX(Catalogo!$N$5:$N$127,MATCH($B11,Catalogo!$B$5:$B$127,0)) -> Referencia de rubros: transporte, grúas, gestión, demoras por clima | D11: =INDEX(Catalogo!$H$5:$H$127,MATCH($B11,Catalogo!$B$5:$B$127,0)) -> Apache-2.0 | E11: =INDEX(Catalogo!$K$5:$K$127,MATCH($B11,Catalogo!$B$5:$B$127,0)) -> Alta | F11: =IF(INDEX(Catalogo!$P$5:$P$127,MATCH($B11,Catalogo!$B$5:$B$127,0))="","Pendiente",INDEX(Catalogo!$P$5:$P$127,MATCH($B11,Catalogo!$B$5:$B$127,0))) -> Pendiente
A12: 3. Evaluación económica | B12: numpy/numpy-financial | C12: =INDEX(Catalogo!$N$5:$N$127,MATCH($B12,Catalogo!$B$5:$B$127,0)) -> Verificar VPN/TIR si se usan flujos en el tiempo | D12: =INDEX(Catalogo!$H$5:$H$127,MATCH($B12,Catalogo!$B$5:$B$127,0)) -> BSD-3 | E12: =INDEX(Catalogo!$K$5:$K$127,MATCH($B12,Catalogo!$B$5:$B$127,0)) -> Alta | F12: =IF(INDEX(Catalogo!$P$5:$P$127,MATCH($B12,Catalogo!$B$5:$B$127,0))="","Pendiente",INDEX(Catalogo!$P$5:$P$127,MATCH($B12,Catalogo!$B$5:$B$127,0))) -> Pendiente
A13: 3. Evaluación económica | B13: PhilipGriffith/AHPy | C13: =INDEX(Catalogo!$N$5:$N$127,MATCH($B13,Catalogo!$B$5:$B$127,0)) -> Pesos de criterios cualitativos con consistencia (se replica en Excel) | D13: =INDEX(Catalogo!$H$5:$H$127,MATCH($B13,Catalogo!$B$5:$B$127,0)) -> MIT | E13: =INDEX(Catalogo!$K$5:$K$127,MATCH($B13,Catalogo!$B$5:$B$127,0)) -> Alta | F13: =IF(INDEX(Catalogo!$P$5:$P$127,MATCH($B13,Catalogo!$B$5:$B$127,0))="","Pendiente",INDEX(Catalogo!$P$5:$P$127,MATCH($B13,Catalogo!$B$5:$B$127,0))) -> Pendiente
A14: 3. Evaluación económica | B14: praveen-christuraj/Well-Costing | C14: =INDEX(Catalogo!$N$5:$N$127,MATCH($B14,Catalogo!$B$5:$B$127,0)) -> Estructura de rate card hora/día/único (solo estructura; sin licencia) | D14: =INDEX(Catalogo!$H$5:$H$127,MATCH($B14,Catalogo!$B$5:$B$127,0)) -> Sin licencia | E14: =INDEX(Catalogo!$K$5:$K$127,MATCH($B14,Catalogo!$B$5:$B$127,0)) -> Alta | F14: =IF(INDEX(Catalogo!$P$5:$P$127,MATCH($B14,Catalogo!$B$5:$B$127,0))="","Pendiente",INDEX(Catalogo!$P$5:$P$127,MATCH($B14,Catalogo!$B$5:$B$127,0))) -> Pendiente
A15: 4. Riesgo y sensibilidad | B15: Netflix-Skunkworks/riskquant | C15: =INDEX(Catalogo!$N$5:$N$127,MATCH($B15,Catalogo!$B$5:$B$127,0)) -> Patrón para convertir el registro de riesgos en dinero | D15: =INDEX(Catalogo!$H$5:$H$127,MATCH($B15,Catalogo!$B$5:$B$127,0)) -> Apache-2.0 | E15: =INDEX(Catalogo!$K$5:$K$127,MATCH($B15,Catalogo!$B$5:$B$127,0)) -> Alta | F15: =IF(INDEX(Catalogo!$P$5:$P$127,MATCH($B15,Catalogo!$B$5:$B$127,0))="","Pendiente",INDEX(Catalogo!$P$5:$P$127,MATCH($B15,Catalogo!$B$5:$B$127,0))) -> Pendiente
A16: 4. Riesgo y sensibilidad | B16: pyscripter/XLRisk | C16: =INDEX(Catalogo!$N$5:$N$127,MATCH($B16,Catalogo!$B$5:$B$127,0)) -> Opcional: que tú corras el Monte Carlo dentro de tu Excel de escritorio | D16: =INDEX(Catalogo!$H$5:$H$127,MATCH($B16,Catalogo!$B$5:$B$127,0)) -> MIT | E16: =INDEX(Catalogo!$K$5:$K$127,MATCH($B16,Catalogo!$B$5:$B$127,0)) -> Alta | F16: =IF(INDEX(Catalogo!$P$5:$P$127,MATCH($B16,Catalogo!$B$5:$B$127,0))="","Pendiente",INDEX(Catalogo!$P$5:$P$127,MATCH($B16,Catalogo!$B$5:$B$127,0))) -> Pendiente
... A26: 6. Control de calidad | B26: microsoft/markitdown | C26: =INDEX(Catalogo!$N$5:$N$127,MATCH($B26,Catalogo!$B$5:$B$127,0)) -> Cruzar cifras del deck contra el Excel | D26: =INDEX(Catalogo!$H$5:$H$127,MATCH($B26,Catalogo!$B$5:$B$127,0)) -> MIT | E26: =INDEX(Catalogo!$K$5:$K$127,MATCH($B26,Catalogo!$B$5:$B$127,0)) -> Media | F26: =IF(INDEX(Catalogo!$P$5:$P$127,MATCH($B26,Catalogo!$B$5:$B$127,0))="","Pendiente",INDEX(Catalogo!$P$5:$P$127,MATCH($B26,Catalogo!$B$5:$B$127,0))) -> Pendiente
