Workbook

Sheet Resumen
B1: Movilización del taladro GRS 110 en La Cira Infantas: Work Order frente a modelo tercerizado
B2: Evaluación para decidir si se mantiene el Work Order o se contrata directamente al transportador. No es un proceso de adjudicación.
B5: 1. QUÉ SE EVALUÓ
B6: Dos formas de pagar las movilizaciones del taladro GRS 110. Work Order (modelo directo): el contratista del taladro cobra una suma global por movilización según la distancia, con tarifa tope, y no se pagan horas de taladro. Modelo tercerizado: SierraCol contrata al transportador y paga además el taladro por cada hora que dura la movilización y un coordinador de transporte (Truck Manager).
B7: Ofertas evaluadas: Petro Star tarifa normal, Petro Star Lump Sum (precio cerrado) y Ecotransur. MTI y Transtecol quedan por fuera porque sus tarifas no se actualizaron a julio de 2026.
B9: 2. ARCHIVO DE TRABAJO Y FUENTES
B10: Este libro es el archivo de trabajo del ejercicio. Las hojas Simulador, Real 2024 y Real 2025 calculan con fórmulas; las demás documentan y verifican.
B11: Fuente | C11: Qué se tomó de ella
B12: Tarifas con evaluaciones minimas.xlsx | C12: Tarifas de las tres ofertas (filas amarillas 'Costo Suma Global'), TRM, tarifa del taladro, horas por rango y Truck Manager.
B13: Cotización 1255 de Petro Star (17-jul-2026) | C13: Tiempos por rango, descuento desde la 6ª, cargo fijo de 0 a 5 movilizaciones, tarifas por hora de equipos y señalizadores, condición 7 sobre demoras.
B14: Ajuste de tarifas de Ecotransur (27-jul-2026) | C14: Nómina y stand-by de 0 a 4 movilizaciones, sin cargo fijo desde la 5ª, solo equipos desde la 6ª.
B15: Movilizaciones 2024 y 2025 (GRS 110) | C15: Frecuencia mensual, mezcla por distancia y horas reales de cada movilización.
B16: Evaluación SierraCol v5, hoja NPT Social 2025 | C16: Bloqueos registrados en OpenWells durante la fase de movilización (01MIRU).
B17: Premisas de SierraCol | C17: Tarifas WO y sus 12 señalizadoras, campaña de 35 pozos, 5 a 6 movilizaciones por mes, TRM 3.700, costo de pozo 600 k.
B19: 3. CONSIDERACIONES DEL EJERCICIO
B20: 1. Campaña proyectada: 35 pozos, 15 en la misma localización y 20 entre 0,1 y 5 km. Frecuencia esperada de 5 a 6 movilizaciones por mes; se analiza de 4 a 8.
B21: 2. Las movilizaciones se asignan a meses enteros. El número de la movilización dentro del mes define si hay cargo fijo (hasta la 5ª en Petro Star, hasta la 4ª en Ecotransur) y si hay descuento (desde la 6ª).
B22: 3. Work Order: tarifa del Excel por rango más 8 señalizadoras que faltan (4 por turno a 375.000 COP). Esa tarifa es el tope: si la movilización tarda más, el WO paga una tarifa menor. Se compara contra el WO más caro posible.
B23: 4. Tercerizado: tarifa del transportador + taladro a 1.456 USD/h por las horas de cada rango (12/18/24/28 h) + Truck Manager de 60 M COP por mes de campaña.
B24: 5. Si una movilización supera el tiempo cotizado (12/24/36/36 h) se paga el taladro por esas horas y además equipos y señalizadores por hora: unos 2.813 USD por hora en total. El WO no paga nada extra.
B25: 6. Bloqueos sociales y escolares durante movilizaciones: 22,25 h en 45 movilizaciones de 2025 (OpenWells, fase de movilización), es decir 22,25 × 35/45 = 17,3 h en una campaña de 35 pozos. En el tercerizado los paga SierraCol (condición 7 de la cotización 1255); en el WO no.
B26: 7. Petro Star normal: 50 % de descuento sobre su tarifa desde la 6ª movilización del mes. Lump Sum: sin descuento en la evaluación principal. Ecotransur: desde la 6ª solo cobra equipos.
B27: 8. Un mes sin poder mover con el contrato vigente paga el cargo fijo completo más el Truck Manager (Petro Star 177 k, Ecotransur 243 k). El fin de la campaña termina el contrato y no genera cobro.
B28: 9. Imprevistos y cobros adicionales: 0 % en ambos modelos (se asume que se compensan). TRM fija en 3.700. Sin IVA.
B29: 10. Las campañas reales de 2024 y 2025 se repiten movilización por movilización con las tarifas de julio de 2026 y las horas reales del log.
B31: 4. RESULTADOS (USD; ahorro = costo WO − costo tercerizado; positivo = el tercerizado cuesta menos)
B32: Escenario | C32: Petro Star tarifa normal (USD) | D32: Ecotransur (USD) | E32: Petro Star Lump Sum (USD) | F32: Nota
B33: Campaña proyectada, 5 movs/mes | C33: 132152.06 | D33: 490519.35 | E33: -472796.26 | F33: Valor fijo (no cambia al editar el Simulador). Ver Sensibilidad, sección 1.
B34: Campaña proyectada, 6 movs/mes | C34: 521560.55 | D34: 584485.57 | E34: -210864.81 | F34: Valor fijo (no cambia al editar el Simulador).
B35: Escenario cargado hoy en el Simulador | C35: =Simulador!D84 -> 132152.06 | D35: =Simulador!D87 -> 490519.35 | E35: =Simulador!D85 -> -472796.26 | F35: Enlace vivo: cambia al editar el Simulador.
B36: Campaña real 2025, horas reales | C36: ='Real 2025'!AA5 -> -70829.783 | D36: ='Real 2025'!AA8 -> -79162.904 | E36: ='Real 2025'!AA6 -> -1448687.2 | F36: Enlace vivo. Incluye equipos por horas excedidas.
B37: Campaña real 2024, horas reales | C37: ='Real 2024'!AA5 -> 1136023.3 | D37: ='Real 2024'!AA8 -> 996624.87 | E37: ='Real 2024'!AA6 -> -973152.06 | F37: Enlace vivo.
B38: En una campaña de 35 pozos (≈ 21 M USD a 600 k por pozo) el ahorro posible va de +0,13 M a +0,58 M: entre 4 k y 17 k por pozo, menos del 3 % del costo del pozo.
B40: 5. VENTAJAS Y DESVENTAJAS DE CADA MODELO
B41: Aspecto | C41: Work Order (directo) | E41: Tercerizado
B42: Costo por movilización | C42: Más alto por movilización. | E42: Más bajo por movilización, solo si se cumplen los tiempos y el mes llega a 5–6 movilizaciones.
B43: Demoras en la movilización | C43: Las absorbe el contratista: la tarifa tiene tope. | E43: Las paga SierraCol: taladro + equipos ≈ 2.813 USD por hora.
B44: Meses con pocas movilizaciones | C44: Sin costo fijo: se paga solo lo que se mueve. | E44: Cargo fijo de nómina y equipos hasta la 5ª movilización (Petro Star) o la 4ª (Ecotransur); descuento desde la 6ª.
B45: Bloqueos sociales o problemas operativos | C45: Sin costo adicional. | E45: Los paga SierraCol (condición 7); un mes sin mover cuesta 177 k (Petro Star) o 243 k (Ecotransur), con el Truck Manager.
B46: Gestión | C46: Un solo contratista responde por todo. | E46: Dos contratistas más el Truck Manager: la coordinación, la seguridad (HSE), las pólizas y la disponibilidad quedan a cargo de SierraCol.
B47: Control y flexibilidad | C47: Menos control directo sobre el transportador. | E47: Control directo de la flota y de los tiempos; se pueden negociar topes y penalidades.
B48: Previsibilidad del presupuesto | C48: Alta: costo cerrado por movilización. | E48: Baja: depende de las movilizaciones de cada mes y de las horas reales.
B50: 6. CONCLUSIÓN
B51: • El tercerizado solo ahorra si la campaña sostiene 5 a 6 movilizaciones todos los meses y cada movilización cumple el tiempo cotizado. En ese caso el ahorro de la campaña es de +0,13 M a +0,52 M con Petro Star normal y de +0,49 M a +0,58 M con Ecotransur.
B52: • El margen es delgado. Con 5 movilizaciones por mes, Petro Star pierde la ventaja con 1,3 h de más por movilización sobre el tiempo cotizado o con un mes bloqueado; Ecotransur aguanta 5,0 h o 2,0 meses bloqueados.
B53: • La campaña real de 2025 (45 movilizaciones, 3 meses por debajo de 5) habría costado más con el tercerizado: Petro Star −71 k, Ecotransur −79 k. En 2024, con 9 de 11 meses en 6 o más y movilizaciones más rápidas, habría ahorrado +1,14 M y +1,00 M.
B54: • El Lump Sum de Petro Star pierde en todos los escenarios con los precios del Excel.
B55: • La diferencia de fondo es el riesgo: el Work Order tiene tarifa tope y absorbe demoras, bloqueos y meses lentos; el tercerizado traslada todo eso a SierraCol.
B57: 7. RECOMENDACIÓN
B58: Mantener el Work Order.
B59: Volver a evaluar el tercerizado solo si se cumplen tres condiciones: (1) un plan de pozos que asegure 6 o más movilizaciones todos los meses; (2) un contrato con tope de horas o penalidad al transportador por exceder el tiempo cotizado; (3) una cláusula que suspenda el cargo fijo en meses con bloqueos o problemas operativos.
B60: Antes de cualquier negociación: Compras (SCM) debe aclarar los precios del Lump Sum, porque los del Excel están por encima de la cotización 1255, y Petro Star debe confirmar si cobra cargo fijo con 5 movilizaciones (si no lo cobra, su ahorro sube unos 0,29 M con 5 movs/mes).
B62: 8. HOJAS DE ESTE LIBRO
B63: Hoja | C63: Contenido
B64: Resumen | C64: Esta hoja.
B65: Gráficas | C65: Gráficos del ejercicio, con sus datos.
B66: Simulador | C66: Modelo editable: parámetros, costo por movilización, cargos fijos, frontera y campaña mes a mes.
B67: Método | C67: Cómo se clasifica cada costo, qué se cancela entre modelos y cómo entra el NPT.
B68: Real 2024 / Real 2025 | C68: Las campañas reales repetidas con cada modelo.
B69: Reconciliación | C69: De dónde sale cada parámetro y control contra la fuente.
B70: Medido y supuesto | C70: Qué es dato y qué es supuesto.
B71: Sensibilidad | C71: Frecuencia de 4 a 8, puntos de quiebre, horas reales y tornado.
B72: Pendientes | C72: Lo que falta confirmar y cuánto está en juego.
B73: Verificación Excel | C73: Revisión línea por línea del archivo de tarifas.

Sheet Gráficas
B1: Gráficas del ejercicio
B2: Cada gráfico se alimenta de la tabla que tiene al lado. Las tablas en verde están enlazadas al Simulador o a las hojas Real; la de frecuencias es fija (motor de cálculo).
B4: 1. AHORRO DE LA CAMPAÑA DE 35 POZOS SEGÚN MOVILIZACIONES POR MES
B5: Movs/mes | C5: Petro Star tarifa normal | D5: Ecotransur | E5: Petro Star Lump Sum
B6: 4 | C6: -135092.52 | D6: 5451.8713 | E6: -740040.84
B7: 4,5 | C7: -2580.4417 | D7: 247985.61 | E7: -607528.76
B8: 5 | C8: 132152.06 | D8: 490519.35 | E8: -472796.26
B9: 5,5 | C9: 279484.05 | D9: 405025.86 | E9: -404125.29
B10: 6 | C10: 521560.55 | D10: 584485.57 | E10: -210864.81
B11: 6,5 | C11: 541571.5 | D11: 521411.53 | E11: -239669.88
B12: 7 | C12: 695332.35 | D12: 660216.65 | E12: -153696.06
B13: 8 | C13: 696138.76 | D13: 633612.89 | E13: -223453.67
B14: Con frecuencias no enteras se alternan meses; el último mes de la campaña puede quedar corto y pagar cargo fijo.
B24: 2. COSTO DE UNA MOVILIZACIÓN DE 0,1–5 km (USD, enlazado al Simulador)
B25: Concepto | C25: Tarifa | D25: Señalizadoras (WO) | E25: Taladro | F25: Truck Manager por movilización (60 M COP / movs del mes)
B26: Work Order | C26: =Simulador!D51-Simulador!D50 -> 98663 | D26: =Simulador!D50 -> 810.81081 | E26: 0 | F26: 0
B27: Petro Star 1ª–5ª | C27: =Simulador!D55 -> 59690.023 | D27: 0 | E27: =Simulador!D53 -> 26208 | F27: =IF(Simulador!$C$16="Mensual fijo",Simulador!$C$14/Simulador!$C$7/Simulador!$C$32,Simulador!$D$54) -> 3243.2432
B28: Petro Star 6ª+ | C28: =Simulador!D56 -> 29845.011 | D28: 0 | E28: =Simulador!D53 -> 26208 | F28: =IF(Simulador!$C$16="Mensual fijo",Simulador!$C$14/Simulador!$C$7/Simulador!$C$32,Simulador!$D$54) -> 3243.2432
B29: Ecotransur 1ª–5ª | C29: =Simulador!D59 -> 56135.946 | D29: 0 | E29: =Simulador!D53 -> 26208 | F29: =IF(Simulador!$C$16="Mensual fijo",Simulador!$C$14/Simulador!$C$7/Simulador!$C$32,Simulador!$D$54) -> 3243.2432
B30: Ecotransur 6ª+ | C30: =Simulador!D60 -> 33291.892 | D30: 0 | E30: =Simulador!D53 -> 26208 | F30: =IF(Simulador!$C$16="Mensual fijo",Simulador!$C$14/Simulador!$C$7/Simulador!$C$32,Simulador!$D$54) -> 3243.2432
B31: Lump Sum | C31: =Simulador!D57 -> 82239.105 | D31: 0 | E31: =Simulador!D53 -> 26208 | F31: =IF(Simulador!$C$16="Mensual fijo",Simulador!$C$14/Simulador!$C$7/Simulador!$C$32,Simulador!$D$54) -> 3243.2432
B44: 3. CAMPAÑA REAL 2025: AHORRO MES A MES CON HORAS REALES (USD, enlazado a Real 2025)
B45: Mes | C45: Movilizaciones | D45: Ahorro Petro Star tarifa normal (USD) | E45: Ahorro Ecotransur (USD)
B46: ='Real 2025'!K59 -> Feb | C46: ='Real 2025'!C59 -> 1 | D46: ='Real 2025'!P59 -> -225526.14 | E46: ='Real 2025'!Q59 -> -274611.91
B47: ='Real 2025'!K60 -> Mar | C47: ='Real 2025'!C60 -> 4 | D47: ='Real 2025'!P60 -> -62484.189 | E47: ='Real 2025'!Q60 -> -45916.027
B48: ='Real 2025'!K61 -> Abr | C48: ='Real 2025'!C61 -> 7 | D48: ='Real 2025'!P61 -> 108428.43 | E48: ='Real 2025'!Q61 -> 93105.254
B49: ='Real 2025'!K62 -> May | C49: ='Real 2025'!C62 -> 5 | D49: ='Real 2025'!P62 -> -84020.254 | E49: ='Real 2025'!Q62 -> -38102.786
B50: ='Real 2025'!K63 -> Jun | C50: ='Real 2025'!C63 -> 6 | D50: ='Real 2025'!P63 -> 94505.536 | E50: ='Real 2025'!Q63 -> 90516.126
B51: ='Real 2025'!K64 -> Jul | C51: ='Real 2025'!C64 -> 7 | D51: ='Real 2025'!P64 -> 91480.134 | E51: ='Real 2025'!Q64 -> 82316.943
B52: ='Real 2025'!K65 -> Ago | C52: ='Real 2025'!C65 -> 7 | D52: ='Real 2025'!P65 -> 78794.696 | E52: ='Real 2025'!Q65 -> 61024.322
B53: ='Real 2025'!K66 -> Sep | C53: ='Real 2025'!C66 -> 5 | D53: ='Real 2025'!P66 -> -4050.9332 | E53: ='Real 2025'!Q66 -> 35906.457
B54: ='Real 2025'!K67 -> Oct | C54: ='Real 2025'!C67 -> 3 | D54: ='Real 2025'!P67 -> -67957.062 | E54: ='Real 2025'!Q67 -> -83401.281
B64: 4. CAMPAÑA REAL 2024: AHORRO MES A MES CON HORAS REALES (USD, enlazado a Real 2024)
B65: Mes | C65: Movilizaciones | D65: Ahorro Petro Star tarifa normal (USD) | E65: Ahorro Ecotransur (USD)
B66: ='Real 2024'!K84 -> Ene | C66: ='Real 2024'!C84 -> 7 | D66: ='Real 2024'!P84 -> 140701.01 | E66: ='Real 2024'!Q84 -> 144343.27
B67: ='Real 2024'!K85 -> Feb | C67: ='Real 2024'!C85 -> 8 | D67: ='Real 2024'!P85 -> 203847.22 | E67: ='Real 2024'!Q85 -> 189864.32
B68: ='Real 2024'!K86 -> Mar | C68: ='Real 2024'!C86 -> 7 | D68: ='Real 2024'!P86 -> 40100.066 | E68: ='Real 2024'!Q86 -> 38540.747
B69: ='Real 2024'!K87 -> Abr | C69: ='Real 2024'!C87 -> 7 | D69: ='Real 2024'!P87 -> 128726.01 | E69: ='Real 2024'!Q87 -> 121387
B70: ='Real 2024'!K88 -> May | C70: ='Real 2024'!C88 -> 7 | D70: ='Real 2024'!P88 -> 139053.46 | E70: ='Real 2024'!Q88 -> 125627.6
B71: ='Real 2024'!K89 -> Jun | C71: ='Real 2024'!C89 -> 9 | D71: ='Real 2024'!P89 -> 221429.57 | E71: ='Real 2024'!Q89 -> 190235.94
B72: ='Real 2024'!K90 -> Jul | C72: ='Real 2024'!C90 -> 7 | D72: ='Real 2024'!P90 -> 187727.53 | E72: ='Real 2024'!Q90 -> 170482.91
B73: ='Real 2024'!K91 -> Ago | C73: ='Real 2024'!C91 -> 3 | D73: ='Real 2024'!P91 -> -53437.506 | E73: ='Real 2024'!Q91 -> -78797.328
B74: ='Real 2024'!K92 -> Sep | C74: ='Real 2024'!C92 -> 6 | D74: ='Real 2024'!P92 -> 78937.215 | E74: ='Real 2024'!Q92 -> 73429.511
B75: ='Real 2024'!K93 -> Oct | C75: ='Real 2024'!C93 -> 6 | D75: ='Real 2024'!P93 -> 96773.59 | E75: ='Real 2024'!Q93 -> 85855.7
B76: ='Real 2024'!K94 -> Nov | C76: ='Real 2024'!C94 -> 3 | D76: ='Real 2024'!P94 -> -47834.899 | E76: ='Real 2024'!Q94 -> -64344.795
B84: 5. MESES SEGÚN CUÁNTAS MOVILIZACIONES TUVIERON (logs)
B85: Movilizaciones en el mes | C85: Meses 2024 | D85: Meses 2025
B86: 1 a 3 | C86: =COUNTIFS('Real 2024'!$C$84:$C$94,"<=3") -> 2 | D86: =COUNTIFS('Real 2025'!$C$59:$C$67,"<=3") -> 2
B87: 4 | C87: =COUNTIFS('Real 2024'!$C$84:$C$94,"=4") -> 0 | D87: =COUNTIFS('Real 2025'!$C$59:$C$67,"=4") -> 1
B88: 5 | C88: =COUNTIFS('Real 2024'!$C$84:$C$94,"=5") -> 0 | D88: =COUNTIFS('Real 2025'!$C$59:$C$67,"=5") -> 2
B89: 6 o más | C89: =COUNTIFS('Real 2024'!$C$84:$C$94,">=6") -> 9 | D89: =COUNTIFS('Real 2025'!$C$59:$C$67,">=6") -> 4
B91: Petro Star cobra cargo fijo hasta la 5ª movilización del mes y Ecotransur hasta la 4ª; desde la 6ª Petro Star descuenta el 50 % y Ecotransur cobra solo equipos.

Sheet Simulador
B1: Simulador de movilización del taladro GRS 110 · La Cira Infantas
B2: Work Order (suma global por movilización) frente a modelo tercerizado (transportador + taladro por hora + Truck Manager). Todo en USD salvo donde dice COP.
B3: Cómo leerlo: azul = dato editable · fondo amarillo = supuesto clave a confirmar · verde = viene de otra hoja · negro = cálculo. Ahorro positivo = el tercerizado cuesta menos que el Work Order.
B5: 1. PARÁMETROS GENERALES | K5: 1b. HORAS EXCEDIDAS, BLOQUEOS, TOPE DEL WO Y COSTO DEL POZO
B6: Variable | C6: Valor | D6: Unidad | E6: Clase | F6: Fuente | K6: Variable | N6: Valor
B7: TRM | C7: 3700 | D7: COP/USD | E7: Premisa SierraCol | F7: Tarifas.xlsx · E3 (fija para el ejercicio) | K7: ¿Se cobran equipos y señalizadores por hora por encima del tiempo estipulado? (Cot. 1255 p. 5) | N7: Sí
B8: Tarifa del taladro (24 h) | C8: 34944 | D8: USD/día | E8: Medido | F8: Tarifas.xlsx · E5 | K8: Señalizadores por hora excedida: 20 × 54.375 COP (Cot. 1255 p. 5) | N8: 1087500
B9: Tarifa del taladro por hora | C9: =C8/24 -> 1456 | D9: USD/h | E9: Cálculo | F9: Tarifas.xlsx · E6 (= E5/24) | K9: Meses bloqueados en la campaña (no se puede mover; contrato vigente) | N9: 0
B10: Oferta que se muestra en la fila 88 (solo detalle) | C10: Petro Star tarifa normal | E10: Selección | F10: Lista: las 3 ofertas (Lump Sum con y sin descuento) | K10: Ajuste a la tarifa WO (%) · las del Excel son el TOPE (movilización rápida); si tarda más paga una tarifa fija menor: solo 0 o negativo | N10: 0
B11: Adicionales sobre tarifa base (Petro Star normal y Ecotransur) | C11: 0 | D11: % | E11: Premisa SierraCol | F11: Tarifas.xlsx · E7. Se cancela con el WO; ver Pendientes | K11: Costo de un pozo en La Cira Infantas, solo perforación (USD) · SierraCol: 550–650 k | N11: 600000
B12: Adicionales sobre Lump Sum | C12: 0 | D12: % | E12: Premisa SierraCol | F12: Tarifas.xlsx · E8 | K12: Horas de bloqueo social o escolar durante movilizaciones en la campaña (OpenWells 2025: 22,25 h en 45 movilizaciones; se escala al número de pozos: 22,25 × pozos / 45) | N12: =22.25*C30/45 -> 17.305556
B13: Adicionales sobre Work Order | C13: 0 | D13: % | E13: Premisa SierraCol | F13: Simetría: los imprevistos también se pagan en el WO
B14: Truck Manager: valor mensual | C14: 60000000 | D14: COP/mes | E14: Medido | F14: Tarifas.xlsx · C29 = (60.000.000/E3)/6
B15: Truck Manager: movilizaciones/mes con que se prorratea | C15: 6 | D15: movs/mes | E15: Medido (fórmula Excel) | F15: Tarifas.xlsx · C29
B16: Truck Manager: forma de cobro | C16: Mensual fijo | E16: Premisa SierraCol | F16: Mensual fijo = 60 M COP por cada mes de campaña (criterio de la evaluación SierraCol v5). Por movilización = 2.702,70 USD (Excel C29)
B17: Descuento Petro Star tarifa normal desde la 6ª del mes | C17: 0.5 | D17: % | E17: Medido | F17: Cot. 1255 p. 2: '50% de cada escenario'
B18: Descuento Lump Sum (solo para la columna de referencia) | C18: 0.5 | D18: % | E18: Referencia aparte | F18: Evaluación principal: Lump Sum SIN descuento (SierraCol). Esta columna se muestra aparte
B19: Movilización del mes desde la que aplica el descuento | C19: 6 | D19: nº | E19: Medido | F19: Cot. 1255 p. 2 · Ecotransur p. 3–4
B20: Señalizadoras que faltan en el WO, por turno | C20: 4 | D20: personas | E20: Premisa SierraCol | F20: Ofertas: 10 por turno · WO: 6 por turno (dato SierraCol)
B21: Tarifa señalizador vial, turno 12 h | C21: 375000 | D21: COP/persona | E21: Medido | F21: Cot. 1255 p. 5, fila Señalizador vial, columna Turno 12 horas
B22: ¿Cargar el recargo de señalizadoras al Work Order? | C22: Sí | E22: Decisión de modelo | F22: Aplica a toda movilización: misma loc. 1 turno, demás rangos 2 turnos
B23: Reducción de la frecuencia por tiempo no productivo (NPT) de perforación | C23: 0 | D23: % | E23: Supuesto (sin dato) | F23: No hay plan de pozos ni NPT operativo en los archivos: se deja en 0 y se sensibiliza
B25: 2. CAMPAÑA A EVALUAR
B26: Variable | C26: Valor | D26: Unidad | E26: Clase | F26: Fuente
B27: Pozos en la misma localización | C27: 15 | D27: pozos | E27: Premisa SierraCol | F27: Proyección de campaña entregada por SierraCol
B28: Pozos en otra localización | C28: 20 | D28: pozos | E28: Premisa SierraCol | F28: Proyección de campaña entregada por SierraCol
B29: Rango de los pozos en otra localización (2 = 0,1–5 km · 3 = 5–10 km · 4 = más de 10 km) | C29: 2 | D29: =INDEX({"Misma localización","0,1–5 km","5–10 km","Más de 10 km"},C29) -> 0,1–5 km | E29: Premisa SierraCol | F29: Confirmado por SierraCol: 0,1–5 km
B30: Total de pozos (movilizaciones) | C30: =C27+C28 -> 35 | D30: pozos | E30: Cálculo | F30: Máximo 60 en la tabla de detalle
B31: Frecuencia mensual | C31: Constante | E31: Premisa SierraCol | F31: Esperado: 5 a 6 movs/mes (SierraCol). Perfil 2024 / Perfil 2025 = meses reales de los logs
B32: Movilizaciones por mes si la frecuencia es constante | C32: 5 | D32: movs/mes | E32: Premisa SierraCol | F32: Rango esperado 5–6; ver Sensibilidad (4 a 8)
B33: Perfil 2024: movilizaciones por mes (ene–nov, log) | C33: 7 | D33: 8 | E33: 7 | F33: 7 | G33: 7 | H33: 9 | I33: 7 | J33: 3 | K33: 6 | L33: 6 | M33: 3
B34: Perfil 2025: movilizaciones por mes (feb–oct, log) | C34: 1 | D34: 4 | E34: 7 | F34: 5 | G34: 6 | H34: 7 | I34: 7 | J34: 5 | K34: 3
B35: Los perfiles salen de Movilizaciones_2024.xlsx (C11:C21) y Movilizaciones_2025.xlsx (C11:C19). Los meses sin registro se tratan como campaña parada (premisa SierraCol) y no entran.
B37: 3. TARIFAS Y COSTO POR MOVILIZACIÓN, POR RANGO DE DISTANCIA
B38: Concepto | C38: Misma localización | D38: 0,1–5 km | E38: 5–10 km | F38: Más de 10 km | G38: Clase | H38: Fuente
B39: Horas de movilización que se le pagan al taladro (tercerizado) | C39: 12 | D39: 18 | E39: 24 | F39: 28 | G39: Dato del Excel | H39: Tarifas.xlsx · C26, C52, C78, C104
B40: Horas extra por movilización (NPT de movilización) | C40: 0 | D40: 0 | E40: 0 | F40: 0 | G40: Supuesto | H40: Logs: ver hojas Real 2024 / Real 2025
B41: Tiempo estipulado por el transportador (h): por encima se cobran equipos y señalizadores por hora | C41: 12 | D41: 24 | E41: 36 | F41: 36 | G41: Medido · Ecotransur = supuesto | H41: Cot. 1255 p. 1–2 'Tiempo total' y p. 5 (Ecotransur no declara tiempos)
B42: Turnos de señalizadoras por movilización | C42: 1 | D42: 2 | E42: 2 | F42: 2 | G42: Premisa SierraCol | H42: 12 h = 1 turno; 18/24/28 h = 2 turnos
B43: Work Order base (USD por movilización) | C43: 75642 | D43: 98663 | E43: 95374 | F43: 110174 | G43: Premisa SierraCol | H43: Tarifas.xlsx · K4:K7 (dato SierraCol)
B44: Tarifa Petro Star normal (COP) | C44: 140385441 | D44: 220853084 | E44: 238462998 | F44: 246462998 | G44: Medido | H44: Tarifas.xlsx · E25, E51, E77, E103
B45: Tarifa Petro Star Lump Sum (COP) | C45: 178363885 | D45: 304284690 | E45: 373649874 | F45: 414800928 | G45: Medido | H45: Tarifas.xlsx · F25, F51, F77, F103 (≠ Cot. 1255: ver Pendientes)
B46: Tarifa Ecotransur (COP) | C46: 140233002 | D46: 207703002 | E46: 249003002 | F46: 253060002 | G46: Medido | H46: Tarifas.xlsx · G25, G51, G77, G103
B47: Ecotransur desde la 6ª: solo equipos (COP) | C47: 123180000 | D47: 123180000 | E47: 139005000 | F47: 167055000 | G47: Medido · misma loc. = supuesto | H47: Ecotransur p. 3–4 (no trae valor para misma localización)
B49: Work Order (USD por movilización)
B50: Recargo de señalizadoras faltantes | C50: =IF($C$22="Sí",$C$20*$C$21*C42/$C$7,0) -> 405.40541 | D50: =IF($C$22="Sí",$C$20*$C$21*D42/$C$7,0) -> 810.81081 | E50: =IF($C$22="Sí",$C$20*$C$21*E42/$C$7,0) -> 810.81081 | F50: =IF($C$22="Sí",$C$20*$C$21*F42/$C$7,0) -> 810.81081 | G50: Personas por turno × tarifa turno × turnos / TRM
B51: Work Order total por movilización | C51: =C43*(1+$C$13+$N$10)+C50 -> 76047.405 | D51: =D43*(1+$C$13+$N$10)+D50 -> 99473.811 | E51: =E43*(1+$C$13+$N$10)+E50 -> 96184.811 | F51: =F43*(1+$C$13+$N$10)+F50 -> 110984.81
B52: Tercerizado (USD por movilización)
B53: Taladro durante la movilización | C53: =(C39+C40)*$C$9 -> 17472 | D53: =(D39+D40)*$C$9 -> 26208 | E53: =(E39+E40)*$C$9 -> 34944 | F53: =(F39+F40)*$C$9 -> 40768 | G53: (Horas + horas extra) × tarifa por hora
B54: Truck Manager por movilización | C54: =IF($C$16="Mensual fijo",0,$C$14/$C$7/$C$15) -> 0 | D54: =IF($C$16="Mensual fijo",0,$C$14/$C$7/$C$15) -> 0 | E54: =IF($C$16="Mensual fijo",0,$C$14/$C$7/$C$15) -> 0 | F54: =IF($C$16="Mensual fijo",0,$C$14/$C$7/$C$15) -> 0 | G54: Si es mensual fijo vale 0 aquí y se suma por mes (sección 7)
B55: Petro Star normal: tarifa, 1ª a 5ª del mes | C55: =C44/$C$7*(1+$C$11) -> 37942.011 | D55: =D44/$C$7*(1+$C$11) -> 59690.023 | E55: =E44/$C$7*(1+$C$11) -> 64449.459 | F55: =F44/$C$7*(1+$C$11) -> 66611.621
B56: Petro Star normal: tarifa, 6ª en adelante | C56: =C55*(1-$C$17) -> 18971.006 | D56: =D55*(1-$C$17) -> 29845.011 | E56: =E55*(1-$C$17) -> 32224.729 | F56: =F55*(1-$C$17) -> 33305.811
B57: Lump Sum: tarifa (sin descuento) | C57: =C45/$C$7*(1+$C$12) -> 48206.455 | D57: =D45/$C$7*(1+$C$12) -> 82239.105 | E57: =E45/$C$7*(1+$C$12) -> 100986.45 | F57: =F45/$C$7*(1+$C$12) -> 112108.36
B58: Lump Sum: tarifa 6ª en adelante (columna con descuento) | C58: =C57*(1-$C$18) -> 24103.228 | D58: =D57*(1-$C$18) -> 41119.553 | E58: =E57*(1-$C$18) -> 50493.226 | F58: =F57*(1-$C$18) -> 56054.179
B59: Ecotransur: tarifa, 1ª a 5ª del mes | C59: =C46/$C$7*(1+$C$11) -> 37900.811 | D59: =D46/$C$7*(1+$C$11) -> 56135.946 | E59: =E46/$C$7*(1+$C$11) -> 67298.109 | F59: =F46/$C$7*(1+$C$11) -> 68394.595
B60: Ecotransur: 6ª en adelante (solo equipos) | C60: =C47/$C$7*(1+$C$11) -> 33291.892 | D60: =D47/$C$7*(1+$C$11) -> 33291.892 | E60: =E47/$C$7*(1+$C$11) -> 37568.919 | F60: =F47/$C$7*(1+$C$11) -> 45150
B61: Costo total por movilización tercerizada = tarifa + taladro + Truck Manager (si es por movilización) + horas excedidas
B62: Petro Star normal, 1ª a 5ª (fila amarilla del Excel sin el TM) | C62: =C55+C53+C54+C69 -> 55414.011 | D62: =D55+D53+D54+D69 -> 85898.023 | E62: =E55+E53+E54+E69 -> 99393.459 | F62: =F55+F53+F54+F69 -> 107379.62
B63: Petro Star normal, 6ª en adelante | C63: =C56+C53+C54+C69 -> 36443.006 | D63: =D56+D53+D54+D69 -> 56053.011 | E63: =E56+E53+E54+E69 -> 67168.729 | F63: =F56+F53+F54+F69 -> 74073.811
B64: Lump Sum sin descuento (fila amarilla del Excel sin el TM) | C64: =C57+C53+C54+C69 -> 65678.455 | D64: =D57+D53+D54+D69 -> 108447.11 | E64: =E57+E53+E54+E69 -> 135930.45 | F64: =F57+F53+F54+F69 -> 152876.36
B65: Lump Sum con descuento, 6ª en adelante | C65: =C58+C53+C54+C69 -> 41575.228 | D65: =D58+D53+D54+D69 -> 67327.553 | E65: =E58+E53+E54+E69 -> 85437.226 | F65: =F58+F53+F54+F69 -> 96822.179
B66: Ecotransur, 1ª a 5ª (fila amarilla del Excel sin el TM) | C66: =C59+C53+C54+C69 -> 55372.811 | D66: =D59+D53+D54+D69 -> 82343.946 | E66: =E59+E53+E54+E69 -> 102242.11 | F66: =F59+F53+F54+F69 -> 109162.6
B67: Ecotransur, 6ª en adelante | C67: =C60+C53+C54+C69 -> 50763.892 | D67: =D60+D53+D54+D69 -> 59499.892 | E67: =E60+E53+E54+E69 -> 72512.919 | F67: =F60+F53+F54+F69 -> 85918
B68: Equipos de la flota mínima por hora excedida (COP/h) | C68: 3934000 | D68: 3934000 | E68: 3934000 | F68: 3934000 | G68: Estimado | H68: Flota mínima Cot. 1255 p. 1–2 a tarifa por hora p. 5 (Ecotransur: mismas tarifas, supuesto)
B69: Cobro por horas excedidas (equipos + señalizadores), por movilización | C69: =IF($N$7="Sí",MAX(0,C39+C40-C41)*(C68+$N$8)/$C$7,0) -> 0 | D69: =IF($N$7="Sí",MAX(0,D39+D40-D41)*(D68+$N$8)/$C$7,0) -> 0 | E69: =IF($N$7="Sí",MAX(0,E39+E40-E41)*(E68+$N$8)/$C$7,0) -> 0 | F69: =IF($N$7="Sí",MAX(0,F39+F40-F41)*(F68+$N$8)/$C$7,0) -> 0 | G69: Cero con las horas del Excel; aparece si las horas superan el tiempo estipulado
B70: 4. CARGO FIJO MENSUAL DEL TRANSPORTADOR (nómina + disponibilidad o stand-by), según movilizaciones del mes
B71: Movilizaciones en el mes | C71: Petro Star (COP) | D71: Ecotransur (COP) | E71: Petro Star (USD) | F71: Ecotransur (USD) | G71: Fuente
B72: 0 | C72: 594780000 | D72: 837374835 | E72: =C72/$C$7 -> 160751.35 | F72: =D72/$C$7 -> 226317.52 | G72: Cot. 1255 p. 4 · Ecotransur p. 2–3. La fila 0 se cobra en cada mes bloqueado con contrato vigente (N9); los meses sin campaña no se cobran
B73: 1 | C73: 494879522 | D73: 669899868 | E73: =C73/$C$7 -> 133751.22 | F73: =D73/$C$7 -> 181054.02 | G73: Nómina + disponibilidad (PS) · nómina 80% + stand-by 80% (EC)
B74: 2 | C74: 352015000 | D74: 502424901 | E74: =C74/$C$7 -> 95139.189 | F74: =D74/$C$7 -> 135790.51
B75: 3 | C75: 258103162 | D75: 334949934 | E75: =C75/$C$7 -> 69757.611 | F75: =D75/$C$7 -> 90527.009
B76: 4 | C76: 208921566 | D76: 167474967 | E76: =C76/$C$7 -> 56465.288 | F76: =D76/$C$7 -> 45263.505
B77: 5 | C77: 151524391 | D77: 0 | E77: =C77/$C$7 -> 40952.538 | F77: =D77/$C$7 -> 0 | G77: PS: la tabla de 5 movs aún cobra (amarillo). EC: desde la 5ª no cobra
B78: 6 o más | C78: 0 | D78: 0 | E78: =C78/$C$7 -> 0 | F78: =D78/$C$7 -> 0 | G78: Sin cargo fijo
B79: El cargo de Petro Star aplica igual a la tarifa normal y al Lump Sum (la tabla de la p. 4 es condición general de la oferta). Los meses bloqueados con contrato vigente pagan la fila 0 más el Truck Manager (parámetro N9); al terminar la campaña termina el contrato y no hay cobro.
B81: 5. COSTO DE LA CAMPAÑA CON LOS PARÁMETROS CARGADOS
B82: Modelo | C82: Costo de la campaña (USD) | D82: Ahorro frente al WO (USD) | E82: Ahorro % | F82: Movilizaciones con descuento | G82: Cargo fijo pagado (USD) | H82: Meses de campaña | I82: Control | L82: Ahorro por pozo (USD) | M82: Ahorro como % del costo de un pozo
B83: Work Order (modelo directo) | C83: =SUM(G157:G216) -> 3130187.3 | H83: =COUNTIF($F$115:$F$150,">0") -> 7 | I83: =IF(COUNT(D157:D216)<>$C$30,"CAMPAÑA RECORTADA (máx. 60 pozos)",IF(MAX(E157:E216)>36,"CAMPAÑA DE MÁS DE 36 MESES: AMPLIAR",IF(COUNTIFS(F115:F150,0,B115:B150,"<="&MAX(E157:E216))>0,"OK · hay meses sin movilización que pagan cargo fijo","OK"))) -> OK
B84: Petro Star tarifa normal | C84: =SUM(H157:H216)+G151+I151+$N$9*$E$72+$N$9*IF($C$16="Mensual fijo",$C$14/$C$7,0)+$N$12*($C$9+IF($N$7="Sí",($D$68+$N$8)/$C$7,0)) -> 2998035.2 | D84: =$C$83-C84 -> 132152.06 | E84: =IF($C$83=0,0,D84/$C$83) -> 0.04221858 | F84: =COUNTIF($F$157:$F$216,">="&$C$19) -> 0 | G84: =G151+$N$9*$E$72 -> 286667.77 | H84: =COUNTIF($F$115:$F$150,">0") -> 7 | L84: =IF($C$30=0,0,D84/$C$30) -> 3775.7732 | M84: =IF($N$11=0,0,L84/$N$11) -> 0.0062929554
B85: Petro Star Lump Sum (sin descuento) | C85: =SUM(I157:I216)+G151+I151+$N$9*$E$72+$N$9*IF($C$16="Mensual fijo",$C$14/$C$7,0)+$N$12*($C$9+IF($N$7="Sí",($D$68+$N$8)/$C$7,0)) -> 3602983.6 | D85: =$C$83-C85 -> -472796.26 | E85: =IF($C$83=0,0,D85/$C$83) -> -0.15104408 | F85: 0 | G85: =G151+$N$9*$E$72 -> 286667.77 | H85: =COUNTIF($F$115:$F$150,">0") -> 7 | L85: =IF($C$30=0,0,D85/$C$30) -> -13508.464 | M85: =IF($N$11=0,0,L85/$N$11) -> -0.022514107
B86: Lump Sum con descuento (solo referencia) | C86: =SUM(J157:J216)+G151+I151+$N$9*$E$72+$N$9*IF($C$16="Mensual fijo",$C$14/$C$7,0)+$N$12*($C$9+IF($N$7="Sí",($D$68+$N$8)/$C$7,0)) -> 3602983.6 | D86: =$C$83-C86 -> -472796.26 | E86: =IF($C$83=0,0,D86/$C$83) -> -0.15104408 | F86: =COUNTIF($F$157:$F$216,">="&$C$19) -> 0 | G86: =G151+$N$9*$E$72 -> 286667.77 | H86: =COUNTIF($F$115:$F$150,">0") -> 7 | L86: =IF($C$30=0,0,D86/$C$30) -> -13508.464 | M86: =IF($N$11=0,0,L86/$N$11) -> -0.022514107
B87: Ecotransur | C87: =SUM(K157:K216)+H151+I151+$N$9*$F$72+$N$9*IF($C$16="Mensual fijo",$C$14/$C$7,0)+$N$12*($C$9+IF($N$7="Sí",($D$68+$N$8)/$C$7,0)) -> 2639667.9 | D87: =$C$83-C87 -> 490519.35 | E87: =IF($C$83=0,0,D87/$C$83) -> 0.15670607 | F87: =COUNTIF($F$157:$F$216,">="&$C$19) -> 0 | G87: =H151+$N$9*$F$72 -> 0 | H87: =COUNTIF($F$115:$F$150,">0") -> 7 | L87: =IF($C$30=0,0,D87/$C$30) -> 14014.839 | M87: =IF($N$11=0,0,L87/$N$11) -> 0.023358064
B88: Oferta elegida en C10 (detalle) | C88: =INDEX(C84:C87,MATCH($C$10,$B$84:$B$87,0)) -> 2998035.2 | D88: =INDEX(D84:D87,MATCH($C$10,$B$84:$B$87,0)) -> 132152.06 | E88: =INDEX(E84:E87,MATCH($C$10,$B$84:$B$87,0)) -> 0.04221858
B89: La fila 'Lump Sum con descuento' es solo referencia; la evaluación principal usa el Lump Sum sin descuento. Esta cifra depende de la frecuencia, de la mezcla por rango y del orden de los pozos dentro del mes. La sección 6 muestra desde cuántas movilizaciones por mes conviene cada oferta.
B91: 6. FRONTERA DE DECISIÓN · ahorro del mes si en él hay n movilizaciones, todas del mismo rango (USD)
B92: Oferta · rango / movilizaciones en el mes → | C92: 1 | D92: 2 | E92: 3 | F92: 4 | G92: 5 | H92: 6 | I92: 7 | J92: 8 | K92: 9 | L92: 10 | M92: 11 | N92: 12 | O92: Equilibrio (movs/mes)
B93: Petro Star tarifa normal · Misma localización | C93: =(C$92*C$51)-(MIN(C$92,$C$19-1)*C$62+MAX(0,C$92-($C$19-1))*C$63+INDEX($E$72:$E$78,MIN(C$92,6)+1)+IF($C$16="Mensual fijo",$C$14/$C$7,0)) -> -129334.04 | D93: =(D$92*C$51)-(MIN(D$92,$C$19-1)*C$62+MAX(0,D$92-($C$19-1))*C$63+INDEX($E$72:$E$78,MIN(D$92,6)+1)+IF($C$16="Mensual fijo",$C$14/$C$7,0)) -> -70088.617 | E93: =(E$92*C$51)-(MIN(E$92,$C$19-1)*C$62+MAX(0,E$92-($C$19-1))*C$63+INDEX($E$72:$E$78,MIN(E$92,6)+1)+IF($C$16="Mensual fijo",$C$14/$C$7,0)) -> -24073.645 | F93: =(F$92*C$51)-(MIN(F$92,$C$19-1)*C$62+MAX(0,F$92-($C$19-1))*C$63+INDEX($E$72:$E$78,MIN(F$92,6)+1)+IF($C$16="Mensual fijo",$C$14/$C$7,0)) -> 9852.073 | G93: =(G$92*C$51)-(MIN(G$92,$C$19-1)*C$62+MAX(0,G$92-($C$19-1))*C$63+INDEX($E$72:$E$78,MIN(G$92,6)+1)+IF($C$16="Mensual fijo",$C$14/$C$7,0)) -> 45998.217 | H93: =(H$92*C$51)-(MIN(H$92,$C$19-1)*C$62+MAX(0,H$92-($C$19-1))*C$63+INDEX($E$72:$E$78,MIN(H$92,6)+1)+IF($C$16="Mensual fijo",$C$14/$C$7,0)) -> 126555.16 | I93: =(I$92*C$51)-(MIN(I$92,$C$19-1)*C$62+MAX(0,I$92-($C$19-1))*C$63+INDEX($E$72:$E$78,MIN(I$92,6)+1)+IF($C$16="Mensual fijo",$C$14/$C$7,0)) -> 166159.56 | J93: =(J$92*C$51)-(MIN(J$92,$C$19-1)*C$62+MAX(0,J$92-($C$19-1))*C$63+INDEX($E$72:$E$78,MIN(J$92,6)+1)+IF($C$16="Mensual fijo",$C$14/$C$7,0)) -> 205763.95 | K93: =(K$92*C$51)-(MIN(K$92,$C$19-1)*C$62+MAX(0,K$92-($C$19-1))*C$63+INDEX($E$72:$E$78,MIN(K$92,6)+1)+IF($C$16="Mensual fijo",$C$14/$C$7,0)) -> 245368.35 | L93: =(L$92*C$51)-(MIN(L$92,$C$19-1)*C$62+MAX(0,L$92-($C$19-1))*C$63+INDEX($E$72:$E$78,MIN(L$92,6)+1)+IF($C$16="Mensual fijo",$C$14/$C$7,0)) -> 284972.75 | M93: =(M$92*C$51)-(MIN(M$92,$C$19-1)*C$62+MAX(0,M$92-($C$19-1))*C$63+INDEX($E$72:$E$78,MIN(M$92,6)+1)+IF($C$16="Mensual fijo",$C$14/$C$7,0)) -> 324577.15 | N93: =(N$92*C$51)-(MIN(N$92,$C$19-1)*C$62+MAX(0,N$92-($C$19-1))*C$63+INDEX($E$72:$E$78,MIN(N$92,6)+1)+IF($C$16="Mensual fijo",$C$14/$C$7,0)) -> 364181.55 | O93: =IFERROR(INDEX($C$92:$N$92,MATCH(1,INDEX(--(C93:N93>=0),0),0)),"no cruza") -> 4
B94: Petro Star tarifa normal · 0,1–5 km | C94: =(C$92*D$51)-(MIN(C$92,$C$19-1)*D$62+MAX(0,C$92-($C$19-1))*D$63+INDEX($E$72:$E$78,MIN(C$92,6)+1)+IF($C$16="Mensual fijo",$C$14/$C$7,0)) -> -136391.65 | D94: =(D$92*D$51)-(MIN(D$92,$C$19-1)*D$62+MAX(0,D$92-($C$19-1))*D$63+INDEX($E$72:$E$78,MIN(D$92,6)+1)+IF($C$16="Mensual fijo",$C$14/$C$7,0)) -> -84203.829 | E94: =(E$92*D$51)-(MIN(E$92,$C$19-1)*D$62+MAX(0,E$92-($C$19-1))*D$63+INDEX($E$72:$E$78,MIN(E$92,6)+1)+IF($C$16="Mensual fijo",$C$14/$C$7,0)) -> -45246.463 | F94: =(F$92*D$51)-(MIN(F$92,$C$19-1)*D$62+MAX(0,F$92-($C$19-1))*D$63+INDEX($E$72:$E$78,MIN(F$92,6)+1)+IF($C$16="Mensual fijo",$C$14/$C$7,0)) -> -18378.352 | G94: =(G$92*D$51)-(MIN(G$92,$C$19-1)*D$62+MAX(0,G$92-($C$19-1))*D$63+INDEX($E$72:$E$78,MIN(G$92,6)+1)+IF($C$16="Mensual fijo",$C$14/$C$7,0)) -> 10710.186 | H94: =(H$92*D$51)-(MIN(H$92,$C$19-1)*D$62+MAX(0,H$92-($C$19-1))*D$63+INDEX($E$72:$E$78,MIN(H$92,6)+1)+IF($C$16="Mensual fijo",$C$14/$C$7,0)) -> 95083.524 | I94: =(I$92*D$51)-(MIN(I$92,$C$19-1)*D$62+MAX(0,I$92-($C$19-1))*D$63+INDEX($E$72:$E$78,MIN(I$92,6)+1)+IF($C$16="Mensual fijo",$C$14/$C$7,0)) -> 138504.32 | J94: =(J$92*D$51)-(MIN(J$92,$C$19-1)*D$62+MAX(0,J$92-($C$19-1))*D$63+INDEX($E$72:$E$78,MIN(J$92,6)+1)+IF($C$16="Mensual fijo",$C$14/$C$7,0)) -> 181925.12 | K94: =(K$92*D$51)-(MIN(K$92,$C$19-1)*D$62+MAX(0,K$92-($C$19-1))*D$63+INDEX($E$72:$E$78,MIN(K$92,6)+1)+IF($C$16="Mensual fijo",$C$14/$C$7,0)) -> 225345.92 | L94: =(L$92*D$51)-(MIN(L$92,$C$19-1)*D$62+MAX(0,L$92-($C$19-1))*D$63+INDEX($E$72:$E$78,MIN(L$92,6)+1)+IF($C$16="Mensual fijo",$C$14/$C$7,0)) -> 268766.72 | M94: =(M$92*D$51)-(MIN(M$92,$C$19-1)*D$62+MAX(0,M$92-($C$19-1))*D$63+INDEX($E$72:$E$78,MIN(M$92,6)+1)+IF($C$16="Mensual fijo",$C$14/$C$7,0)) -> 312187.52 | N94: =(N$92*D$51)-(MIN(N$92,$C$19-1)*D$62+MAX(0,N$92-($C$19-1))*D$63+INDEX($E$72:$E$78,MIN(N$92,6)+1)+IF($C$16="Mensual fijo",$C$14/$C$7,0)) -> 355608.32 | O94: =IFERROR(INDEX($C$92:$N$92,MATCH(1,INDEX(--(C94:N94>=0),0),0)),"no cruza") -> 5
B95: Petro Star tarifa normal · 5–10 km | C95: =(C$92*E$51)-(MIN(C$92,$C$19-1)*E$62+MAX(0,C$92-($C$19-1))*E$63+INDEX($E$72:$E$78,MIN(C$92,6)+1)+IF($C$16="Mensual fijo",$C$14/$C$7,0)) -> -153176.09 | D95: =(D$92*E$51)-(MIN(D$92,$C$19-1)*E$62+MAX(0,D$92-($C$19-1))*E$63+INDEX($E$72:$E$78,MIN(D$92,6)+1)+IF($C$16="Mensual fijo",$C$14/$C$7,0)) -> -117772.7 | E95: =(E$92*E$51)-(MIN(E$92,$C$19-1)*E$62+MAX(0,E$92-($C$19-1))*E$63+INDEX($E$72:$E$78,MIN(E$92,6)+1)+IF($C$16="Mensual fijo",$C$14/$C$7,0)) -> -95599.772 | F95: =(F$92*E$51)-(MIN(F$92,$C$19-1)*E$62+MAX(0,F$92-($C$19-1))*E$63+INDEX($E$72:$E$78,MIN(F$92,6)+1)+IF($C$16="Mensual fijo",$C$14/$C$7,0)) -> -85516.097 | G95: =(G$92*E$51)-(MIN(G$92,$C$19-1)*E$62+MAX(0,G$92-($C$19-1))*E$63+INDEX($E$72:$E$78,MIN(G$92,6)+1)+IF($C$16="Mensual fijo",$C$14/$C$7,0)) -> -73211.995 | H95: =(H$92*E$51)-(MIN(H$92,$C$19-1)*E$62+MAX(0,H$92-($C$19-1))*E$63+INDEX($E$72:$E$78,MIN(H$92,6)+1)+IF($C$16="Mensual fijo",$C$14/$C$7,0)) -> -3243.3754 | I95: =(I$92*E$51)-(MIN(I$92,$C$19-1)*E$62+MAX(0,I$92-($C$19-1))*E$63+INDEX($E$72:$E$78,MIN(I$92,6)+1)+IF($C$16="Mensual fijo",$C$14/$C$7,0)) -> 25772.706 | J95: =(J$92*E$51)-(MIN(J$92,$C$19-1)*E$62+MAX(0,J$92-($C$19-1))*E$63+INDEX($E$72:$E$78,MIN(J$92,6)+1)+IF($C$16="Mensual fijo",$C$14/$C$7,0)) -> 54788.787 | K95: =(K$92*E$51)-(MIN(K$92,$C$19-1)*E$62+MAX(0,K$92-($C$19-1))*E$63+INDEX($E$72:$E$78,MIN(K$92,6)+1)+IF($C$16="Mensual fijo",$C$14/$C$7,0)) -> 83804.869 | L95: =(L$92*E$51)-(MIN(L$92,$C$19-1)*E$62+MAX(0,L$92-($C$19-1))*E$63+INDEX($E$72:$E$78,MIN(L$92,6)+1)+IF($C$16="Mensual fijo",$C$14/$C$7,0)) -> 112820.95 | M95: =(M$92*E$51)-(MIN(M$92,$C$19-1)*E$62+MAX(0,M$92-($C$19-1))*E$63+INDEX($E$72:$E$78,MIN(M$92,6)+1)+IF($C$16="Mensual fijo",$C$14/$C$7,0)) -> 141837.03 | N95: =(N$92*E$51)-(MIN(N$92,$C$19-1)*E$62+MAX(0,N$92-($C$19-1))*E$63+INDEX($E$72:$E$78,MIN(N$92,6)+1)+IF($C$16="Mensual fijo",$C$14/$C$7,0)) -> 170853.11 | O95: =IFERROR(INDEX($C$92:$N$92,MATCH(1,INDEX(--(C95:N95>=0),0),0)),"no cruza") -> 7
B96: Petro Star tarifa normal · Más de 10 km | C96: =(C$92*F$51)-(MIN(C$92,$C$19-1)*F$62+MAX(0,C$92-($C$19-1))*F$63+INDEX($E$72:$E$78,MIN(C$92,6)+1)+IF($C$16="Mensual fijo",$C$14/$C$7,0)) -> -146362.25 | D96: =(D$92*F$51)-(MIN(D$92,$C$19-1)*F$62+MAX(0,D$92-($C$19-1))*F$63+INDEX($E$72:$E$78,MIN(D$92,6)+1)+IF($C$16="Mensual fijo",$C$14/$C$7,0)) -> -104145.03 | E96: =(E$92*F$51)-(MIN(E$92,$C$19-1)*F$62+MAX(0,E$92-($C$19-1))*F$63+INDEX($E$72:$E$78,MIN(E$92,6)+1)+IF($C$16="Mensual fijo",$C$14/$C$7,0)) -> -75158.258 | F96: =(F$92*F$51)-(MIN(F$92,$C$19-1)*F$62+MAX(0,F$92-($C$19-1))*F$63+INDEX($E$72:$E$78,MIN(F$92,6)+1)+IF($C$16="Mensual fijo",$C$14/$C$7,0)) -> -58260.745 | G96: =(G$92*F$51)-(MIN(G$92,$C$19-1)*F$62+MAX(0,G$92-($C$19-1))*F$63+INDEX($E$72:$E$78,MIN(G$92,6)+1)+IF($C$16="Mensual fijo",$C$14/$C$7,0)) -> -39142.806 | H96: =(H$92*F$51)-(MIN(H$92,$C$19-1)*F$62+MAX(0,H$92-($C$19-1))*F$63+INDEX($E$72:$E$78,MIN(H$92,6)+1)+IF($C$16="Mensual fijo",$C$14/$C$7,0)) -> 38720.733 | I96: =(I$92*F$51)-(MIN(I$92,$C$19-1)*F$62+MAX(0,I$92-($C$19-1))*F$63+INDEX($E$72:$E$78,MIN(I$92,6)+1)+IF($C$16="Mensual fijo",$C$14/$C$7,0)) -> 75631.733 | J96: =(J$92*F$51)-(MIN(J$92,$C$19-1)*F$62+MAX(0,J$92-($C$19-1))*F$63+INDEX($E$72:$E$78,MIN(J$92,6)+1)+IF($C$16="Mensual fijo",$C$14/$C$7,0)) -> 112542.73 | K96: =(K$92*F$51)-(MIN(K$92,$C$19-1)*F$62+MAX(0,K$92-($C$19-1))*F$63+INDEX($E$72:$E$78,MIN(K$92,6)+1)+IF($C$16="Mensual fijo",$C$14/$C$7,0)) -> 149453.73 | L96: =(L$92*F$51)-(MIN(L$92,$C$19-1)*F$62+MAX(0,L$92-($C$19-1))*F$63+INDEX($E$72:$E$78,MIN(L$92,6)+1)+IF($C$16="Mensual fijo",$C$14/$C$7,0)) -> 186364.73 | M96: =(M$92*F$51)-(MIN(M$92,$C$19-1)*F$62+MAX(0,M$92-($C$19-1))*F$63+INDEX($E$72:$E$78,MIN(M$92,6)+1)+IF($C$16="Mensual fijo",$C$14/$C$7,0)) -> 223275.73 | N96: =(N$92*F$51)-(MIN(N$92,$C$19-1)*F$62+MAX(0,N$92-($C$19-1))*F$63+INDEX($E$72:$E$78,MIN(N$92,6)+1)+IF($C$16="Mensual fijo",$C$14/$C$7,0)) -> 260186.73 | O96: =IFERROR(INDEX($C$92:$N$92,MATCH(1,INDEX(--(C96:N96>=0),0),0)),"no cruza") -> 6
B97: Petro Star Lump Sum (sin descuento) · Misma localización | C97: =(C$92*C$51)-(MIN(C$92,$C$19-1)*C$64+MAX(0,C$92-($C$19-1))*C$64+INDEX($E$72:$E$78,MIN(C$92,6)+1)+IF($C$16="Mensual fijo",$C$14/$C$7,0)) -> -139598.49 | D97: =(D$92*C$51)-(MIN(D$92,$C$19-1)*C$64+MAX(0,D$92-($C$19-1))*C$64+INDEX($E$72:$E$78,MIN(D$92,6)+1)+IF($C$16="Mensual fijo",$C$14/$C$7,0)) -> -90617.505 | E97: =(E$92*C$51)-(MIN(E$92,$C$19-1)*C$64+MAX(0,E$92-($C$19-1))*C$64+INDEX($E$72:$E$78,MIN(E$92,6)+1)+IF($C$16="Mensual fijo",$C$14/$C$7,0)) -> -54866.978 | F97: =(F$92*C$51)-(MIN(F$92,$C$19-1)*C$64+MAX(0,F$92-($C$19-1))*C$64+INDEX($E$72:$E$78,MIN(F$92,6)+1)+IF($C$16="Mensual fijo",$C$14/$C$7,0)) -> -31205.704 | G97: =(G$92*C$51)-(MIN(G$92,$C$19-1)*C$64+MAX(0,G$92-($C$19-1))*C$64+INDEX($E$72:$E$78,MIN(G$92,6)+1)+IF($C$16="Mensual fijo",$C$14/$C$7,0)) -> -5324.0043 | H97: =(H$92*C$51)-(MIN(H$92,$C$19-1)*C$64+MAX(0,H$92-($C$19-1))*C$64+INDEX($E$72:$E$78,MIN(H$92,6)+1)+IF($C$16="Mensual fijo",$C$14/$C$7,0)) -> 45997.484 | I97: =(I$92*C$51)-(MIN(I$92,$C$19-1)*C$64+MAX(0,I$92-($C$19-1))*C$64+INDEX($E$72:$E$78,MIN(I$92,6)+1)+IF($C$16="Mensual fijo",$C$14/$C$7,0)) -> 56366.434 | J97: =(J$92*C$51)-(MIN(J$92,$C$19-1)*C$64+MAX(0,J$92-($C$19-1))*C$64+INDEX($E$72:$E$78,MIN(J$92,6)+1)+IF($C$16="Mensual fijo",$C$14/$C$7,0)) -> 66735.384 | K97: =(K$92*C$51)-(MIN(K$92,$C$19-1)*C$64+MAX(0,K$92-($C$19-1))*C$64+INDEX($E$72:$E$78,MIN(K$92,6)+1)+IF($C$16="Mensual fijo",$C$14/$C$7,0)) -> 77104.334 | L97: =(L$92*C$51)-(MIN(L$92,$C$19-1)*C$64+MAX(0,L$92-($C$19-1))*C$64+INDEX($E$72:$E$78,MIN(L$92,6)+1)+IF($C$16="Mensual fijo",$C$14/$C$7,0)) -> 87473.284 | M97: =(M$92*C$51)-(MIN(M$92,$C$19-1)*C$64+MAX(0,M$92-($C$19-1))*C$64+INDEX($E$72:$E$78,MIN(M$92,6)+1)+IF($C$16="Mensual fijo",$C$14/$C$7,0)) -> 97842.234 | N97: =(N$92*C$51)-(MIN(N$92,$C$19-1)*C$64+MAX(0,N$92-($C$19-1))*C$64+INDEX($E$72:$E$78,MIN(N$92,6)+1)+IF($C$16="Mensual fijo",$C$14/$C$7,0)) -> 108211.18 | O97: =IFERROR(INDEX($C$92:$N$92,MATCH(1,INDEX(--(C97:N97>=0),0),0)),"no cruza") -> 6
B98: Petro Star Lump Sum (sin descuento) · 0,1–5 km | C98: =(C$92*D$51)-(MIN(C$92,$C$19-1)*D$64+MAX(0,C$92-($C$19-1))*D$64+INDEX($E$72:$E$78,MIN(C$92,6)+1)+IF($C$16="Mensual fijo",$C$14/$C$7,0)) -> -158940.73 | D98: =(D$92*D$51)-(MIN(D$92,$C$19-1)*D$64+MAX(0,D$92-($C$19-1))*D$64+INDEX($E$72:$E$78,MIN(D$92,6)+1)+IF($C$16="Mensual fijo",$C$14/$C$7,0)) -> -129301.99 | E98: =(E$92*D$51)-(MIN(E$92,$C$19-1)*D$64+MAX(0,E$92-($C$19-1))*D$64+INDEX($E$72:$E$78,MIN(E$92,6)+1)+IF($C$16="Mensual fijo",$C$14/$C$7,0)) -> -112893.71 | F98: =(F$92*D$51)-(MIN(F$92,$C$19-1)*D$64+MAX(0,F$92-($C$19-1))*D$64+INDEX($E$72:$E$78,MIN(F$92,6)+1)+IF($C$16="Mensual fijo",$C$14/$C$7,0)) -> -108574.68 | G98: =(G$92*D$51)-(MIN(G$92,$C$19-1)*D$64+MAX(0,G$92-($C$19-1))*D$64+INDEX($E$72:$E$78,MIN(G$92,6)+1)+IF($C$16="Mensual fijo",$C$14/$C$7,0)) -> -102035.23 | H98: =(H$92*D$51)-(MIN(H$92,$C$19-1)*D$64+MAX(0,H$92-($C$19-1))*D$64+INDEX($E$72:$E$78,MIN(H$92,6)+1)+IF($C$16="Mensual fijo",$C$14/$C$7,0)) -> -70055.984 | I98: =(I$92*D$51)-(MIN(I$92,$C$19-1)*D$64+MAX(0,I$92-($C$19-1))*D$64+INDEX($E$72:$E$78,MIN(I$92,6)+1)+IF($C$16="Mensual fijo",$C$14/$C$7,0)) -> -79029.278 | J98: =(J$92*D$51)-(MIN(J$92,$C$19-1)*D$64+MAX(0,J$92-($C$19-1))*D$64+INDEX($E$72:$E$78,MIN(J$92,6)+1)+IF($C$16="Mensual fijo",$C$14/$C$7,0)) -> -88002.573 | K98: =(K$92*D$51)-(MIN(K$92,$C$19-1)*D$64+MAX(0,K$92-($C$19-1))*D$64+INDEX($E$72:$E$78,MIN(K$92,6)+1)+IF($C$16="Mensual fijo",$C$14/$C$7,0)) -> -96975.868 | L98: =(L$92*D$51)-(MIN(L$92,$C$19-1)*D$64+MAX(0,L$92-($C$19-1))*D$64+INDEX($E$72:$E$78,MIN(L$92,6)+1)+IF($C$16="Mensual fijo",$C$14/$C$7,0)) -> -105949.16 | M98: =(M$92*D$51)-(MIN(M$92,$C$19-1)*D$64+MAX(0,M$92-($C$19-1))*D$64+INDEX($E$72:$E$78,MIN(M$92,6)+1)+IF($C$16="Mensual fijo",$C$14/$C$7,0)) -> -114922.46 | N98: =(N$92*D$51)-(MIN(N$92,$C$19-1)*D$64+MAX(0,N$92-($C$19-1))*D$64+INDEX($E$72:$E$78,MIN(N$92,6)+1)+IF($C$16="Mensual fijo",$C$14/$C$7,0)) -> -123895.75 | O98: =IFERROR(INDEX($C$92:$N$92,MATCH(1,INDEX(--(C98:N98>=0),0),0)),"no cruza") -> no cruza
B99: Petro Star Lump Sum (sin descuento) · 5–10 km | C99: =(C$92*E$51)-(MIN(C$92,$C$19-1)*E$64+MAX(0,C$92-($C$19-1))*E$64+INDEX($E$72:$E$78,MIN(C$92,6)+1)+IF($C$16="Mensual fijo",$C$14/$C$7,0)) -> -189713.08 | D99: =(D$92*E$51)-(MIN(D$92,$C$19-1)*E$64+MAX(0,D$92-($C$19-1))*E$64+INDEX($E$72:$E$78,MIN(D$92,6)+1)+IF($C$16="Mensual fijo",$C$14/$C$7,0)) -> -190846.69 | E99: =(E$92*E$51)-(MIN(E$92,$C$19-1)*E$64+MAX(0,E$92-($C$19-1))*E$64+INDEX($E$72:$E$78,MIN(E$92,6)+1)+IF($C$16="Mensual fijo",$C$14/$C$7,0)) -> -205210.75 | F99: =(F$92*E$51)-(MIN(F$92,$C$19-1)*E$64+MAX(0,F$92-($C$19-1))*E$64+INDEX($E$72:$E$78,MIN(F$92,6)+1)+IF($C$16="Mensual fijo",$C$14/$C$7,0)) -> -231664.07 | G99: =(G$92*E$51)-(MIN(G$92,$C$19-1)*E$64+MAX(0,G$92-($C$19-1))*E$64+INDEX($E$72:$E$78,MIN(G$92,6)+1)+IF($C$16="Mensual fijo",$C$14/$C$7,0)) -> -255896.96 | H99: =(H$92*E$51)-(MIN(H$92,$C$19-1)*E$64+MAX(0,H$92-($C$19-1))*E$64+INDEX($E$72:$E$78,MIN(H$92,6)+1)+IF($C$16="Mensual fijo",$C$14/$C$7,0)) -> -254690.07 | I99: =(I$92*E$51)-(MIN(I$92,$C$19-1)*E$64+MAX(0,I$92-($C$19-1))*E$64+INDEX($E$72:$E$78,MIN(I$92,6)+1)+IF($C$16="Mensual fijo",$C$14/$C$7,0)) -> -294435.71 | J99: =(J$92*E$51)-(MIN(J$92,$C$19-1)*E$64+MAX(0,J$92-($C$19-1))*E$64+INDEX($E$72:$E$78,MIN(J$92,6)+1)+IF($C$16="Mensual fijo",$C$14/$C$7,0)) -> -334181.35 | K99: =(K$92*E$51)-(MIN(K$92,$C$19-1)*E$64+MAX(0,K$92-($C$19-1))*E$64+INDEX($E$72:$E$78,MIN(K$92,6)+1)+IF($C$16="Mensual fijo",$C$14/$C$7,0)) -> -373926.99 | L99: =(L$92*E$51)-(MIN(L$92,$C$19-1)*E$64+MAX(0,L$92-($C$19-1))*E$64+INDEX($E$72:$E$78,MIN(L$92,6)+1)+IF($C$16="Mensual fijo",$C$14/$C$7,0)) -> -413672.63 | M99: =(M$92*E$51)-(MIN(M$92,$C$19-1)*E$64+MAX(0,M$92-($C$19-1))*E$64+INDEX($E$72:$E$78,MIN(M$92,6)+1)+IF($C$16="Mensual fijo",$C$14/$C$7,0)) -> -453418.27 | N99: =(N$92*E$51)-(MIN(N$92,$C$19-1)*E$64+MAX(0,N$92-($C$19-1))*E$64+INDEX($E$72:$E$78,MIN(N$92,6)+1)+IF($C$16="Mensual fijo",$C$14/$C$7,0)) -> -493163.92 | O99: =IFERROR(INDEX($C$92:$N$92,MATCH(1,INDEX(--(C99:N99>=0),0),0)),"no cruza") -> no cruza
B100: Petro Star Lump Sum (sin descuento) · Más de 10 km | C100: =(C$92*F$51)-(MIN(C$92,$C$19-1)*F$64+MAX(0,C$92-($C$19-1))*F$64+INDEX($E$72:$E$78,MIN(C$92,6)+1)+IF($C$16="Mensual fijo",$C$14/$C$7,0)) -> -191858.99 | D100: =(D$92*F$51)-(MIN(D$92,$C$19-1)*F$64+MAX(0,D$92-($C$19-1))*F$64+INDEX($E$72:$E$78,MIN(D$92,6)+1)+IF($C$16="Mensual fijo",$C$14/$C$7,0)) -> -195138.5 | E100: =(E$92*F$51)-(MIN(E$92,$C$19-1)*F$64+MAX(0,E$92-($C$19-1))*F$64+INDEX($E$72:$E$78,MIN(E$92,6)+1)+IF($C$16="Mensual fijo",$C$14/$C$7,0)) -> -211648.47 | F100: =(F$92*F$51)-(MIN(F$92,$C$19-1)*F$64+MAX(0,F$92-($C$19-1))*F$64+INDEX($E$72:$E$78,MIN(F$92,6)+1)+IF($C$16="Mensual fijo",$C$14/$C$7,0)) -> -240247.7 | G100: =(G$92*F$51)-(MIN(G$92,$C$19-1)*F$64+MAX(0,G$92-($C$19-1))*F$64+INDEX($E$72:$E$78,MIN(G$92,6)+1)+IF($C$16="Mensual fijo",$C$14/$C$7,0)) -> -266626.49 | H100: =(H$92*F$51)-(MIN(H$92,$C$19-1)*F$64+MAX(0,H$92-($C$19-1))*F$64+INDEX($E$72:$E$78,MIN(H$92,6)+1)+IF($C$16="Mensual fijo",$C$14/$C$7,0)) -> -267565.5 | I100: =(I$92*F$51)-(MIN(I$92,$C$19-1)*F$64+MAX(0,I$92-($C$19-1))*F$64+INDEX($E$72:$E$78,MIN(I$92,6)+1)+IF($C$16="Mensual fijo",$C$14/$C$7,0)) -> -309457.05 | J100: =(J$92*F$51)-(MIN(J$92,$C$19-1)*F$64+MAX(0,J$92-($C$19-1))*F$64+INDEX($E$72:$E$78,MIN(J$92,6)+1)+IF($C$16="Mensual fijo",$C$14/$C$7,0)) -> -351348.6 | K100: =(K$92*F$51)-(MIN(K$92,$C$19-1)*F$64+MAX(0,K$92-($C$19-1))*F$64+INDEX($E$72:$E$78,MIN(K$92,6)+1)+IF($C$16="Mensual fijo",$C$14/$C$7,0)) -> -393240.15 | L100: =(L$92*F$51)-(MIN(L$92,$C$19-1)*F$64+MAX(0,L$92-($C$19-1))*F$64+INDEX($E$72:$E$78,MIN(L$92,6)+1)+IF($C$16="Mensual fijo",$C$14/$C$7,0)) -> -435131.7 | M100: =(M$92*F$51)-(MIN(M$92,$C$19-1)*F$64+MAX(0,M$92-($C$19-1))*F$64+INDEX($E$72:$E$78,MIN(M$92,6)+1)+IF($C$16="Mensual fijo",$C$14/$C$7,0)) -> -477023.25 | N100: =(N$92*F$51)-(MIN(N$92,$C$19-1)*F$64+MAX(0,N$92-($C$19-1))*F$64+INDEX($E$72:$E$78,MIN(N$92,6)+1)+IF($C$16="Mensual fijo",$C$14/$C$7,0)) -> -518914.79 | O100: =IFERROR(INDEX($C$92:$N$92,MATCH(1,INDEX(--(C100:N100>=0),0),0)),"no cruza") -> no cruza
B101: Lump Sum con descuento (solo referencia) · Misma localización | C101: =(C$92*C$51)-(MIN(C$92,$C$19-1)*C$64+MAX(0,C$92-($C$19-1))*C$65+INDEX($E$72:$E$78,MIN(C$92,6)+1)+IF($C$16="Mensual fijo",$C$14/$C$7,0)) -> -139598.49 | D101: =(D$92*C$51)-(MIN(D$92,$C$19-1)*C$64+MAX(0,D$92-($C$19-1))*C$65+INDEX($E$72:$E$78,MIN(D$92,6)+1)+IF($C$16="Mensual fijo",$C$14/$C$7,0)) -> -90617.505 | E101: =(E$92*C$51)-(MIN(E$92,$C$19-1)*C$64+MAX(0,E$92-($C$19-1))*C$65+INDEX($E$72:$E$78,MIN(E$92,6)+1)+IF($C$16="Mensual fijo",$C$14/$C$7,0)) -> -54866.978 | F101: =(F$92*C$51)-(MIN(F$92,$C$19-1)*C$64+MAX(0,F$92-($C$19-1))*C$65+INDEX($E$72:$E$78,MIN(F$92,6)+1)+IF($C$16="Mensual fijo",$C$14/$C$7,0)) -> -31205.704 | G101: =(G$92*C$51)-(MIN(G$92,$C$19-1)*C$64+MAX(0,G$92-($C$19-1))*C$65+INDEX($E$72:$E$78,MIN(G$92,6)+1)+IF($C$16="Mensual fijo",$C$14/$C$7,0)) -> -5324.0043 | H101: =(H$92*C$51)-(MIN(H$92,$C$19-1)*C$64+MAX(0,H$92-($C$19-1))*C$65+INDEX($E$72:$E$78,MIN(H$92,6)+1)+IF($C$16="Mensual fijo",$C$14/$C$7,0)) -> 70100.711 | I101: =(I$92*C$51)-(MIN(I$92,$C$19-1)*C$64+MAX(0,I$92-($C$19-1))*C$65+INDEX($E$72:$E$78,MIN(I$92,6)+1)+IF($C$16="Mensual fijo",$C$14/$C$7,0)) -> 104572.89 | J101: =(J$92*C$51)-(MIN(J$92,$C$19-1)*C$64+MAX(0,J$92-($C$19-1))*C$65+INDEX($E$72:$E$78,MIN(J$92,6)+1)+IF($C$16="Mensual fijo",$C$14/$C$7,0)) -> 139045.07 | K101: =(K$92*C$51)-(MIN(K$92,$C$19-1)*C$64+MAX(0,K$92-($C$19-1))*C$65+INDEX($E$72:$E$78,MIN(K$92,6)+1)+IF($C$16="Mensual fijo",$C$14/$C$7,0)) -> 173517.24 | L101: =(L$92*C$51)-(MIN(L$92,$C$19-1)*C$64+MAX(0,L$92-($C$19-1))*C$65+INDEX($E$72:$E$78,MIN(L$92,6)+1)+IF($C$16="Mensual fijo",$C$14/$C$7,0)) -> 207989.42 | M101: =(M$92*C$51)-(MIN(M$92,$C$19-1)*C$64+MAX(0,M$92-($C$19-1))*C$65+INDEX($E$72:$E$78,MIN(M$92,6)+1)+IF($C$16="Mensual fijo",$C$14/$C$7,0)) -> 242461.6 | N101: =(N$92*C$51)-(MIN(N$92,$C$19-1)*C$64+MAX(0,N$92-($C$19-1))*C$65+INDEX($E$72:$E$78,MIN(N$92,6)+1)+IF($C$16="Mensual fijo",$C$14/$C$7,0)) -> 276933.78 | O101: =IFERROR(INDEX($C$92:$N$92,MATCH(1,INDEX(--(C101:N101>=0),0),0)),"no cruza") -> 6
B102: Lump Sum con descuento (solo referencia) · 0,1–5 km | C102: =(C$92*D$51)-(MIN(C$92,$C$19-1)*D$64+MAX(0,C$92-($C$19-1))*D$65+INDEX($E$72:$E$78,MIN(C$92,6)+1)+IF($C$16="Mensual fijo",$C$14/$C$7,0)) -> -158940.73 | D102: =(D$92*D$51)-(MIN(D$92,$C$19-1)*D$64+MAX(0,D$92-($C$19-1))*D$65+INDEX($E$72:$E$78,MIN(D$92,6)+1)+IF($C$16="Mensual fijo",$C$14/$C$7,0)) -> -129301.99 | E102: =(E$92*D$51)-(MIN(E$92,$C$19-1)*D$64+MAX(0,E$92-($C$19-1))*D$65+INDEX($E$72:$E$78,MIN(E$92,6)+1)+IF($C$16="Mensual fijo",$C$14/$C$7,0)) -> -112893.71 | F102: =(F$92*D$51)-(MIN(F$92,$C$19-1)*D$64+MAX(0,F$92-($C$19-1))*D$65+INDEX($E$72:$E$78,MIN(F$92,6)+1)+IF($C$16="Mensual fijo",$C$14/$C$7,0)) -> -108574.68 | G102: =(G$92*D$51)-(MIN(G$92,$C$19-1)*D$64+MAX(0,G$92-($C$19-1))*D$65+INDEX($E$72:$E$78,MIN(G$92,6)+1)+IF($C$16="Mensual fijo",$C$14/$C$7,0)) -> -102035.23 | H102: =(H$92*D$51)-(MIN(H$92,$C$19-1)*D$64+MAX(0,H$92-($C$19-1))*D$65+INDEX($E$72:$E$78,MIN(H$92,6)+1)+IF($C$16="Mensual fijo",$C$14/$C$7,0)) -> -28936.431 | I102: =(I$92*D$51)-(MIN(I$92,$C$19-1)*D$64+MAX(0,I$92-($C$19-1))*D$65+INDEX($E$72:$E$78,MIN(I$92,6)+1)+IF($C$16="Mensual fijo",$C$14/$C$7,0)) -> 3209.827 | J102: =(J$92*D$51)-(MIN(J$92,$C$19-1)*D$64+MAX(0,J$92-($C$19-1))*D$65+INDEX($E$72:$E$78,MIN(J$92,6)+1)+IF($C$16="Mensual fijo",$C$14/$C$7,0)) -> 35356.085 | K102: =(K$92*D$51)-(MIN(K$92,$C$19-1)*D$64+MAX(0,K$92-($C$19-1))*D$65+INDEX($E$72:$E$78,MIN(K$92,6)+1)+IF($C$16="Mensual fijo",$C$14/$C$7,0)) -> 67502.343 | L102: =(L$92*D$51)-(MIN(L$92,$C$19-1)*D$64+MAX(0,L$92-($C$19-1))*D$65+INDEX($E$72:$E$78,MIN(L$92,6)+1)+IF($C$16="Mensual fijo",$C$14/$C$7,0)) -> 99648.601 | M102: =(M$92*D$51)-(MIN(M$92,$C$19-1)*D$64+MAX(0,M$92-($C$19-1))*D$65+INDEX($E$72:$E$78,MIN(M$92,6)+1)+IF($C$16="Mensual fijo",$C$14/$C$7,0)) -> 131794.86 | N102: =(N$92*D$51)-(MIN(N$92,$C$19-1)*D$64+MAX(0,N$92-($C$19-1))*D$65+INDEX($E$72:$E$78,MIN(N$92,6)+1)+IF($C$16="Mensual fijo",$C$14/$C$7,0)) -> 163941.12 | O102: =IFERROR(INDEX($C$92:$N$92,MATCH(1,INDEX(--(C102:N102>=0),0),0)),"no cruza") -> 7
B103: Lump Sum con descuento (solo referencia) · 5–10 km | C103: =(C$92*E$51)-(MIN(C$92,$C$19-1)*E$64+MAX(0,C$92-($C$19-1))*E$65+INDEX($E$72:$E$78,MIN(C$92,6)+1)+IF($C$16="Mensual fijo",$C$14/$C$7,0)) -> -189713.08 | D103: =(D$92*E$51)-(MIN(D$92,$C$19-1)*E$64+MAX(0,D$92-($C$19-1))*E$65+INDEX($E$72:$E$78,MIN(D$92,6)+1)+IF($C$16="Mensual fijo",$C$14/$C$7,0)) -> -190846.69 | E103: =(E$92*E$51)-(MIN(E$92,$C$19-1)*E$64+MAX(0,E$92-($C$19-1))*E$65+INDEX($E$72:$E$78,MIN(E$92,6)+1)+IF($C$16="Mensual fijo",$C$14/$C$7,0)) -> -205210.75 | F103: =(F$92*E$51)-(MIN(F$92,$C$19-1)*E$64+MAX(0,F$92-($C$19-1))*E$65+INDEX($E$72:$E$78,MIN(F$92,6)+1)+IF($C$16="Mensual fijo",$C$14/$C$7,0)) -> -231664.07 | G103: =(G$92*E$51)-(MIN(G$92,$C$19-1)*E$64+MAX(0,G$92-($C$19-1))*E$65+INDEX($E$72:$E$78,MIN(G$92,6)+1)+IF($C$16="Mensual fijo",$C$14/$C$7,0)) -> -255896.96 | H103: =(H$92*E$51)-(MIN(H$92,$C$19-1)*E$64+MAX(0,H$92-($C$19-1))*E$65+INDEX($E$72:$E$78,MIN(H$92,6)+1)+IF($C$16="Mensual fijo",$C$14/$C$7,0)) -> -204196.84 | I103: =(I$92*E$51)-(MIN(I$92,$C$19-1)*E$64+MAX(0,I$92-($C$19-1))*E$65+INDEX($E$72:$E$78,MIN(I$92,6)+1)+IF($C$16="Mensual fijo",$C$14/$C$7,0)) -> -193449.26 | J103: =(J$92*E$51)-(MIN(J$92,$C$19-1)*E$64+MAX(0,J$92-($C$19-1))*E$65+INDEX($E$72:$E$78,MIN(J$92,6)+1)+IF($C$16="Mensual fijo",$C$14/$C$7,0)) -> -182701.67 | K103: =(K$92*E$51)-(MIN(K$92,$C$19-1)*E$64+MAX(0,K$92-($C$19-1))*E$65+INDEX($E$72:$E$78,MIN(K$92,6)+1)+IF($C$16="Mensual fijo",$C$14/$C$7,0)) -> -171954.09 | L103: =(L$92*E$51)-(MIN(L$92,$C$19-1)*E$64+MAX(0,L$92-($C$19-1))*E$65+INDEX($E$72:$E$78,MIN(L$92,6)+1)+IF($C$16="Mensual fijo",$C$14/$C$7,0)) -> -161206.5 | M103: =(M$92*E$51)-(MIN(M$92,$C$19-1)*E$64+MAX(0,M$92-($C$19-1))*E$65+INDEX($E$72:$E$78,MIN(M$92,6)+1)+IF($C$16="Mensual fijo",$C$14/$C$7,0)) -> -150458.92 | N103: =(N$92*E$51)-(MIN(N$92,$C$19-1)*E$64+MAX(0,N$92-($C$19-1))*E$65+INDEX($E$72:$E$78,MIN(N$92,6)+1)+IF($C$16="Mensual fijo",$C$14/$C$7,0)) -> -139711.33 | O103: =IFERROR(INDEX($C$92:$N$92,MATCH(1,INDEX(--(C103:N103>=0),0),0)),"no cruza") -> no cruza
B104: Lump Sum con descuento (solo referencia) · Más de 10 km | C104: =(C$92*F$51)-(MIN(C$92,$C$19-1)*F$64+MAX(0,C$92-($C$19-1))*F$65+INDEX($E$72:$E$78,MIN(C$92,6)+1)+IF($C$16="Mensual fijo",$C$14/$C$7,0)) -> -191858.99 | D104: =(D$92*F$51)-(MIN(D$92,$C$19-1)*F$64+MAX(0,D$92-($C$19-1))*F$65+INDEX($E$72:$E$78,MIN(D$92,6)+1)+IF($C$16="Mensual fijo",$C$14/$C$7,0)) -> -195138.5 | E104: =(E$92*F$51)-(MIN(E$92,$C$19-1)*F$64+MAX(0,E$92-($C$19-1))*F$65+INDEX($E$72:$E$78,MIN(E$92,6)+1)+IF($C$16="Mensual fijo",$C$14/$C$7,0)) -> -211648.47 | F104: =(F$92*F$51)-(MIN(F$92,$C$19-1)*F$64+MAX(0,F$92-($C$19-1))*F$65+INDEX($E$72:$E$78,MIN(F$92,6)+1)+IF($C$16="Mensual fijo",$C$14/$C$7,0)) -> -240247.7 | G104: =(G$92*F$51)-(MIN(G$92,$C$19-1)*F$64+MAX(0,G$92-($C$19-1))*F$65+INDEX($E$72:$E$78,MIN(G$92,6)+1)+IF($C$16="Mensual fijo",$C$14/$C$7,0)) -> -266626.49 | H104: =(H$92*F$51)-(MIN(H$92,$C$19-1)*F$64+MAX(0,H$92-($C$19-1))*F$65+INDEX($E$72:$E$78,MIN(H$92,6)+1)+IF($C$16="Mensual fijo",$C$14/$C$7,0)) -> -211511.33 | I104: =(I$92*F$51)-(MIN(I$92,$C$19-1)*F$64+MAX(0,I$92-($C$19-1))*F$65+INDEX($E$72:$E$78,MIN(I$92,6)+1)+IF($C$16="Mensual fijo",$C$14/$C$7,0)) -> -197348.69 | J104: =(J$92*F$51)-(MIN(J$92,$C$19-1)*F$64+MAX(0,J$92-($C$19-1))*F$65+INDEX($E$72:$E$78,MIN(J$92,6)+1)+IF($C$16="Mensual fijo",$C$14/$C$7,0)) -> -183186.06 | K104: =(K$92*F$51)-(MIN(K$92,$C$19-1)*F$64+MAX(0,K$92-($C$19-1))*F$65+INDEX($E$72:$E$78,MIN(K$92,6)+1)+IF($C$16="Mensual fijo",$C$14/$C$7,0)) -> -169023.43 | L104: =(L$92*F$51)-(MIN(L$92,$C$19-1)*F$64+MAX(0,L$92-($C$19-1))*F$65+INDEX($E$72:$E$78,MIN(L$92,6)+1)+IF($C$16="Mensual fijo",$C$14/$C$7,0)) -> -154860.8 | M104: =(M$92*F$51)-(MIN(M$92,$C$19-1)*F$64+MAX(0,M$92-($C$19-1))*F$65+INDEX($E$72:$E$78,MIN(M$92,6)+1)+IF($C$16="Mensual fijo",$C$14/$C$7,0)) -> -140698.17 | N104: =(N$92*F$51)-(MIN(N$92,$C$19-1)*F$64+MAX(0,N$92-($C$19-1))*F$65+INDEX($E$72:$E$78,MIN(N$92,6)+1)+IF($C$16="Mensual fijo",$C$14/$C$7,0)) -> -126535.54 | O104: =IFERROR(INDEX($C$92:$N$92,MATCH(1,INDEX(--(C104:N104>=0),0),0)),"no cruza") -> no cruza
B105: Ecotransur · Misma localización | C105: =(C$92*C$51)-(MIN(C$92,$C$19-1)*C$66+MAX(0,C$92-($C$19-1))*C$67+INDEX($F$72:$F$78,MIN(C$92,6)+1)+IF($C$16="Mensual fijo",$C$14/$C$7,0)) -> -176595.64 | D105: =(D$92*C$51)-(MIN(D$92,$C$19-1)*C$66+MAX(0,D$92-($C$19-1))*C$67+INDEX($F$72:$F$78,MIN(D$92,6)+1)+IF($C$16="Mensual fijo",$C$14/$C$7,0)) -> -110657.54 | E105: =(E$92*C$51)-(MIN(E$92,$C$19-1)*C$66+MAX(0,E$92-($C$19-1))*C$67+INDEX($F$72:$F$78,MIN(E$92,6)+1)+IF($C$16="Mensual fijo",$C$14/$C$7,0)) -> -44719.443 | F105: =(F$92*C$51)-(MIN(F$92,$C$19-1)*C$66+MAX(0,F$92-($C$19-1))*C$67+INDEX($F$72:$F$78,MIN(F$92,6)+1)+IF($C$16="Mensual fijo",$C$14/$C$7,0)) -> 21218.655 | G105: =(G$92*C$51)-(MIN(G$92,$C$19-1)*C$66+MAX(0,G$92-($C$19-1))*C$67+INDEX($F$72:$F$78,MIN(G$92,6)+1)+IF($C$16="Mensual fijo",$C$14/$C$7,0)) -> 87156.754 | H105: =(H$92*C$51)-(MIN(H$92,$C$19-1)*C$66+MAX(0,H$92-($C$19-1))*C$67+INDEX($F$72:$F$78,MIN(H$92,6)+1)+IF($C$16="Mensual fijo",$C$14/$C$7,0)) -> 112440.27 | I105: =(I$92*C$51)-(MIN(I$92,$C$19-1)*C$66+MAX(0,I$92-($C$19-1))*C$67+INDEX($F$72:$F$78,MIN(I$92,6)+1)+IF($C$16="Mensual fijo",$C$14/$C$7,0)) -> 137723.78 | J105: =(J$92*C$51)-(MIN(J$92,$C$19-1)*C$66+MAX(0,J$92-($C$19-1))*C$67+INDEX($F$72:$F$78,MIN(J$92,6)+1)+IF($C$16="Mensual fijo",$C$14/$C$7,0)) -> 163007.29 | K105: =(K$92*C$51)-(MIN(K$92,$C$19-1)*C$66+MAX(0,K$92-($C$19-1))*C$67+INDEX($F$72:$F$78,MIN(K$92,6)+1)+IF($C$16="Mensual fijo",$C$14/$C$7,0)) -> 188290.81 | L105: =(L$92*C$51)-(MIN(L$92,$C$19-1)*C$66+MAX(0,L$92-($C$19-1))*C$67+INDEX($F$72:$F$78,MIN(L$92,6)+1)+IF($C$16="Mensual fijo",$C$14/$C$7,0)) -> 213574.32 | M105: =(M$92*C$51)-(MIN(M$92,$C$19-1)*C$66+MAX(0,M$92-($C$19-1))*C$67+INDEX($F$72:$F$78,MIN(M$92,6)+1)+IF($C$16="Mensual fijo",$C$14/$C$7,0)) -> 238857.84 | N105: =(N$92*C$51)-(MIN(N$92,$C$19-1)*C$66+MAX(0,N$92-($C$19-1))*C$67+INDEX($F$72:$F$78,MIN(N$92,6)+1)+IF($C$16="Mensual fijo",$C$14/$C$7,0)) -> 264141.35 | O105: =IFERROR(INDEX($C$92:$N$92,MATCH(1,INDEX(--(C105:N105>=0),0),0)),"no cruza") -> 4
B106: Ecotransur · 0,1–5 km | C106: =(C$92*D$51)-(MIN(C$92,$C$19-1)*D$66+MAX(0,C$92-($C$19-1))*D$67+INDEX($F$72:$F$78,MIN(C$92,6)+1)+IF($C$16="Mensual fijo",$C$14/$C$7,0)) -> -180140.37 | D106: =(D$92*D$51)-(MIN(D$92,$C$19-1)*D$66+MAX(0,D$92-($C$19-1))*D$67+INDEX($F$72:$F$78,MIN(D$92,6)+1)+IF($C$16="Mensual fijo",$C$14/$C$7,0)) -> -117747 | E106: =(E$92*D$51)-(MIN(E$92,$C$19-1)*D$66+MAX(0,E$92-($C$19-1))*D$67+INDEX($F$72:$F$78,MIN(E$92,6)+1)+IF($C$16="Mensual fijo",$C$14/$C$7,0)) -> -55353.632 | F106: =(F$92*D$51)-(MIN(F$92,$C$19-1)*D$66+MAX(0,F$92-($C$19-1))*D$67+INDEX($F$72:$F$78,MIN(F$92,6)+1)+IF($C$16="Mensual fijo",$C$14/$C$7,0)) -> 7039.7365 | G106: =(G$92*D$51)-(MIN(G$92,$C$19-1)*D$66+MAX(0,G$92-($C$19-1))*D$67+INDEX($F$72:$F$78,MIN(G$92,6)+1)+IF($C$16="Mensual fijo",$C$14/$C$7,0)) -> 69433.105 | H106: =(H$92*D$51)-(MIN(H$92,$C$19-1)*D$66+MAX(0,H$92-($C$19-1))*D$67+INDEX($F$72:$F$78,MIN(H$92,6)+1)+IF($C$16="Mensual fijo",$C$14/$C$7,0)) -> 109407.02 | I106: =(I$92*D$51)-(MIN(I$92,$C$19-1)*D$66+MAX(0,I$92-($C$19-1))*D$67+INDEX($F$72:$F$78,MIN(I$92,6)+1)+IF($C$16="Mensual fijo",$C$14/$C$7,0)) -> 149380.94 | J106: =(J$92*D$51)-(MIN(J$92,$C$19-1)*D$66+MAX(0,J$92-($C$19-1))*D$67+INDEX($F$72:$F$78,MIN(J$92,6)+1)+IF($C$16="Mensual fijo",$C$14/$C$7,0)) -> 189354.86 | K106: =(K$92*D$51)-(MIN(K$92,$C$19-1)*D$66+MAX(0,K$92-($C$19-1))*D$67+INDEX($F$72:$F$78,MIN(K$92,6)+1)+IF($C$16="Mensual fijo",$C$14/$C$7,0)) -> 229328.78 | L106: =(L$92*D$51)-(MIN(L$92,$C$19-1)*D$66+MAX(0,L$92-($C$19-1))*D$67+INDEX($F$72:$F$78,MIN(L$92,6)+1)+IF($C$16="Mensual fijo",$C$14/$C$7,0)) -> 269302.7 | M106: =(M$92*D$51)-(MIN(M$92,$C$19-1)*D$66+MAX(0,M$92-($C$19-1))*D$67+INDEX($F$72:$F$78,MIN(M$92,6)+1)+IF($C$16="Mensual fijo",$C$14/$C$7,0)) -> 309276.62 | N106: =(N$92*D$51)-(MIN(N$92,$C$19-1)*D$66+MAX(0,N$92-($C$19-1))*D$67+INDEX($F$72:$F$78,MIN(N$92,6)+1)+IF($C$16="Mensual fijo",$C$14/$C$7,0)) -> 349250.54 | O106: =IFERROR(INDEX($C$92:$N$92,MATCH(1,INDEX(--(C106:N106>=0),0),0)),"no cruza") -> 4
...

Sheet Método
B1: Método: cómo está armado el costo de cada modelo y qué se cancela
B2: Se lee antes del Simulador. Lo que decide el resultado es cuántas movilizaciones caen en cada mes, no el promedio.
B4: 1. CLASIFICACIÓN DE CADA RENGLÓN DE COSTO
B5: Renglón | C5: Modelo | D5: Tipo | E5: Umbral | F5: Nota
B6: Tarifa por movilización (Work Order) | C6: Work Order | D6: Variable por movilización; escalón por rango | E6: Límites de rango 0,2 / 5 / 10 km | F6: No es monótona: 5–10 km (95.374) cuesta menos que 0,1–5 km (98.663).
B7: Tarifa con tope | C7: Work Order | D7: Acotada arriba y abajo | E7: Tope superior = tarifa del Excel (movilización rápida); si tarda más, tarifa fija menor | F7: El WO nunca paga más que la tarifa del Excel, tarde lo que tarde. Comparar contra el tope es el escenario más caro del WO, es decir, el más favorable al tercerizado.
B8: Recargo de señalizadoras faltantes | C8: Work Order | D8: Variable; escalón 1 o 2 turnos | E8: 12 h = 1 turno; más de 12 h = 2 turnos | F8: 4 personas por turno × 375.000 COP (Cot. 1255 p. 5).
B9: Tarifa del transportador | C9: Tercerizado | D9: Variable; escalón por rango | E9: Misma localización / 5 / 10 / 20 km | F9: Petro Star no cotiza más de 20 km: no hay tarifa por encima de ese límite.
B10: Descuento desde la 6ª del mes | C10: Tercerizado | D10: Salto según el número de la movilización en el mes | E10: 6ª movilización del mes | F10: Petro Star: 50 % de la tarifa. Ecotransur: solo equipos. Lump Sum: sin descuento (evaluación principal).
B11: Cargo fijo mensual (nómina + disponibilidad) | C11: Tercerizado | D11: Escalón decreciente; fijo mensual | E11: Petro Star 0–5 movs; Ecotransur 0–4 movs | F11: Petro Star todavía cobra con 5 movs (p. 4); Ecotransur no cobra desde la 5ª.
B12: Taladro durante la movilización | C12: Tercerizado | D12: Variable por hora | E12: Horas por rango (12/18/24/28) | F12: 34.944 USD/día. Bajo el WO no se paga (premisa SierraCol).
B13: Mes bloqueado (no se puede mover) | C13: Tercerizado | D13: Fijo mensual | E13: Mes con 0 movilizaciones y contrato vigente | F13: Petro Star 176.968 · Ecotransur 242.534 USD por mes (cargo de 0 movilizaciones + Truck Manager). Con el WO, 0.
B14: Truck Manager | C14: Tercerizado | D14: Fijo mensual (así se modela) | E14: 60 M COP por cada mes de campaña | F14: El Excel lo prorratea a 6 movs/mes (2.702,70 USD); con menos de 6 movs/mes ese prorrateo lo subestima. Por encima lo sobreestima.
B15: Horas excedidas sobre el tiempo estipulado | C15: Tercerizado | D15: Salto al pasar el tiempo cotizado | E15: Tiempo total 12/24/36/36 h | F15: Se paga el taladro por hora (1.456 USD) y además equipos y señalizadores por hora (~1.357 USD; Cot. 1255 p. 5). Con el WO, 0.
B16: Bandas de horas por ítem (Opción A/B) | C16: Tercerizado (Ecotransur) | D16: Salto por banda de horas | E16: 8–12 / ≤14 / 14–18 / 18–24 / ≤22 h | F16: El formato del Ítem 1 no viene adjunto: el Excel usa ítems 'más de X horas'.
B17: Personal, turnos o equipos fuera del mínimo | C17: Ambos | D17: Variable | E17: Lo que exceda el equipo mínimo | F17: Premisa: se cancela entre modelos (adicionales 0 %). Ver Pendientes.
B19: 2. ¿QUÉ VARIABLE AFECTA A LOS DOS MODELOS Y QUÉ SE CANCELA?
B20: Variable | C20: ¿A quién afecta? | D20: ¿Se cancela? | E20: Por qué
B21: Número de pozos de la campaña | C21: Ambos | D21: No | E21: El WO crece lineal; el tercerizado tiene umbrales mensuales. Entra completo al diferencial.
B22: Frecuencia mensual de movilizaciones | C22: Solo tercerizado | D22: No | E22: El WO cobra por movilización, no por mes. Es la variable que define la frontera.
B23: Rango de distancia | C23: Ambos, distinto | D23: No | E23: Las tarifas no se mueven igual: pasar de 0,1–5 a 5–10 km abarata el WO y encarece el tercerizado.
B24: Adicionales / imprevistos | C24: Ambos | D24: Sí (premisa) | E24: Se pone 0 % en ambos. Si no se cancelan, el residuo cae sobre el tercerizado (ver Sensibilidad).
B25: Taladro parado por NPT de perforación | C25: Ambos | D25: Sí | E25: La tarifa del taladro durante la perforación la rige su contrato en los dos modelos.
B26: Demoras dentro de la movilización | C26: Solo tercerizado | D26: No | E26: El WO es suma cerrada. En el tercerizado se paga el taladro por hora y, con Petro Star, equipos y nómina (cláusula 7).
B27: TRM | C27: Solo tercerizado | D27: No | E27: Las ofertas están en COP; el WO en USD. TRM alta favorece al tercerizado.
B28: Tarifa del taladro | C28: Solo tercerizado | D28: No | E28: Bajo el WO no se pagan horas de taladro.
B29: Señalizadoras | C29: Solo WO (recargo) | D29: No | E29: Las ofertas ya incluyen 20; el WO tiene 12.
B30: Truck Manager | C30: Solo tercerizado | D30: No | E30: Premisa SierraCol.
B32: 3. NPT: POR QUÉ CANAL AFECTA A CADA MODELO
B33: NPT de perforación (pozo): el taladro está parado o perforando más días. Su tarifa diaria se paga igual en los dos modelos, así que ese costo se cancela. Lo que NO se cancela es el efecto sobre la frecuencia: menos movilizaciones por mes. Al WO no le pasa nada (paga por movilización). Al tercerizado le cambia la factura: si el mes cae por debajo de 5 (Ecotransur) o de 6 (Petro Star), aparece el cargo fijo y se pierde el descuento. Canal: frecuencia, no horas.
B34: NPT de movilización (demora en el traslado): en el WO lo absorbe el contratista del taladro (suma global cerrada). En el tercerizado carga horas de taladro (1.456 USD/h) y, con Petro Star, si la demora no es atribuible al transportador, también equipos y nómina (Cot. 1255 p. 5, cláusula 7; a tarifas horarias de la p. 5 la flota mínima más 20 señalizadores suma unos 1.357 USD/h). Ecotransur no trae esa cláusula, pero factura aparte turnos extra. Canal: horas, residuo completo sobre el tercerizado.
B35: Lo único medido en los archivos es el sobretiempo de movilización de los logs (hojas Real 2024 / Real 2025): misma localización excede las 12 h del Excel en 10 de 23 movs (2024) y 10 de 11 (2025); 0,1–5 km excede las 18 h en 11 de 28 y 10 de 17; 5–10 km y más de 10 km en 2024 quedaron por debajo de lo supuesto. No hay NPT de perforación ni plan de pozos: se deja editable en 0 % (Simulador C23) y se muestra su sensibilidad.
B37: 4. VERIFICACIONES OBLIGATORIAS
B38: Verificación | C38: Resultado | D38: Detalle
B39: Recalcular fórmulas heredadas | C39: Hecho | D39: Las filas amarillas 'Costo Suma Global' (31, 57, 83, 109) se reproducen al centavo (hoja Reconciliación). El recargo de señalizadoras da 405,41 / 810,81 USD. El total WO de la campaña es 3.130.187 USD (= M18); la nota J55 cita 3.107.890.
B40: Monotonía de tarifas con la distancia | C40: Hallazgo | D40: Petro Star, Lump Sum y Ecotransur crecen con la distancia. El WO no: 5–10 km < 0,1–5 km. Si los 20 pozos fueran de 5–10 km, el ahorro de Petro Star cae unos 324.000 USD y el de Ecotransur unos 430.000 USD.
B41: Cobertura de más de 20 km | C41: Brecha | D41: Petro Star cotiza 10–20 km. El log 2024 tiene 1 movimiento de 22,1 km (pozo 5681); 2025 ninguno (máx. 14,6 km). Se valoró con la tarifa de 10–20 km y queda marcado.
B42: Horas de Petro Star vs Excel | C42: Diferencia | D42: Cotización: 12 / 24 / 36 / 36 h. Excel: 12 / 18 / 24 / 28 h. Por movilización: 0 / 8.736 / 17.472 / 11.648 USD de taladro. En la campaña base (20 pozos en 0,1–5 km): 174.720 USD. Editable en Simulador fila 39.
B43: IVA del Lump Sum | C43: Fuera de alcance | D43: Por instrucción de SierraCol se trabaja sin IVA. Si el IVA del 50 % de alquiler no fuera descontable, el Lump Sum costaría unos 225.000 USD más en la campaña base.
B44: Celdas sueltas F155 y F156 | C44: No usadas | D44: Valores 8 y 15 sin rótulo, dentro del bloque 5.6. No entran en ningún cálculo de este simulador.

Sheet Real 2024
B1: Campaña real 2024 · taladro GRS 110 · cómo habría funcionado cada modelo
B2: Movimientos de Movilizaciones_2024.xlsx (detalle, columnas D, C, F, G, H), en orden de fecha. Los meses sin registro no se cuentan (campaña parada). Parámetros y tarifas vienen de la hoja Simulador (verde). Columnas M–P usan las horas del Excel; Q–T, las horas reales del log. Ahorro positivo = el tercerizado cuesta menos.
W3: Modelo | X3: Costo con horas Excel (USD) | Y3: Ahorro con horas Excel (USD) | Z3: Costo con horas reales (USD) | AA3: Ahorro con horas reales (USD)
B4: Resumen | W4: Work Order | X4: =L79 -> 6424357.4 | Z4: =L79 -> 6424357.4
W5: Petro Star tarifa normal | X5: =M79+$H$95+$J$95 -> 5378820.6 | Y5: =$X$4-X5 -> 1045536.9 | Z5: =Q79+$H$95+$J$95 -> 5288334.2 | AA5: =$Z$4-Z5 -> 1136023.3
W6: Petro Star Lump Sum | X6: =N79+$H$95+$J$95 -> 7487995.9 | Y6: =$X$4-X6 -> -1063638.5 | Z6: =R79+$H$95+$J$95 -> 7397509.5 | AA6: =$Z$4-Z6 -> -973152.06
B7: Fecha | C7: Pozo | D7: Km | E7: Rango (log) | F7: Rango nº | G7: Mes | H7: Nº en el mes | I7: Horas reales | J7: Horas Excel | K7: Sobretiempo (h) | L7: Work Order (USD) | M7: Petro Star tarifa normal, horas Excel (USD) | N7: Petro Star Lump Sum, horas Excel (USD) | O7: Lump Sum con descuento (referencia), horas Excel (USD) | P7: Ecotransur, horas Excel (USD) | Q7: Petro Star tarifa normal, horas reales (USD) | R7: Petro Star Lump Sum, horas reales (USD) | S7: Lump Sum con descuento (referencia), horas reales (USD) | T7: Ecotransur, horas reales (USD) | U7: Nota | W7: Lump Sum con descuento (ref.) | X7: =O79+$H$95+$J$95 -> 6739376.7 | Y7: =$X$4-X7 -> -315019.27 | Z7: =S79+$H$95+$J$95 -> 6648890.3 | AA7: =$Z$4-Z7 -> -224532.87
B8: 45298 | C8: 5681 | D8: 22.1 | E8: 10+ km | F8: =MATCH(E8,{"Misma locación","0.15 - 5 km","5 - 10 km","10+ km"},0) -> 4 | G8: =MONTH(B8) -> 1 | H8: =COUNTIF($G$8:G8,G8) -> 1 | I8: 22 | J8: =INDEX(Simulador!$C$39:$F$39,F8) -> 28 | K8: =IF(I8="","",I8-J8) -> -6 | L8: =INDEX(Simulador!$C$51:$F$51,F8) -> 110984.81 | M8: =IF(H8>=Simulador!$C$19,INDEX(Simulador!$C$63:$F$63,F8),INDEX(Simulador!$C$62:$F$62,F8)) -> 107379.62 | N8: =INDEX(Simulador!$C$64:$F$64,F8) -> 152876.36 | O8: =IF(H8>=Simulador!$C$19,INDEX(Simulador!$C$65:$F$65,F8),INDEX(Simulador!$C$64:$F$64,F8)) -> 152876.36 | P8: =IF(H8>=Simulador!$C$19,INDEX(Simulador!$C$67:$F$67,F8),INDEX(Simulador!$C$66:$F$66,F8)) -> 109162.6 | Q8: =M8+(IF(I8="",J8+INDEX(Simulador!$C$40:$F$40,F8),I8)-J8-INDEX(Simulador!$C$40:$F$40,F8))*Simulador!$C$9-INDEX(Simulador!$C$69:$F$69,F8)+IF(Simulador!$N$7="Sí",MAX(0,IF(I8="",J8+INDEX(Simulador!$C$40:$F$40,F8),I8)-INDEX(Simulador!$C$41:$F$41,F8))*(INDEX(Simulador!$C$68:$F$68,F8)+Simulador!$N$8)/Simulador!$C$7,0) -> 98643.621 | R8: =N8+(IF(I8="",J8+INDEX(Simulador!$C$40:$F$40,F8),I8)-J8-INDEX(Simulador!$C$40:$F$40,F8))*Simulador!$C$9-INDEX(Simulador!$C$69:$F$69,F8)+IF(Simulador!$N$7="Sí",MAX(0,IF(I8="",J8+INDEX(Simulador!$C$40:$F$40,F8),I8)-INDEX(Simulador!$C$41:$F$41,F8))*(INDEX(Simulador!$C$68:$F$68,F8)+Simulador!$N$8)/Simulador!$C$7,0) -> 144140.36 | S8: =O8+(IF(I8="",J8+INDEX(Simulador!$C$40:$F$40,F8),I8)-J8-INDEX(Simulador!$C$40:$F$40,F8))*Simulador!$C$9-INDEX(Simulador!$C$69:$F$69,F8)+IF(Simulador!$N$7="Sí",MAX(0,IF(I8="",J8+INDEX(Simulador!$C$40:$F$40,F8),I8)-INDEX(Simulador!$C$41:$F$41,F8))*(INDEX(Simulador!$C$68:$F$68,F8)+Simulador!$N$8)/Simulador!$C$7,0) -> 144140.36 | T8: =P8+(IF(I8="",J8+INDEX(Simulador!$C$40:$F$40,F8),I8)-J8-INDEX(Simulador!$C$40:$F$40,F8))*Simulador!$C$9-INDEX(Simulador!$C$69:$F$69,F8)+IF(Simulador!$N$7="Sí",MAX(0,IF(I8="",J8+INDEX(Simulador!$C$40:$F$40,F8),I8)-INDEX(Simulador!$C$41:$F$41,F8))*(INDEX(Simulador!$C$68:$F$68,F8)+Simulador!$N$8)/Simulador!$C$7,0) -> 100426.6 | U8: Más de 20 km: Petro Star no tiene tarifa (se usa la de 10–20 km) | W8: Ecotransur | X8: =P79+$I$95+$J$95 -> 5518219 | Y8: =$X$4-X8 -> 906138.47 | Z8: =T79+$I$95+$J$95 -> 5427732.6 | AA8: =$Z$4-Z8 -> 996624.87
B9: 45301 | C9: 5270 | D9: 4.1 | E9: 0.15 - 5 km | F9: =MATCH(E9,{"Misma locación","0.15 - 5 km","5 - 10 km","10+ km"},0) -> 2 | G9: =MONTH(B9) -> 1 | H9: =COUNTIF($G$8:G9,G9) -> 2 | I9: 19.5 | J9: =INDEX(Simulador!$C$39:$F$39,F9) -> 18 | K9: =IF(I9="","",I9-J9) -> 1.5 | L9: =INDEX(Simulador!$C$51:$F$51,F9) -> 99473.811 | M9: =IF(H9>=Simulador!$C$19,INDEX(Simulador!$C$63:$F$63,F9),INDEX(Simulador!$C$62:$F$62,F9)) -> 85898.023 | N9: =INDEX(Simulador!$C$64:$F$64,F9) -> 108447.11 | O9: =IF(H9>=Simulador!$C$19,INDEX(Simulador!$C$65:$F$65,F9),INDEX(Simulador!$C$64:$F$64,F9)) -> 108447.11 | P9: =IF(H9>=Simulador!$C$19,INDEX(Simulador!$C$67:$F$67,F9),INDEX(Simulador!$C$66:$F$66,F9)) -> 82343.946 | Q9: =M9+(IF(I9="",J9+INDEX(Simulador!$C$40:$F$40,F9),I9)-J9-INDEX(Simulador!$C$40:$F$40,F9))*Simulador!$C$9-INDEX(Simulador!$C$69:$F$69,F9)+IF(Simulador!$N$7="Sí",MAX(0,IF(I9="",J9+INDEX(Simulador!$C$40:$F$40,F9),I9)-INDEX(Simulador!$C$41:$F$41,F9))*(INDEX(Simulador!$C$68:$F$68,F9)+Simulador!$N$8)/Simulador!$C$7,0) -> 88082.023 | R9: =N9+(IF(I9="",J9+INDEX(Simulador!$C$40:$F$40,F9),I9)-J9-INDEX(Simulador!$C$40:$F$40,F9))*Simulador!$C$9-INDEX(Simulador!$C$69:$F$69,F9)+IF(Simulador!$N$7="Sí",MAX(0,IF(I9="",J9+INDEX(Simulador!$C$40:$F$40,F9),I9)-INDEX(Simulador!$C$41:$F$41,F9))*(INDEX(Simulador!$C$68:$F$68,F9)+Simulador!$N$8)/Simulador!$C$7,0) -> 110631.11 | S9: =O9+(IF(I9="",J9+INDEX(Simulador!$C$40:$F$40,F9),I9)-J9-INDEX(Simulador!$C$40:$F$40,F9))*Simulador!$C$9-INDEX(Simulador!$C$69:$F$69,F9)+IF(Simulador!$N$7="Sí",MAX(0,IF(I9="",J9+INDEX(Simulador!$C$40:$F$40,F9),I9)-INDEX(Simulador!$C$41:$F$41,F9))*(INDEX(Simulador!$C$68:$F$68,F9)+Simulador!$N$8)/Simulador!$C$7,0) -> 110631.11 | T9: =P9+(IF(I9="",J9+INDEX(Simulador!$C$40:$F$40,F9),I9)-J9-INDEX(Simulador!$C$40:$F$40,F9))*Simulador!$C$9-INDEX(Simulador!$C$69:$F$69,F9)+IF(Simulador!$N$7="Sí",MAX(0,IF(I9="",J9+INDEX(Simulador!$C$40:$F$40,F9),I9)-INDEX(Simulador!$C$41:$F$41,F9))*(INDEX(Simulador!$C$68:$F$68,F9)+Simulador!$N$8)/Simulador!$C$7,0) -> 84527.946 | W9: Movilizaciones | X9: =COUNT(B8:B77) -> 70
B10: 45305 | C10: 5077 | D10: 4.1 | E10: 0.15 - 5 km | F10: =MATCH(E10,{"Misma locación","0.15 - 5 km","5 - 10 km","10+ km"},0) -> 2 | G10: =MONTH(B10) -> 1 | H10: =COUNTIF($G$8:G10,G10) -> 3 | I10: 15.75 | J10: =INDEX(Simulador!$C$39:$F$39,F10) -> 18 | K10: =IF(I10="","",I10-J10) -> -2.25 | L10: =INDEX(Simulador!$C$51:$F$51,F10) -> 99473.811 | M10: =IF(H10>=Simulador!$C$19,INDEX(Simulador!$C$63:$F$63,F10),INDEX(Simulador!$C$62:$F$62,F10)) -> 85898.023 | N10: =INDEX(Simulador!$C$64:$F$64,F10) -> 108447.11 | O10: =IF(H10>=Simulador!$C$19,INDEX(Simulador!$C$65:$F$65,F10),INDEX(Simulador!$C$64:$F$64,F10)) -> 108447.11 | P10: =IF(H10>=Simulador!$C$19,INDEX(Simulador!$C$67:$F$67,F10),INDEX(Simulador!$C$66:$F$66,F10)) -> 82343.946 | Q10: =M10+(IF(I10="",J10+INDEX(Simulador!$C$40:$F$40,F10),I10)-J10-INDEX(Simulador!$C$40:$F$40,F10))*Simulador!$C$9-INDEX(Simulador!$C$69:$F$69,F10)+IF(Simulador!$N$7="Sí",MAX(0,IF(I10="",J10+INDEX(Simulador!$C$40:$F$40,F10),I10)-INDEX(Simulador!$C$41:$F$41,F10))*(INDEX(Simulador!$C$68:$F$68,F10)+Simulador!$N$8)/Simulador!$C$7,0) -> 82622.023 | R10: =N10+(IF(I10="",J10+INDEX(Simulador!$C$40:$F$40,F10),I10)-J10-INDEX(Simulador!$C$40:$F$40,F10))*Simulador!$C$9-INDEX(Simulador!$C$69:$F$69,F10)+IF(Simulador!$N$7="Sí",MAX(0,IF(I10="",J10+INDEX(Simulador!$C$40:$F$40,F10),I10)-INDEX(Simulador!$C$41:$F$41,F10))*(INDEX(Simulador!$C$68:$F$68,F10)+Simulador!$N$8)/Simulador!$C$7,0) -> 105171.11 | S10: =O10+(IF(I10="",J10+INDEX(Simulador!$C$40:$F$40,F10),I10)-J10-INDEX(Simulador!$C$40:$F$40,F10))*Simulador!$C$9-INDEX(Simulador!$C$69:$F$69,F10)+IF(Simulador!$N$7="Sí",MAX(0,IF(I10="",J10+INDEX(Simulador!$C$40:$F$40,F10),I10)-INDEX(Simulador!$C$41:$F$41,F10))*(INDEX(Simulador!$C$68:$F$68,F10)+Simulador!$N$8)/Simulador!$C$7,0) -> 105171.11 | T10: =P10+(IF(I10="",J10+INDEX(Simulador!$C$40:$F$40,F10),I10)-J10-INDEX(Simulador!$C$40:$F$40,F10))*Simulador!$C$9-INDEX(Simulador!$C$69:$F$69,F10)+IF(Simulador!$N$7="Sí",MAX(0,IF(I10="",J10+INDEX(Simulador!$C$40:$F$40,F10),I10)-INDEX(Simulador!$C$41:$F$41,F10))*(INDEX(Simulador!$C$68:$F$68,F10)+Simulador!$N$8)/Simulador!$C$7,0) -> 79067.946 | W10: Meses con movilizaciones | X10: =COUNTIF(C84:C94,">0") -> 11
B11: 45309 | C11: 5136 | D11: 3.25 | E11: 0.15 - 5 km | F11: =MATCH(E11,{"Misma locación","0.15 - 5 km","5 - 10 km","10+ km"},0) -> 2 | G11: =MONTH(B11) -> 1 | H11: =COUNTIF($G$8:G11,G11) -> 4 | J11: =INDEX(Simulador!$C$39:$F$39,F11) -> 18 | K11: =IF(I11="","",I11-J11) | L11: =INDEX(Simulador!$C$51:$F$51,F11) -> 99473.811 | M11: =IF(H11>=Simulador!$C$19,INDEX(Simulador!$C$63:$F$63,F11),INDEX(Simulador!$C$62:$F$62,F11)) -> 85898.023 | N11: =INDEX(Simulador!$C$64:$F$64,F11) -> 108447.11 | O11: =IF(H11>=Simulador!$C$19,INDEX(Simulador!$C$65:$F$65,F11),INDEX(Simulador!$C$64:$F$64,F11)) -> 108447.11 | P11: =IF(H11>=Simulador!$C$19,INDEX(Simulador!$C$67:$F$67,F11),INDEX(Simulador!$C$66:$F$66,F11)) -> 82343.946 | Q11: =M11+(IF(I11="",J11+INDEX(Simulador!$C$40:$F$40,F11),I11)-J11-INDEX(Simulador!$C$40:$F$40,F11))*Simulador!$C$9-INDEX(Simulador!$C$69:$F$69,F11)+IF(Simulador!$N$7="Sí",MAX(0,IF(I11="",J11+INDEX(Simulador!$C$40:$F$40,F11),I11)-INDEX(Simulador!$C$41:$F$41,F11))*(INDEX(Simulador!$C$68:$F$68,F11)+Simulador!$N$8)/Simulador!$C$7,0) -> 85898.023 | R11: =N11+(IF(I11="",J11+INDEX(Simulador!$C$40:$F$40,F11),I11)-J11-INDEX(Simulador!$C$40:$F$40,F11))*Simulador!$C$9-INDEX(Simulador!$C$69:$F$69,F11)+IF(Simulador!$N$7="Sí",MAX(0,IF(I11="",J11+INDEX(Simulador!$C$40:$F$40,F11),I11)-INDEX(Simulador!$C$41:$F$41,F11))*(INDEX(Simulador!$C$68:$F$68,F11)+Simulador!$N$8)/Simulador!$C$7,0) -> 108447.11 | S11: =O11+(IF(I11="",J11+INDEX(Simulador!$C$40:$F$40,F11),I11)-J11-INDEX(Simulador!$C$40:$F$40,F11))*Simulador!$C$9-INDEX(Simulador!$C$69:$F$69,F11)+IF(Simulador!$N$7="Sí",MAX(0,IF(I11="",J11+INDEX(Simulador!$C$40:$F$40,F11),I11)-INDEX(Simulador!$C$41:$F$41,F11))*(INDEX(Simulador!$C$68:$F$68,F11)+Simulador!$N$8)/Simulador!$C$7,0) -> 108447.11 | T11: =P11+(IF(I11="",J11+INDEX(Simulador!$C$40:$F$40,F11),I11)-J11-INDEX(Simulador!$C$40:$F$40,F11))*Simulador!$C$9-INDEX(Simulador!$C$69:$F$69,F11)+IF(Simulador!$N$7="Sí",MAX(0,IF(I11="",J11+INDEX(Simulador!$C$40:$F$40,F11),I11)-INDEX(Simulador!$C$41:$F$41,F11))*(INDEX(Simulador!$C$68:$F$68,F11)+Simulador!$N$8)/Simulador!$C$7,0) -> 82343.946 | U11: Sin horas en el log: se usan las del Excel | W11: Promedio movs/mes (meses activos) | X11: =X9/X10 -> 6.3636364
B12: 45312 | C12: 5106 | D12: 4.9 | E12: 0.15 - 5 km | F12: =MATCH(E12,{"Misma locación","0.15 - 5 km","5 - 10 km","10+ km"},0) -> 2 | G12: =MONTH(B12) -> 1 | H12: =COUNTIF($G$8:G12,G12) -> 5 | I12: 20 | J12: =INDEX(Simulador!$C$39:$F$39,F12) -> 18 | K12: =IF(I12="","",I12-J12) -> 2 | L12: =INDEX(Simulador!$C$51:$F$51,F12) -> 99473.811 | M12: =IF(H12>=Simulador!$C$19,INDEX(Simulador!$C$63:$F$63,F12),INDEX(Simulador!$C$62:$F$62,F12)) -> 85898.023 | N12: =INDEX(Simulador!$C$64:$F$64,F12) -> 108447.11 | O12: =IF(H12>=Simulador!$C$19,INDEX(Simulador!$C$65:$F$65,F12),INDEX(Simulador!$C$64:$F$64,F12)) -> 108447.11 | P12: =IF(H12>=Simulador!$C$19,INDEX(Simulador!$C$67:$F$67,F12),INDEX(Simulador!$C$66:$F$66,F12)) -> 82343.946 | Q12: =M12+(IF(I12="",J12+INDEX(Simulador!$C$40:$F$40,F12),I12)-J12-INDEX(Simulador!$C$40:$F$40,F12))*Simulador!$C$9-INDEX(Simulador!$C$69:$F$69,F12)+IF(Simulador!$N$7="Sí",MAX(0,IF(I12="",J12+INDEX(Simulador!$C$40:$F$40,F12),I12)-INDEX(Simulador!$C$41:$F$41,F12))*(INDEX(Simulador!$C$68:$F$68,F12)+Simulador!$N$8)/Simulador!$C$7,0) -> 88810.023 | R12: =N12+(IF(I12="",J12+INDEX(Simulador!$C$40:$F$40,F12),I12)-J12-INDEX(Simulador!$C$40:$F$40,F12))*Simulador!$C$9-INDEX(Simulador!$C$69:$F$69,F12)+IF(Simulador!$N$7="Sí",MAX(0,IF(I12="",J12+INDEX(Simulador!$C$40:$F$40,F12),I12)-INDEX(Simulador!$C$41:$F$41,F12))*(INDEX(Simulador!$C$68:$F$68,F12)+Simulador!$N$8)/Simulador!$C$7,0) -> 111359.11 | S12: =O12+(IF(I12="",J12+INDEX(Simulador!$C$40:$F$40,F12),I12)-J12-INDEX(Simulador!$C$40:$F$40,F12))*Simulador!$C$9-INDEX(Simulador!$C$69:$F$69,F12)+IF(Simulador!$N$7="Sí",MAX(0,IF(I12="",J12+INDEX(Simulador!$C$40:$F$40,F12),I12)-INDEX(Simulador!$C$41:$F$41,F12))*(INDEX(Simulador!$C$68:$F$68,F12)+Simulador!$N$8)/Simulador!$C$7,0) -> 111359.11 | T12: =P12+(IF(I12="",J12+INDEX(Simulador!$C$40:$F$40,F12),I12)-J12-INDEX(Simulador!$C$40:$F$40,F12))*Simulador!$C$9-INDEX(Simulador!$C$69:$F$69,F12)+IF(Simulador!$N$7="Sí",MAX(0,IF(I12="",J12+INDEX(Simulador!$C$40:$F$40,F12),I12)-INDEX(Simulador!$C$41:$F$41,F12))*(INDEX(Simulador!$C$68:$F$68,F12)+Simulador!$N$8)/Simulador!$C$7,0) -> 85255.946 | W12: Meses con 6 o más movilizaciones | X12: =COUNTIF(C84:C94,">=6") -> 9
B13: 45317 | C13: 5067 | D13: 0.4 | E13: 0.15 - 5 km | F13: =MATCH(E13,{"Misma locación","0.15 - 5 km","5 - 10 km","10+ km"},0) -> 2 | G13: =MONTH(B13) -> 1 | H13: =COUNTIF($G$8:G13,G13) -> 6 | I13: 12.5 | J13: =INDEX(Simulador!$C$39:$F$39,F13) -> 18 | K13: =IF(I13="","",I13-J13) -> -5.5 | L13: =INDEX(Simulador!$C$51:$F$51,F13) -> 99473.811 | M13: =IF(H13>=Simulador!$C$19,INDEX(Simulador!$C$63:$F$63,F13),INDEX(Simulador!$C$62:$F$62,F13)) -> 56053.011 | N13: =INDEX(Simulador!$C$64:$F$64,F13) -> 108447.11 | O13: =IF(H13>=Simulador!$C$19,INDEX(Simulador!$C$65:$F$65,F13),INDEX(Simulador!$C$64:$F$64,F13)) -> 67327.553 | P13: =IF(H13>=Simulador!$C$19,INDEX(Simulador!$C$67:$F$67,F13),INDEX(Simulador!$C$66:$F$66,F13)) -> 59499.892 | Q13: =M13+(IF(I13="",J13+INDEX(Simulador!$C$40:$F$40,F13),I13)-J13-INDEX(Simulador!$C$40:$F$40,F13))*Simulador!$C$9-INDEX(Simulador!$C$69:$F$69,F13)+IF(Simulador!$N$7="Sí",MAX(0,IF(I13="",J13+INDEX(Simulador!$C$40:$F$40,F13),I13)-INDEX(Simulador!$C$41:$F$41,F13))*(INDEX(Simulador!$C$68:$F$68,F13)+Simulador!$N$8)/Simulador!$C$7,0) -> 48045.011 | R13: =N13+(IF(I13="",J13+INDEX(Simulador!$C$40:$F$40,F13),I13)-J13-INDEX(Simulador!$C$40:$F$40,F13))*Simulador!$C$9-INDEX(Simulador!$C$69:$F$69,F13)+IF(Simulador!$N$7="Sí",MAX(0,IF(I13="",J13+INDEX(Simulador!$C$40:$F$40,F13),I13)-INDEX(Simulador!$C$41:$F$41,F13))*(INDEX(Simulador!$C$68:$F$68,F13)+Simulador!$N$8)/Simulador!$C$7,0) -> 100439.11 | S13: =O13+(IF(I13="",J13+INDEX(Simulador!$C$40:$F$40,F13),I13)-J13-INDEX(Simulador!$C$40:$F$40,F13))*Simulador!$C$9-INDEX(Simulador!$C$69:$F$69,F13)+IF(Simulador!$N$7="Sí",MAX(0,IF(I13="",J13+INDEX(Simulador!$C$40:$F$40,F13),I13)-INDEX(Simulador!$C$41:$F$41,F13))*(INDEX(Simulador!$C$68:$F$68,F13)+Simulador!$N$8)/Simulador!$C$7,0) -> 59319.553 | T13: =P13+(IF(I13="",J13+INDEX(Simulador!$C$40:$F$40,F13),I13)-J13-INDEX(Simulador!$C$40:$F$40,F13))*Simulador!$C$9-INDEX(Simulador!$C$69:$F$69,F13)+IF(Simulador!$N$7="Sí",MAX(0,IF(I13="",J13+INDEX(Simulador!$C$40:$F$40,F13),I13)-INDEX(Simulador!$C$41:$F$41,F13))*(INDEX(Simulador!$C$68:$F$68,F13)+Simulador!$N$8)/Simulador!$C$7,0) -> 51491.892 | W13: Meses con menos de 5 movilizaciones | X13: =COUNTIF(C84:C94,"<5") -> 2
B14: 45321 | C14: 5023 | D14: 5.2 | E14: 5 - 10 km | F14: =MATCH(E14,{"Misma locación","0.15 - 5 km","5 - 10 km","10+ km"},0) -> 3 | G14: =MONTH(B14) -> 1 | H14: =COUNTIF($G$8:G14,G14) -> 7 | I14: 16 | J14: =INDEX(Simulador!$C$39:$F$39,F14) -> 24 | K14: =IF(I14="","",I14-J14) -> -8 | L14: =INDEX(Simulador!$C$51:$F$51,F14) -> 96184.811 | M14: =IF(H14>=Simulador!$C$19,INDEX(Simulador!$C$63:$F$63,F14),INDEX(Simulador!$C$62:$F$62,F14)) -> 67168.729 | N14: =INDEX(Simulador!$C$64:$F$64,F14) -> 135930.45 | O14: =IF(H14>=Simulador!$C$19,INDEX(Simulador!$C$65:$F$65,F14),INDEX(Simulador!$C$64:$F$64,F14)) -> 85437.226 | P14: =IF(H14>=Simulador!$C$19,INDEX(Simulador!$C$67:$F$67,F14),INDEX(Simulador!$C$66:$F$66,F14)) -> 72512.919 | Q14: =M14+(IF(I14="",J14+INDEX(Simulador!$C$40:$F$40,F14),I14)-J14-INDEX(Simulador!$C$40:$F$40,F14))*Simulador!$C$9-INDEX(Simulador!$C$69:$F$69,F14)+IF(Simulador!$N$7="Sí",MAX(0,IF(I14="",J14+INDEX(Simulador!$C$40:$F$40,F14),I14)-INDEX(Simulador!$C$41:$F$41,F14))*(INDEX(Simulador!$C$68:$F$68,F14)+Simulador!$N$8)/Simulador!$C$7,0) -> 55520.729 | R14: =N14+(IF(I14="",J14+INDEX(Simulador!$C$40:$F$40,F14),I14)-J14-INDEX(Simulador!$C$40:$F$40,F14))*Simulador!$C$9-INDEX(Simulador!$C$69:$F$69,F14)+IF(Simulador!$N$7="Sí",MAX(0,IF(I14="",J14+INDEX(Simulador!$C$40:$F$40,F14),I14)-INDEX(Simulador!$C$41:$F$41,F14))*(INDEX(Simulador!$C$68:$F$68,F14)+Simulador!$N$8)/Simulador!$C$7,0) -> 124282.45 | S14: =O14+(IF(I14="",J14+INDEX(Simulador!$C$40:$F$40,F14),I14)-J14-INDEX(Simulador!$C$40:$F$40,F14))*Simulador!$C$9-INDEX(Simulador!$C$69:$F$69,F14)+IF(Simulador!$N$7="Sí",MAX(0,IF(I14="",J14+INDEX(Simulador!$C$40:$F$40,F14),I14)-INDEX(Simulador!$C$41:$F$41,F14))*(INDEX(Simulador!$C$68:$F$68,F14)+Simulador!$N$8)/Simulador!$C$7,0) -> 73789.226 | T14: =P14+(IF(I14="",J14+INDEX(Simulador!$C$40:$F$40,F14),I14)-J14-INDEX(Simulador!$C$40:$F$40,F14))*Simulador!$C$9-INDEX(Simulador!$C$69:$F$69,F14)+IF(Simulador!$N$7="Sí",MAX(0,IF(I14="",J14+INDEX(Simulador!$C$40:$F$40,F14),I14)-INDEX(Simulador!$C$41:$F$41,F14))*(INDEX(Simulador!$C$68:$F$68,F14)+Simulador!$N$8)/Simulador!$C$7,0) -> 60864.919
B15: 45325 | C15: 5002 | D15: 0.0064007998 | E15: Misma locación | F15: =MATCH(E15,{"Misma locación","0.15 - 5 km","5 - 10 km","10+ km"},0) -> 1 | G15: =MONTH(B15) -> 2 | H15: =COUNTIF($G$8:G15,G15) -> 1 | I15: 8 | J15: =INDEX(Simulador!$C$39:$F$39,F15) -> 12 | K15: =IF(I15="","",I15-J15) -> -4 | L15: =INDEX(Simulador!$C$51:$F$51,F15) -> 76047.405 | M15: =IF(H15>=Simulador!$C$19,INDEX(Simulador!$C$63:$F$63,F15),INDEX(Simulador!$C$62:$F$62,F15)) -> 55414.011 | N15: =INDEX(Simulador!$C$64:$F$64,F15) -> 65678.455 | O15: =IF(H15>=Simulador!$C$19,INDEX(Simulador!$C$65:$F$65,F15),INDEX(Simulador!$C$64:$F$64,F15)) -> 65678.455 | P15: =IF(H15>=Simulador!$C$19,INDEX(Simulador!$C$67:$F$67,F15),INDEX(Simulador!$C$66:$F$66,F15)) -> 55372.811 | Q15: =M15+(IF(I15="",J15+INDEX(Simulador!$C$40:$F$40,F15),I15)-J15-INDEX(Simulador!$C$40:$F$40,F15))*Simulador!$C$9-INDEX(Simulador!$C$69:$F$69,F15)+IF(Simulador!$N$7="Sí",MAX(0,IF(I15="",J15+INDEX(Simulador!$C$40:$F$40,F15),I15)-INDEX(Simulador!$C$41:$F$41,F15))*(INDEX(Simulador!$C$68:$F$68,F15)+Simulador!$N$8)/Simulador!$C$7,0) -> 49590.011 | R15: =N15+(IF(I15="",J15+INDEX(Simulador!$C$40:$F$40,F15),I15)-J15-INDEX(Simulador!$C$40:$F$40,F15))*Simulador!$C$9-INDEX(Simulador!$C$69:$F$69,F15)+IF(Simulador!$N$7="Sí",MAX(0,IF(I15="",J15+INDEX(Simulador!$C$40:$F$40,F15),I15)-INDEX(Simulador!$C$41:$F$41,F15))*(INDEX(Simulador!$C$68:$F$68,F15)+Simulador!$N$8)/Simulador!$C$7,0) -> 59854.455 | S15: =O15+(IF(I15="",J15+INDEX(Simulador!$C$40:$F$40,F15),I15)-J15-INDEX(Simulador!$C$40:$F$40,F15))*Simulador!$C$9-INDEX(Simulador!$C$69:$F$69,F15)+IF(Simulador!$N$7="Sí",MAX(0,IF(I15="",J15+INDEX(Simulador!$C$40:$F$40,F15),I15)-INDEX(Simulador!$C$41:$F$41,F15))*(INDEX(Simulador!$C$68:$F$68,F15)+Simulador!$N$8)/Simulador!$C$7,0) -> 59854.455 | T15: =P15+(IF(I15="",J15+INDEX(Simulador!$C$40:$F$40,F15),I15)-J15-INDEX(Simulador!$C$40:$F$40,F15))*Simulador!$C$9-INDEX(Simulador!$C$69:$F$69,F15)+IF(Simulador!$N$7="Sí",MAX(0,IF(I15="",J15+INDEX(Simulador!$C$40:$F$40,F15),I15)-INDEX(Simulador!$C$41:$F$41,F15))*(INDEX(Simulador!$C$68:$F$68,F15)+Simulador!$N$8)/Simulador!$C$7,0) -> 49548.811
B16: 45328 | C16: 5009 | D16: 3 | E16: 0.15 - 5 km | F16: =MATCH(E16,{"Misma locación","0.15 - 5 km","5 - 10 km","10+ km"},0) -> 2 | G16: =MONTH(B16) -> 2 | H16: =COUNTIF($G$8:G16,G16) -> 2 | I16: 22 | J16: =INDEX(Simulador!$C$39:$F$39,F16) -> 18 | K16: =IF(I16="","",I16-J16) -> 4 | L16: =INDEX(Simulador!$C$51:$F$51,F16) -> 99473.811 | M16: =IF(H16>=Simulador!$C$19,INDEX(Simulador!$C$63:$F$63,F16),INDEX(Simulador!$C$62:$F$62,F16)) -> 85898.023 | N16: =INDEX(Simulador!$C$64:$F$64,F16) -> 108447.11 | O16: =IF(H16>=Simulador!$C$19,INDEX(Simulador!$C$65:$F$65,F16),INDEX(Simulador!$C$64:$F$64,F16)) -> 108447.11 | P16: =IF(H16>=Simulador!$C$19,INDEX(Simulador!$C$67:$F$67,F16),INDEX(Simulador!$C$66:$F$66,F16)) -> 82343.946 | Q16: =M16+(IF(I16="",J16+INDEX(Simulador!$C$40:$F$40,F16),I16)-J16-INDEX(Simulador!$C$40:$F$40,F16))*Simulador!$C$9-INDEX(Simulador!$C$69:$F$69,F16)+IF(Simulador!$N$7="Sí",MAX(0,IF(I16="",J16+INDEX(Simulador!$C$40:$F$40,F16),I16)-INDEX(Simulador!$C$41:$F$41,F16))*(INDEX(Simulador!$C$68:$F$68,F16)+Simulador!$N$8)/Simulador!$C$7,0) -> 91722.023 | R16: =N16+(IF(I16="",J16+INDEX(Simulador!$C$40:$F$40,F16),I16)-J16-INDEX(Simulador!$C$40:$F$40,F16))*Simulador!$C$9-INDEX(Simulador!$C$69:$F$69,F16)+IF(Simulador!$N$7="Sí",MAX(0,IF(I16="",J16+INDEX(Simulador!$C$40:$F$40,F16),I16)-INDEX(Simulador!$C$41:$F$41,F16))*(INDEX(Simulador!$C$68:$F$68,F16)+Simulador!$N$8)/Simulador!$C$7,0) -> 114271.11 | S16: =O16+(IF(I16="",J16+INDEX(Simulador!$C$40:$F$40,F16),I16)-J16-INDEX(Simulador!$C$40:$F$40,F16))*Simulador!$C$9-INDEX(Simulador!$C$69:$F$69,F16)+IF(Simulador!$N$7="Sí",MAX(0,IF(I16="",J16+INDEX(Simulador!$C$40:$F$40,F16),I16)-INDEX(Simulador!$C$41:$F$41,F16))*(INDEX(Simulador!$C$68:$F$68,F16)+Simulador!$N$8)/Simulador!$C$7,0) -> 114271.11 | T16: =P16+(IF(I16="",J16+INDEX(Simulador!$C$40:$F$40,F16),I16)-J16-INDEX(Simulador!$C$40:$F$40,F16))*Simulador!$C$9-INDEX(Simulador!$C$69:$F$69,F16)+IF(Simulador!$N$7="Sí",MAX(0,IF(I16="",J16+INDEX(Simulador!$C$40:$F$40,F16),I16)-INDEX(Simulador!$C$41:$F$41,F16))*(INDEX(Simulador!$C$68:$F$68,F16)+Simulador!$N$8)/Simulador!$C$7,0) -> 88167.946
B17: 45331 | C17: 5200 | D17: 0.02 | E17: Misma locación | F17: =MATCH(E17,{"Misma locación","0.15 - 5 km","5 - 10 km","10+ km"},0) -> 1 | G17: =MONTH(B17) -> 2 | H17: =COUNTIF($G$8:G17,G17) -> 3 | I17: 10 | J17: =INDEX(Simulador!$C$39:$F$39,F17) -> 12 | K17: =IF(I17="","",I17-J17) -> -2 | L17: =INDEX(Simulador!$C$51:$F$51,F17) -> 76047.405 | M17: =IF(H17>=Simulador!$C$19,INDEX(Simulador!$C$63:$F$63,F17),INDEX(Simulador!$C$62:$F$62,F17)) -> 55414.011 | N17: =INDEX(Simulador!$C$64:$F$64,F17) -> 65678.455 | O17: =IF(H17>=Simulador!$C$19,INDEX(Simulador!$C$65:$F$65,F17),INDEX(Simulador!$C$64:$F$64,F17)) -> 65678.455 | P17: =IF(H17>=Simulador!$C$19,INDEX(Simulador!$C$67:$F$67,F17),INDEX(Simulador!$C$66:$F$66,F17)) -> 55372.811 | Q17: =M17+(IF(I17="",J17+INDEX(Simulador!$C$40:$F$40,F17),I17)-J17-INDEX(Simulador!$C$40:$F$40,F17))*Simulador!$C$9-INDEX(Simulador!$C$69:$F$69,F17)+IF(Simulador!$N$7="Sí",MAX(0,IF(I17="",J17+INDEX(Simulador!$C$40:$F$40,F17),I17)-INDEX(Simulador!$C$41:$F$41,F17))*(INDEX(Simulador!$C$68:$F$68,F17)+Simulador!$N$8)/Simulador!$C$7,0) -> 52502.011 | R17: =N17+(IF(I17="",J17+INDEX(Simulador!$C$40:$F$40,F17),I17)-J17-INDEX(Simulador!$C$40:$F$40,F17))*Simulador!$C$9-INDEX(Simulador!$C$69:$F$69,F17)+IF(Simulador!$N$7="Sí",MAX(0,IF(I17="",J17+INDEX(Simulador!$C$40:$F$40,F17),I17)-INDEX(Simulador!$C$41:$F$41,F17))*(INDEX(Simulador!$C$68:$F$68,F17)+Simulador!$N$8)/Simulador!$C$7,0) -> 62766.455 | S17: =O17+(IF(I17="",J17+INDEX(Simulador!$C$40:$F$40,F17),I17)-J17-INDEX(Simulador!$C$40:$F$40,F17))*Simulador!$C$9-INDEX(Simulador!$C$69:$F$69,F17)+IF(Simulador!$N$7="Sí",MAX(0,IF(I17="",J17+INDEX(Simulador!$C$40:$F$40,F17),I17)-INDEX(Simulador!$C$41:$F$41,F17))*(INDEX(Simulador!$C$68:$F$68,F17)+Simulador!$N$8)/Simulador!$C$7,0) -> 62766.455 | T17: =P17+(IF(I17="",J17+INDEX(Simulador!$C$40:$F$40,F17),I17)-J17-INDEX(Simulador!$C$40:$F$40,F17))*Simulador!$C$9-INDEX(Simulador!$C$69:$F$69,F17)+IF(Simulador!$N$7="Sí",MAX(0,IF(I17="",J17+INDEX(Simulador!$C$40:$F$40,F17),I17)-INDEX(Simulador!$C$41:$F$41,F17))*(INDEX(Simulador!$C$68:$F$68,F17)+Simulador!$N$8)/Simulador!$C$7,0) -> 52460.811
B18: 45334 | C18: 5013 | D18: 0.02 | E18: Misma locación | F18: =MATCH(E18,{"Misma locación","0.15 - 5 km","5 - 10 km","10+ km"},0) -> 1 | G18: =MONTH(B18) -> 2 | H18: =COUNTIF($G$8:G18,G18) -> 4 | I18: 10 | J18: =INDEX(Simulador!$C$39:$F$39,F18) -> 12 | K18: =IF(I18="","",I18-J18) -> -2 | L18: =INDEX(Simulador!$C$51:$F$51,F18) -> 76047.405 | M18: =IF(H18>=Simulador!$C$19,INDEX(Simulador!$C$63:$F$63,F18),INDEX(Simulador!$C$62:$F$62,F18)) -> 55414.011 | N18: =INDEX(Simulador!$C$64:$F$64,F18) -> 65678.455 | O18: =IF(H18>=Simulador!$C$19,INDEX(Simulador!$C$65:$F$65,F18),INDEX(Simulador!$C$64:$F$64,F18)) -> 65678.455 | P18: =IF(H18>=Simulador!$C$19,INDEX(Simulador!$C$67:$F$67,F18),INDEX(Simulador!$C$66:$F$66,F18)) -> 55372.811 | Q18: =M18+(IF(I18="",J18+INDEX(Simulador!$C$40:$F$40,F18),I18)-J18-INDEX(Simulador!$C$40:$F$40,F18))*Simulador!$C$9-INDEX(Simulador!$C$69:$F$69,F18)+IF(Simulador!$N$7="Sí",MAX(0,IF(I18="",J18+INDEX(Simulador!$C$40:$F$40,F18),I18)-INDEX(Simulador!$C$41:$F$41,F18))*(INDEX(Simulador!$C$68:$F$68,F18)+Simulador!$N$8)/Simulador!$C$7,0) -> 52502.011 | R18: =N18+(IF(I18="",J18+INDEX(Simulador!$C$40:$F$40,F18),I18)-J18-INDEX(Simulador!$C$40:$F$40,F18))*Simulador!$C$9-INDEX(Simulador!$C$69:$F$69,F18)+IF(Simulador!$N$7="Sí",MAX(0,IF(I18="",J18+INDEX(Simulador!$C$40:$F$40,F18),I18)-INDEX(Simulador!$C$41:$F$41,F18))*(INDEX(Simulador!$C$68:$F$68,F18)+Simulador!$N$8)/Simulador!$C$7,0) -> 62766.455 | S18: =O18+(IF(I18="",J18+INDEX(Simulador!$C$40:$F$40,F18),I18)-J18-INDEX(Simulador!$C$40:$F$40,F18))*Simulador!$C$9-INDEX(Simulador!$C$69:$F$69,F18)+IF(Simulador!$N$7="Sí",MAX(0,IF(I18="",J18+INDEX(Simulador!$C$40:$F$40,F18),I18)-INDEX(Simulador!$C$41:$F$41,F18))*(INDEX(Simulador!$C$68:$F$68,F18)+Simulador!$N$8)/Simulador!$C$7,0) -> 62766.455 | T18: =P18+(IF(I18="",J18+INDEX(Simulador!$C$40:$F$40,F18),I18)-J18-INDEX(Simulador!$C$40:$F$40,F18))*Simulador!$C$9-INDEX(Simulador!$C$69:$F$69,F18)+IF(Simulador!$N$7="Sí",MAX(0,IF(I18="",J18+INDEX(Simulador!$C$40:$F$40,F18),I18)-INDEX(Simulador!$C$41:$F$41,F18))*(INDEX(Simulador!$C$68:$F$68,F18)+Simulador!$N$8)/Simulador!$C$7,0) -> 52460.811
B19: 45337 | C19: 5675 | D19: 3.4 | E19: 0.15 - 5 km | F19: =MATCH(E19,{"Misma locación","0.15 - 5 km","5 - 10 km","10+ km"},0) -> 2 | G19: =MONTH(B19) -> 2 | H19: =COUNTIF($G$8:G19,G19) -> 5 | I19: 12 | J19: =INDEX(Simulador!$C$39:$F$39,F19) -> 18 | K19: =IF(I19="","",I19-J19) -> -6 | L19: =INDEX(Simulador!$C$51:$F$51,F19) -> 99473.811 | M19: =IF(H19>=Simulador!$C$19,INDEX(Simulador!$C$63:$F$63,F19),INDEX(Simulador!$C$62:$F$62,F19)) -> 85898.023 | N19: =INDEX(Simulador!$C$64:$F$64,F19) -> 108447.11 | O19: =IF(H19>=Simulador!$C$19,INDEX(Simulador!$C$65:$F$65,F19),INDEX(Simulador!$C$64:$F$64,F19)) -> 108447.11 | P19: =IF(H19>=Simulador!$C$19,INDEX(Simulador!$C$67:$F$67,F19),INDEX(Simulador!$C$66:$F$66,F19)) -> 82343.946 | Q19: =M19+(IF(I19="",J19+INDEX(Simulador!$C$40:$F$40,F19),I19)-J19-INDEX(Simulador!$C$40:$F$40,F19))*Simulador!$C$9-INDEX(Simulador!$C$69:$F$69,F19)+IF(Simulador!$N$7="Sí",MAX(0,IF(I19="",J19+INDEX(Simulador!$C$40:$F$40,F19),I19)-INDEX(Simulador!$C$41:$F$41,F19))*(INDEX(Simulador!$C$68:$F$68,F19)+Simulador!$N$8)/Simulador!$C$7,0) -> 77162.023 | R19: =N19+(IF(I19="",J19+INDEX(Simulador!$C$40:$F$40,F19),I19)-J19-INDEX(Simulador!$C$40:$F$40,F19))*Simulador!$C$9-INDEX(Simulador!$C$69:$F$69,F19)+IF(Simulador!$N$7="Sí",MAX(0,IF(I19="",J19+INDEX(Simulador!$C$40:$F$40,F19),I19)-INDEX(Simulador!$C$41:$F$41,F19))*(INDEX(Simulador!$C$68:$F$68,F19)+Simulador!$N$8)/Simulador!$C$7,0) -> 99711.105 | S19: =O19+(IF(I19="",J19+INDEX(Simulador!$C$40:$F$40,F19),I19)-J19-INDEX(Simulador!$C$40:$F$40,F19))*Simulador!$C$9-INDEX(Simulador!$C$69:$F$69,F19)+IF(Simulador!$N$7="Sí",MAX(0,IF(I19="",J19+INDEX(Simulador!$C$40:$F$40,F19),I19)-INDEX(Simulador!$C$41:$F$41,F19))*(INDEX(Simulador!$C$68:$F$68,F19)+Simulador!$N$8)/Simulador!$C$7,0) -> 99711.105 | T19: =P19+(IF(I19="",J19+INDEX(Simulador!$C$40:$F$40,F19),I19)-J19-INDEX(Simulador!$C$40:$F$40,F19))*Simulador!$C$9-INDEX(Simulador!$C$69:$F$69,F19)+IF(Simulador!$N$7="Sí",MAX(0,IF(I19="",J19+INDEX(Simulador!$C$40:$F$40,F19),I19)-INDEX(Simulador!$C$41:$F$41,F19))*(INDEX(Simulador!$C$68:$F$68,F19)+Simulador!$N$8)/Simulador!$C$7,0) -> 73607.946
B20: 45342 | C20: 5141 | D20: 0.019202399 | E20: Misma locación | F20: =MATCH(E20,{"Misma locación","0.15 - 5 km","5 - 10 km","10+ km"},0) -> 1 | G20: =MONTH(B20) -> 2 | H20: =COUNTIF($G$8:G20,G20) -> 6 | I20: 14 | J20: =INDEX(Simulador!$C$39:$F$39,F20) -> 12 | K20: =IF(I20="","",I20-J20) -> 2 | L20: =INDEX(Simulador!$C$51:$F$51,F20) -> 76047.405 | M20: =IF(H20>=Simulador!$C$19,INDEX(Simulador!$C$63:$F$63,F20),INDEX(Simulador!$C$62:$F$62,F20)) -> 36443.006 | N20: =INDEX(Simulador!$C$64:$F$64,F20) -> 65678.455 | O20: =IF(H20>=Simulador!$C$19,INDEX(Simulador!$C$65:$F$65,F20),INDEX(Simulador!$C$64:$F$64,F20)) -> 41575.228 | P20: =IF(H20>=Simulador!$C$19,INDEX(Simulador!$C$67:$F$67,F20),INDEX(Simulador!$C$66:$F$66,F20)) -> 50763.892 | Q20: =M20+(IF(I20="",J20+INDEX(Simulador!$C$40:$F$40,F20),I20)-J20-INDEX(Simulador!$C$40:$F$40,F20))*Simulador!$C$9-INDEX(Simulador!$C$69:$F$69,F20)+IF(Simulador!$N$7="Sí",MAX(0,IF(I20="",J20+INDEX(Simulador!$C$40:$F$40,F20),I20)-INDEX(Simulador!$C$41:$F$41,F20))*(INDEX(Simulador!$C$68:$F$68,F20)+Simulador!$N$8)/Simulador!$C$7,0) -> 42069.33 | R20: =N20+(IF(I20="",J20+INDEX(Simulador!$C$40:$F$40,F20),I20)-J20-INDEX(Simulador!$C$40:$F$40,F20))*Simulador!$C$9-INDEX(Simulador!$C$69:$F$69,F20)+IF(Simulador!$N$7="Sí",MAX(0,IF(I20="",J20+INDEX(Simulador!$C$40:$F$40,F20),I20)-INDEX(Simulador!$C$41:$F$41,F20))*(INDEX(Simulador!$C$68:$F$68,F20)+Simulador!$N$8)/Simulador!$C$7,0) -> 71304.78 | S20: =O20+(IF(I20="",J20+INDEX(Simulador!$C$40:$F$40,F20),I20)-J20-INDEX(Simulador!$C$40:$F$40,F20))*Simulador!$C$9-INDEX(Simulador!$C$69:$F$69,F20)+IF(Simulador!$N$7="Sí",MAX(0,IF(I20="",J20+INDEX(Simulador!$C$40:$F$40,F20),I20)-INDEX(Simulador!$C$41:$F$41,F20))*(INDEX(Simulador!$C$68:$F$68,F20)+Simulador!$N$8)/Simulador!$C$7,0) -> 47201.552 | T20: =P20+(IF(I20="",J20+INDEX(Simulador!$C$40:$F$40,F20),I20)-J20-INDEX(Simulador!$C$40:$F$40,F20))*Simulador!$C$9-INDEX(Simulador!$C$69:$F$69,F20)+IF(Simulador!$N$7="Sí",MAX(0,IF(I20="",J20+INDEX(Simulador!$C$40:$F$40,F20),I20)-INDEX(Simulador!$C$41:$F$41,F20))*(INDEX(Simulador!$C$68:$F$68,F20)+Simulador!$N$8)/Simulador!$C$7,0) -> 56390.216
B21: 45346 | C21: 5032 | D21: 2.8 | E21: 0.15 - 5 km | F21: =MATCH(E21,{"Misma locación","0.15 - 5 km","5 - 10 km","10+ km"},0) -> 2 | G21: =MONTH(B21) -> 2 | H21: =COUNTIF($G$8:G21,G21) -> 7 | I21: 17 | J21: =INDEX(Simulador!$C$39:$F$39,F21) -> 18 | K21: =IF(I21="","",I21-J21) -> -1 | L21: =INDEX(Simulador!$C$51:$F$51,F21) -> 99473.811 | M21: =IF(H21>=Simulador!$C$19,INDEX(Simulador!$C$63:$F$63,F21),INDEX(Simulador!$C$62:$F$62,F21)) -> 56053.011 | N21: =INDEX(Simulador!$C$64:$F$64,F21) -> 108447.11 | O21: =IF(H21>=Simulador!$C$19,INDEX(Simulador!$C$65:$F$65,F21),INDEX(Simulador!$C$64:$F$64,F21)) -> 67327.553 | P21: =IF(H21>=Simulador!$C$19,INDEX(Simulador!$C$67:$F$67,F21),INDEX(Simulador!$C$66:$F$66,F21)) -> 59499.892 | Q21: =M21+(IF(I21="",J21+INDEX(Simulador!$C$40:$F$40,F21),I21)-J21-INDEX(Simulador!$C$40:$F$40,F21))*Simulador!$C$9-INDEX(Simulador!$C$69:$F$69,F21)+IF(Simulador!$N$7="Sí",MAX(0,IF(I21="",J21+INDEX(Simulador!$C$40:$F$40,F21),I21)-INDEX(Simulador!$C$41:$F$41,F21))*(INDEX(Simulador!$C$68:$F$68,F21)+Simulador!$N$8)/Simulador!$C$7,0) -> 54597.011 | R21: =N21+(IF(I21="",J21+INDEX(Simulador!$C$40:$F$40,F21),I21)-J21-INDEX(Simulador!$C$40:$F$40,F21))*Simulador!$C$9-INDEX(Simulador!$C$69:$F$69,F21)+IF(Simulador!$N$7="Sí",MAX(0,IF(I21="",J21+INDEX(Simulador!$C$40:$F$40,F21),I21)-INDEX(Simulador!$C$41:$F$41,F21))*(INDEX(Simulador!$C$68:$F$68,F21)+Simulador!$N$8)/Simulador!$C$7,0) -> 106991.11 | S21: =O21+(IF(I21="",J21+INDEX(Simulador!$C$40:$F$40,F21),I21)-J21-INDEX(Simulador!$C$40:$F$40,F21))*Simulador!$C$9-INDEX(Simulador!$C$69:$F$69,F21)+IF(Simulador!$N$7="Sí",MAX(0,IF(I21="",J21+INDEX(Simulador!$C$40:$F$40,F21),I21)-INDEX(Simulador!$C$41:$F$41,F21))*(INDEX(Simulador!$C$68:$F$68,F21)+Simulador!$N$8)/Simulador!$C$7,0) -> 65871.553 | T21: =P21+(IF(I21="",J21+INDEX(Simulador!$C$40:$F$40,F21),I21)-J21-INDEX(Simulador!$C$40:$F$40,F21))*Simulador!$C$9-INDEX(Simulador!$C$69:$F$69,F21)+IF(Simulador!$N$7="Sí",MAX(0,IF(I21="",J21+INDEX(Simulador!$C$40:$F$40,F21),I21)-INDEX(Simulador!$C$41:$F$41,F21))*(INDEX(Simulador!$C$68:$F$68,F21)+Simulador!$N$8)/Simulador!$C$7,0) -> 58043.892
B22: 45351 | C22: 5856 | D22: 2.8 | E22: 0.15 - 5 km | F22: =MATCH(E22,{"Misma locación","0.15 - 5 km","5 - 10 km","10+ km"},0) -> 2 | G22: =MONTH(B22) -> 2 | H22: =COUNTIF($G$8:G22,G22) -> 8 | I22: 22 | J22: =INDEX(Simulador!$C$39:$F$39,F22) -> 18 | K22: =IF(I22="","",I22-J22) -> 4 | L22: =INDEX(Simulador!$C$51:$F$51,F22) -> 99473.811 | M22: =IF(H22>=Simulador!$C$19,INDEX(Simulador!$C$63:$F$63,F22),INDEX(Simulador!$C$62:$F$62,F22)) -> 56053.011 | N22: =INDEX(Simulador!$C$64:$F$64,F22) -> 108447.11 | O22: =IF(H22>=Simulador!$C$19,INDEX(Simulador!$C$65:$F$65,F22),INDEX(Simulador!$C$64:$F$64,F22)) -> 67327.553 | P22: =IF(H22>=Simulador!$C$19,INDEX(Simulador!$C$67:$F$67,F22),INDEX(Simulador!$C$66:$F$66,F22)) -> 59499.892 | Q22: =M22+(IF(I22="",J22+INDEX(Simulador!$C$40:$F$40,F22),I22)-J22-INDEX(Simulador!$C$40:$F$40,F22))*Simulador!$C$9-INDEX(Simulador!$C$69:$F$69,F22)+IF(Simulador!$N$7="Sí",MAX(0,IF(I22="",J22+INDEX(Simulador!$C$40:$F$40,F22),I22)-INDEX(Simulador!$C$41:$F$41,F22))*(INDEX(Simulador!$C$68:$F$68,F22)+Simulador!$N$8)/Simulador!$C$7,0) -> 61877.011 | R22: =N22+(IF(I22="",J22+INDEX(Simulador!$C$40:$F$40,F22),I22)-J22-INDEX(Simulador!$C$40:$F$40,F22))*Simulador!$C$9-INDEX(Simulador!$C$69:$F$69,F22)+IF(Simulador!$N$7="Sí",MAX(0,IF(I22="",J22+INDEX(Simulador!$C$40:$F$40,F22),I22)-INDEX(Simulador!$C$41:$F$41,F22))*(INDEX(Simulador!$C$68:$F$68,F22)+Simulador!$N$8)/Simulador!$C$7,0) -> 114271.11 | S22: =O22+(IF(I22="",J22+INDEX(Simulador!$C$40:$F$40,F22),I22)-J22-INDEX(Simulador!$C$40:$F$40,F22))*Simulador!$C$9-INDEX(Simulador!$C$69:$F$69,F22)+IF(Simulador!$N$7="Sí",MAX(0,IF(I22="",J22+INDEX(Simulador!$C$40:$F$40,F22),I22)-INDEX(Simulador!$C$41:$F$41,F22))*(INDEX(Simulador!$C$68:$F$68,F22)+Simulador!$N$8)/Simulador!$C$7,0) -> 73151.553 | T22: =P22+(IF(I22="",J22+INDEX(Simulador!$C$40:$F$40,F22),I22)-J22-INDEX(Simulador!$C$40:$F$40,F22))*Simulador!$C$9-INDEX(Simulador!$C$69:$F$69,F22)+IF(Simulador!$N$7="Sí",MAX(0,IF(I22="",J22+INDEX(Simulador!$C$40:$F$40,F22),I22)-INDEX(Simulador!$C$41:$F$41,F22))*(INDEX(Simulador!$C$68:$F$68,F22)+Simulador!$N$8)/Simulador!$C$7,0) -> 65323.892
B23: 45355 | C23: 5083 | D23: 2.7 | E23: 0.15 - 5 km | F23: =MATCH(E23,{"Misma locación","0.15 - 5 km","5 - 10 km","10+ km"},0) -> 2 | G23: =MONTH(B23) -> 3 | H23: =COUNTIF($G$8:G23,G23) -> 1 | I23: 16 | J23: =INDEX(Simulador!$C$39:$F$39,F23) -> 18 | K23: =IF(I23="","",I23-J23) -> -2 | L23: =INDEX(Simulador!$C$51:$F$51,F23) -> 99473.811 | M23: =IF(H23>=Simulador!$C$19,INDEX(Simulador!$C$63:$F$63,F23),INDEX(Simulador!$C$62:$F$62,F23)) -> 85898.023 | N23: =INDEX(Simulador!$C$64:$F$64,F23) -> 108447.11 | O23: =IF(H23>=Simulador!$C$19,INDEX(Simulador!$C$65:$F$65,F23),INDEX(Simulador!$C$64:$F$64,F23)) -> 108447.11 | P23: =IF(H23>=Simulador!$C$19,INDEX(Simulador!$C$67:$F$67,F23),INDEX(Simulador!$C$66:$F$66,F23)) -> 82343.946 | Q23: =M23+(IF(I23="",J23+INDEX(Simulador!$C$40:$F$40,F23),I23)-J23-INDEX(Simulador!$C$40:$F$40,F23))*Simulador!$C$9-INDEX(Simulador!$C$69:$F$69,F23)+IF(Simulador!$N$7="Sí",MAX(0,IF(I23="",J23+INDEX(Simulador!$C$40:$F$40,F23),I23)-INDEX(Simulador!$C$41:$F$41,F23))*(INDEX(Simulador!$C$68:$F$68,F23)+Simulador!$N$8)/Simulador!$C$7,0) -> 82986.023 | R23: =N23+(IF(I23="",J23+INDEX(Simulador!$C$40:$F$40,F23),I23)-J23-INDEX(Simulador!$C$40:$F$40,F23))*Simulador!$C$9-INDEX(Simulador!$C$69:$F$69,F23)+IF(Simulador!$N$7="Sí",MAX(0,IF(I23="",J23+INDEX(Simulador!$C$40:$F$40,F23),I23)-INDEX(Simulador!$C$41:$F$41,F23))*(INDEX(Simulador!$C$68:$F$68,F23)+Simulador!$N$8)/Simulador!$C$7,0) -> 105535.11 | S23: =O23+(IF(I23="",J23+INDEX(Simulador!$C$40:$F$40,F23),I23)-J23-INDEX(Simulador!$C$40:$F$40,F23))*Simulador!$C$9-INDEX(Simulador!$C$69:$F$69,F23)+IF(Simulador!$N$7="Sí",MAX(0,IF(I23="",J23+INDEX(Simulador!$C$40:$F$40,F23),I23)-INDEX(Simulador!$C$41:$F$41,F23))*(INDEX(Simulador!$C$68:$F$68,F23)+Simulador!$N$8)/Simulador!$C$7,0) -> 105535.11 | T23: =P23+(IF(I23="",J23+INDEX(Simulador!$C$40:$F$40,F23),I23)-J23-INDEX(Simulador!$C$40:$F$40,F23))*Simulador!$C$9-INDEX(Simulador!$C$69:$F$69,F23)+IF(Simulador!$N$7="Sí",MAX(0,IF(I23="",J23+INDEX(Simulador!$C$40:$F$40,F23),I23)-INDEX(Simulador!$C$41:$F$41,F23))*(INDEX(Simulador!$C$68:$F$68,F23)+Simulador!$N$8)/Simulador!$C$7,0) -> 79431.946
B24: 45360 | C24: 5078 | D24: 0.04 | E24: Misma locación | F24: =MATCH(E24,{"Misma locación","0.15 - 5 km","5 - 10 km","10+ km"},0) -> 1 | G24: =MONTH(B24) -> 3 | H24: =COUNTIF($G$8:G24,G24) -> 2 | I24: 10.5 | J24: =INDEX(Simulador!$C$39:$F$39,F24) -> 12 | K24: =IF(I24="","",I24-J24) -> -1.5 | L24: =INDEX(Simulador!$C$51:$F$51,F24) -> 76047.405 | M24: =IF(H24>=Simulador!$C$19,INDEX(Simulador!$C$63:$F$63,F24),INDEX(Simulador!$C$62:$F$62,F24)) -> 55414.011 | N24: =INDEX(Simulador!$C$64:$F$64,F24) -> 65678.455 | O24: =IF(H24>=Simulador!$C$19,INDEX(Simulador!$C$65:$F$65,F24),INDEX(Simulador!$C$64:$F$64,F24)) -> 65678.455 | P24: =IF(H24>=Simulador!$C$19,INDEX(Simulador!$C$67:$F$67,F24),INDEX(Simulador!$C$66:$F$66,F24)) -> 55372.811 | Q24: =M24+(IF(I24="",J24+INDEX(Simulador!$C$40:$F$40,F24),I24)-J24-INDEX(Simulador!$C$40:$F$40,F24))*Simulador!$C$9-INDEX(Simulador!$C$69:$F$69,F24)+IF(Simulador!$N$7="Sí",MAX(0,IF(I24="",J24+INDEX(Simulador!$C$40:$F$40,F24),I24)-INDEX(Simulador!$C$41:$F$41,F24))*(INDEX(Simulador!$C$68:$F$68,F24)+Simulador!$N$8)/Simulador!$C$7,0) -> 53230.011 | R24: =N24+(IF(I24="",J24+INDEX(Simulador!$C$40:$F$40,F24),I24)-J24-INDEX(Simulador!$C$40:$F$40,F24))*Simulador!$C$9-INDEX(Simulador!$C$69:$F$69,F24)+IF(Simulador!$N$7="Sí",MAX(0,IF(I24="",J24+INDEX(Simulador!$C$40:$F$40,F24),I24)-INDEX(Simulador!$C$41:$F$41,F24))*(INDEX(Simulador!$C$68:$F$68,F24)+Simulador!$N$8)/Simulador!$C$7,0) -> 63494.455 | S24: =O24+(IF(I24="",J24+INDEX(Simulador!$C$40:$F$40,F24),I24)-J24-INDEX(Simulador!$C$40:$F$40,F24))*Simulador!$C$9-INDEX(Simulador!$C$69:$F$69,F24)+IF(Simulador!$N$7="Sí",MAX(0,IF(I24="",J24+INDEX(Simulador!$C$40:$F$40,F24),I24)-INDEX(Simulador!$C$41:$F$41,F24))*(INDEX(Simulador!$C$68:$F$68,F24)+Simulador!$N$8)/Simulador!$C$7,0) -> 63494.455 | T24: =P24+(IF(I24="",J24+INDEX(Simulador!$C$40:$F$40,F24),I24)-J24-INDEX(Simulador!$C$40:$F$40,F24))*Simulador!$C$9-INDEX(Simulador!$C$69:$F$69,F24)+IF(Simulador!$N$7="Sí",MAX(0,IF(I24="",J24+INDEX(Simulador!$C$40:$F$40,F24),I24)-INDEX(Simulador!$C$41:$F$41,F24))*(INDEX(Simulador!$C$68:$F$68,F24)+Simulador!$N$8)/Simulador!$C$7,0) -> 53188.811
B25: 45364 | C25: 5027 | D25: 0.04 | E25: Misma locación | F25: =MATCH(E25,{"Misma locación","0.15 - 5 km","5 - 10 km","10+ km"},0) -> 1 | G25: =MONTH(B25) -> 3 | H25: =COUNTIF($G$8:G25,G25) -> 3 | I25: 10.5 | J25: =INDEX(Simulador!$C$39:$F$39,F25) -> 12 | K25: =IF(I25="","",I25-J25) -> -1.5 | L25: =INDEX(Simulador!$C$51:$F$51,F25) -> 76047.405 | M25: =IF(H25>=Simulador!$C$19,INDEX(Simulador!$C$63:$F$63,F25),INDEX(Simulador!$C$62:$F$62,F25)) -> 55414.011 | N25: =INDEX(Simulador!$C$64:$F$64,F25) -> 65678.455 | O25: =IF(H25>=Simulador!$C$19,INDEX(Simulador!$C$65:$F$65,F25),INDEX(Simulador!$C$64:$F$64,F25)) -> 65678.455 | P25: =IF(H25>=Simulador!$C$19,INDEX(Simulador!$C$67:$F$67,F25),INDEX(Simulador!$C$66:$F$66,F25)) -> 55372.811 | Q25: =M25+(IF(I25="",J25+INDEX(Simulador!$C$40:$F$40,F25),I25)-J25-INDEX(Simulador!$C$40:$F$40,F25))*Simulador!$C$9-INDEX(Simulador!$C$69:$F$69,F25)+IF(Simulador!$N$7="Sí",MAX(0,IF(I25="",J25+INDEX(Simulador!$C$40:$F$40,F25),I25)-INDEX(Simulador!$C$41:$F$41,F25))*(INDEX(Simulador!$C$68:$F$68,F25)+Simulador!$N$8)/Simulador!$C$7,0) -> 53230.011 | R25: =N25+(IF(I25="",J25+INDEX(Simulador!$C$40:$F$40,F25),I25)-J25-INDEX(Simulador!$C$40:$F$40,F25))*Simulador!$C$9-INDEX(Simulador!$C$69:$F$69,F25)+IF(Simulador!$N$7="Sí",MAX(0,IF(I25="",J25+INDEX(Simulador!$C$40:$F$40,F25),I25)-INDEX(Simulador!$C$41:$F$41,F25))*(INDEX(Simulador!$C$68:$F$68,F25)+Simulador!$N$8)/Simulador!$C$7,0) -> 63494.455 | S25: =O25+(IF(I25="",J25+INDEX(Simulador!$C$40:$F$40,F25),I25)-J25-INDEX(Simulador!$C$40:$F$40,F25))*Simulador!$C$9-INDEX(Simulador!$C$69:$F$69,F25)+IF(Simulador!$N$7="Sí",MAX(0,IF(I25="",J25+INDEX(Simulador!$C$40:$F$40,F25),I25)-INDEX(Simulador!$C$41:$F$41,F25))*(INDEX(Simulador!$C$68:$F$68,F25)+Simulador!$N$8)/Simulador!$C$7,0) -> 63494.455 | T25: =P25+(IF(I25="",J25+INDEX(Simulador!$C$40:$F$40,F25),I25)-J25-INDEX(Simulador!$C$40:$F$40,F25))*Simulador!$C$9-INDEX(Simulador!$C$69:$F$69,F25)+IF(Simulador!$N$7="Sí",MAX(0,IF(I25="",J25+INDEX(Simulador!$C$40:$F$40,F25),I25)-INDEX(Simulador!$C$41:$F$41,F25))*(INDEX(Simulador!$C$68:$F$68,F25)+Simulador!$N$8)/Simulador!$C$7,0) -> 53188.811
... B77: 45608 | C77: 3932 | D77: 4.4 | E77: 0.15 - 5 km | F77: =MATCH(E77,{"Misma locación","0.15 - 5 km","5 - 10 km","10+ km"},0) -> 2 | G77: =MONTH(B77) -> 11 | H77: =COUNTIF($G$8:G77,G77) -> 3 | I77: 15.75 | J77: =INDEX(Simulador!$C$39:$F$39,F77) -> 18 | K77: =IF(I77="","",I77-J77) -> -2.25 | L77: =INDEX(Simulador!$C$51:$F$51,F77) -> 99473.811 | M77: =IF(H77>=Simulador!$C$19,INDEX(Simulador!$C$63:$F$63,F77),INDEX(Simulador!$C$62:$F$62,F77)) -> 85898.023 | N77: =INDEX(Simulador!$C$64:$F$64,F77) -> 108447.11 | O77: =IF(H77>=Simulador!$C$19,INDEX(Simulador!$C$65:$F$65,F77),INDEX(Simulador!$C$64:$F$64,F77)) -> 108447.11 | P77: =IF(H77>=Simulador!$C$19,INDEX(Simulador!$C$67:$F$67,F77),INDEX(Simulador!$C$66:$F$66,F77)) -> 82343.946 | Q77: =M77+(IF(I77="",J77+INDEX(Simulador!$C$40:$F$40,F77),I77)-J77-INDEX(Simulador!$C$40:$F$40,F77))*Simulador!$C$9-INDEX(Simulador!$C$69:$F$69,F77)+IF(Simulador!$N$7="Sí",MAX(0,IF(I77="",J77+INDEX(Simulador!$C$40:$F$40,F77),I77)-INDEX(Simulador!$C$41:$F$41,F77))*(INDEX(Simulador!$C$68:$F$68,F77)+Simulador!$N$8)/Simulador!$C$7,0) -> 82622.023 | R77: =N77+(IF(I77="",J77+INDEX(Simulador!$C$40:$F$40,F77),I77)-J77-INDEX(Simulador!$C$40:$F$40,F77))*Simulador!$C$9-INDEX(Simulador!$C$69:$F$69,F77)+IF(Simulador!$N$7="Sí",MAX(0,IF(I77="",J77+INDEX(Simulador!$C$40:$F$40,F77),I77)-INDEX(Simulador!$C$41:$F$41,F77))*(INDEX(Simulador!$C$68:$F$68,F77)+Simulador!$N$8)/Simulador!$C$7,0) -> 105171.11 | S77: =O77+(IF(I77="",J77+INDEX(Simulador!$C$40:$F$40,F77),I77)-J77-INDEX(Simulador!$C$40:$F$40,F77))*Simulador!$C$9-INDEX(Simulador!$C$69:$F$69,F77)+IF(Simulador!$N$7="Sí",MAX(0,IF(I77="",J77+INDEX(Simulador!$C$40:$F$40,F77),I77)-INDEX(Simulador!$C$41:$F$41,F77))*(INDEX(Simulador!$C$68:$F$68,F77)+Simulador!$N$8)/Simulador!$C$7,0) -> 105171.11 | T77: =P77+(IF(I77="",J77+INDEX(Simulador!$C$40:$F$40,F77),I77)-J77-INDEX(Simulador!$C$40:$F$40,F77))*Simulador!$C$9-INDEX(Simulador!$C$69:$F$69,F77)+IF(Simulador!$N$7="Sí",MAX(0,IF(I77="",J77+INDEX(Simulador!$C$40:$F$40,F77),I77)-INDEX(Simulador!$C$41:$F$41,F77))*(INDEX(Simulador!$C$68:$F$68,F77)+Simulador!$N$8)/Simulador!$C$7,0) -> 79067.946
B79: Totales por movimiento (sin cargo fijo) | L79: =SUM(L8:L77) -> 6424357.4 | M79: =SUM(M8:M77) -> 5060927 | N79: =SUM(N8:N77) -> 7170102.3 | O79: =SUM(O8:O77) -> 6421483.1 | P79: =SUM(P8:P77) -> 5158786.6 | Q79: =SUM(Q8:Q77) -> 4970440.6 | R79: =SUM(R8:R77) -> 7079615.9 | S79: =SUM(S8:S77) -> 6330996.7 | T79: =SUM(T8:T77) -> 5068300.2
B82: Meses con movilizaciones
B83: Mes | C83: Movilizaciones | D83: Misma localización | E83: 0,1–5 km | F83: 5–10 km | G83: Más de 10 km | H83: Cargo fijo Petro Star (USD) | I83: Cargo fijo Ecotransur (USD) | J83: Truck Manager mensual (USD) | K83: Mes | L83: Work Order (USD) | M83: Petro Star tarifa normal, horas reales (USD) | N83: Ecotransur, horas reales (USD) | O83: Petro Star Lump Sum, horas reales (USD) | P83: Ahorro Petro Star tarifa normal (USD) | Q83: Ahorro Ecotransur (USD) | R83: Ahorro Petro Star Lump Sum (USD)
B84: 1 | C84: =COUNTIF($G$8:$G$77,B84) -> 7 | D84: =COUNTIFS($G$8:$G$77,B84,$F$8:$F$77,1) -> 0 | E84: =COUNTIFS($G$8:$G$77,B84,$F$8:$F$77,2) -> 5 | F84: =COUNTIFS($G$8:$G$77,B84,$F$8:$F$77,3) -> 1 | G84: =COUNTIFS($G$8:$G$77,B84,$F$8:$F$77,4) -> 1 | H84: =IF(C84=0,0,INDEX(Simulador!$E$72:$E$78,MIN(C84,6)+1)) -> 0 | I84: =IF(C84=0,0,INDEX(Simulador!$F$72:$F$78,MIN(C84,6)+1)) -> 0 | J84: =IF(AND(C84>0,Simulador!$C$16="Mensual fijo"),Simulador!$C$14/Simulador!$C$7,0) -> 16216.216 | K84: Ene | L84: =SUMIF($G$8:$G$77,B84,$L$8:$L$77) -> 704538.68 | M84: =SUMIF($G$8:$G$77,B84,$Q$8:$Q$77)+H84+J84 -> 563837.67 | N84: =SUMIF($G$8:$G$77,B84,$T$8:$T$77)+I84+J84 -> 560195.41 | O84: =SUMIF($G$8:$G$77,B84,$R$8:$R$77)+H84+J84 -> 820686.55 | P84: =L84-M84 -> 140701.01 | Q84: =L84-N84 -> 144343.27 | R84: =L84-O84 -> -116147.88
B85: 2 | C85: =COUNTIF($G$8:$G$77,B85) -> 8 | D85: =COUNTIFS($G$8:$G$77,B85,$F$8:$F$77,1) -> 4 | E85: =COUNTIFS($G$8:$G$77,B85,$F$8:$F$77,2) -> 4 | F85: =COUNTIFS($G$8:$G$77,B85,$F$8:$F$77,3) -> 0 | G85: =COUNTIFS($G$8:$G$77,B85,$F$8:$F$77,4) -> 0 | H85: =IF(C85=0,0,INDEX(Simulador!$E$72:$E$78,MIN(C85,6)+1)) -> 0 | I85: =IF(C85=0,0,INDEX(Simulador!$F$72:$F$78,MIN(C85,6)+1)) -> 0 | J85: =IF(AND(C85>0,Simulador!$C$16="Mensual fijo"),Simulador!$C$14/Simulador!$C$7,0) -> 16216.216 | K85: Feb | L85: =SUMIF($G$8:$G$77,B85,$L$8:$L$77) -> 702084.86 | M85: =SUMIF($G$8:$G$77,B85,$Q$8:$Q$77)+H85+J85 -> 498237.65 | N85: =SUMIF($G$8:$G$77,B85,$T$8:$T$77)+I85+J85 -> 512220.54 | O85: =SUMIF($G$8:$G$77,B85,$R$8:$R$77)+H85+J85 -> 708152.78 | P85: =L85-M85 -> 203847.22 | Q85: =L85-N85 -> 189864.32 | R85: =L85-O85 -> -6067.9189
B86: 3 | C86: =COUNTIF($G$8:$G$77,B86) -> 7 | D86: =COUNTIFS($G$8:$G$77,B86,$F$8:$F$77,1) -> 3 | E86: =COUNTIFS($G$8:$G$77,B86,$F$8:$F$77,2) -> 3 | F86: =COUNTIFS($G$8:$G$77,B86,$F$8:$F$77,3) -> 1 | G86: =COUNTIFS($G$8:$G$77,B86,$F$8:$F$77,4) -> 0 | H86: =IF(C86=0,0,INDEX(Simulador!$E$72:$E$78,MIN(C86,6)+1)) -> 0 | I86: =IF(C86=0,0,INDEX(Simulador!$F$72:$F$78,MIN(C86,6)+1)) -> 0 | J86: =IF(AND(C86>0,Simulador!$C$16="Mensual fijo"),Simulador!$C$14/Simulador!$C$7,0) -> 16216.216 | K86: Mar | L86: =SUMIF($G$8:$G$77,B86,$L$8:$L$77) -> 622748.46 | M86: =SUMIF($G$8:$G$77,B86,$Q$8:$Q$77)+H86+J86 -> 582648.39 | N86: =SUMIF($G$8:$G$77,B86,$T$8:$T$77)+I86+J86 -> 584207.71 | O86: =SUMIF($G$8:$G$77,B86,$R$8:$R$77)+H86+J86 -> 779695.71 | P86: =L86-M86 -> 40100.066 | Q86: =L86-N86 -> 38540.747 | R86: =L86-O86 -> -156947.25
B87: 4 | C87: =COUNTIF($G$8:$G$77,B87) -> 7 | D87: =COUNTIFS($G$8:$G$77,B87,$F$8:$F$77,1) -> 1 | E87: =COUNTIFS($G$8:$G$77,B87,$F$8:$F$77,2) -> 3 | F87: =COUNTIFS($G$8:$G$77,B87,$F$8:$F$77,3) -> 3 | G87: =COUNTIFS($G$8:$G$77,B87,$F$8:$F$77,4) -> 0 | H87: =IF(C87=0,0,INDEX(Simulador!$E$72:$E$78,MIN(C87,6)+1)) -> 0 | I87: =IF(C87=0,0,INDEX(Simulador!$F$72:$F$78,MIN(C87,6)+1)) -> 0 | J87: =IF(AND(C87>0,Simulador!$C$16="Mensual fijo"),Simulador!$C$14/Simulador!$C$7,0) -> 16216.216 | K87: Abr | L87: =SUMIF($G$8:$G$77,B87,$L$8:$L$77) -> 663023.27 | M87: =SUMIF($G$8:$G$77,B87,$Q$8:$Q$77)+H87+J87 -> 534297.26 | N87: =SUMIF($G$8:$G$77,B87,$T$8:$T$77)+I87+J87 -> 541636.27 | O87: =SUMIF($G$8:$G$77,B87,$R$8:$R$77)+H87+J87 -> 783889.67 | P87: =L87-M87 -> 128726.01 | Q87: =L87-N87 -> 121387 | R87: =L87-O87 -> -120866.4
B88: 5 | C88: =COUNTIF($G$8:$G$77,B88) -> 7 | D88: =COUNTIFS($G$8:$G$77,B88,$F$8:$F$77,1) -> 3 | E88: =COUNTIFS($G$8:$G$77,B88,$F$8:$F$77,2) -> 3 | F88: =COUNTIFS($G$8:$G$77,B88,$F$8:$F$77,3) -> 1 | G88: =COUNTIFS($G$8:$G$77,B88,$F$8:$F$77,4) -> 0 | H88: =IF(C88=0,0,INDEX(Simulador!$E$72:$E$78,MIN(C88,6)+1)) -> 0 | I88: =IF(C88=0,0,INDEX(Simulador!$F$72:$F$78,MIN(C88,6)+1)) -> 0 | J88: =IF(AND(C88>0,Simulador!$C$16="Mensual fijo"),Simulador!$C$14/Simulador!$C$7,0) -> 16216.216 | K88: May | L88: =SUMIF($G$8:$G$77,B88,$L$8:$L$77) -> 622748.46 | M88: =SUMIF($G$8:$G$77,B88,$Q$8:$Q$77)+H88+J88 -> 483695 | N88: =SUMIF($G$8:$G$77,B88,$T$8:$T$77)+I88+J88 -> 497120.86 | O88: =SUMIF($G$8:$G$77,B88,$R$8:$R$77)+H88+J88 -> 667488.59 | P88: =L88-M88 -> 139053.46 | Q88: =L88-N88 -> 125627.6 | R88: =L88-O88 -> -44740.128
B89: 6 | C89: =COUNTIF($G$8:$G$77,B89) -> 9 | D89: =COUNTIFS($G$8:$G$77,B89,$F$8:$F$77,1) -> 4 | E89: =COUNTIFS($G$8:$G$77,B89,$F$8:$F$77,2) -> 4 | F89: =COUNTIFS($G$8:$G$77,B89,$F$8:$F$77,3) -> 1 | G89: =COUNTIFS($G$8:$G$77,B89,$F$8:$F$77,4) -> 0 | H89: =IF(C89=0,0,INDEX(Simulador!$E$72:$E$78,MIN(C89,6)+1)) -> 0 | I89: =IF(C89=0,0,INDEX(Simulador!$F$72:$F$78,MIN(C89,6)+1)) -> 0 | J89: =IF(AND(C89>0,Simulador!$C$16="Mensual fijo"),Simulador!$C$14/Simulador!$C$7,0) -> 16216.216 | K89: Jun | L89: =SUMIF($G$8:$G$77,B89,$L$8:$L$77) -> 798269.68 | M89: =SUMIF($G$8:$G$77,B89,$Q$8:$Q$77)+H89+J89 -> 576840.1 | N89: =SUMIF($G$8:$G$77,B89,$T$8:$T$77)+I89+J89 -> 608033.73 | O89: =SUMIF($G$8:$G$77,B89,$R$8:$R$77)+H89+J89 -> 842263.24 | P89: =L89-M89 -> 221429.57 | Q89: =L89-N89 -> 190235.94 | R89: =L89-O89 -> -43993.561
B90: 7 | C90: =COUNTIF($G$8:$G$77,B90) -> 7 | D90: =COUNTIFS($G$8:$G$77,B90,$F$8:$F$77,1) -> 2 | E90: =COUNTIFS($G$8:$G$77,B90,$F$8:$F$77,2) -> 3 | F90: =COUNTIFS($G$8:$G$77,B90,$F$8:$F$77,3) -> 0 | G90: =COUNTIFS($G$8:$G$77,B90,$F$8:$F$77,4) -> 2 | H90: =IF(C90=0,0,INDEX(Simulador!$E$72:$E$78,MIN(C90,6)+1)) -> 0 | I90: =IF(C90=0,0,INDEX(Simulador!$F$72:$F$78,MIN(C90,6)+1)) -> 0 | J90: =IF(AND(C90>0,Simulador!$C$16="Mensual fijo"),Simulador!$C$14/Simulador!$C$7,0) -> 16216.216 | K90: Jul | L90: =SUMIF($G$8:$G$77,B90,$L$8:$L$77) -> 672485.86 | M90: =SUMIF($G$8:$G$77,B90,$Q$8:$Q$77)+H90+J90 -> 484758.33 | N90: =SUMIF($G$8:$G$77,B90,$T$8:$T$77)+I90+J90 -> 502002.95 | O90: =SUMIF($G$8:$G$77,B90,$R$8:$R$77)+H90+J90 -> 716204.76 | P90: =L90-M90 -> 187727.53 | Q90: =L90-N90 -> 170482.91 | R90: =L90-O90 -> -43718.896
B91: 8 | C91: =COUNTIF($G$8:$G$77,B91) -> 3 | D91: =COUNTIFS($G$8:$G$77,B91,$F$8:$F$77,1) -> 1 | E91: =COUNTIFS($G$8:$G$77,B91,$F$8:$F$77,2) -> 0 | F91: =COUNTIFS($G$8:$G$77,B91,$F$8:$F$77,3) -> 1 | G91: =COUNTIFS($G$8:$G$77,B91,$F$8:$F$77,4) -> 1 | H91: =IF(C91=0,0,INDEX(Simulador!$E$72:$E$78,MIN(C91,6)+1)) -> 69757.611 | I91: =IF(C91=0,0,INDEX(Simulador!$F$72:$F$78,MIN(C91,6)+1)) -> 90527.009 | J91: =IF(AND(C91>0,Simulador!$C$16="Mensual fijo"),Simulador!$C$14/Simulador!$C$7,0) -> 16216.216 | K91: Ago | L91: =SUMIF($G$8:$G$77,B91,$L$8:$L$77) -> 283217.03 | M91: =SUMIF($G$8:$G$77,B91,$Q$8:$Q$77)+H91+J91 -> 336654.53 | N91: =SUMIF($G$8:$G$77,B91,$T$8:$T$77)+I91+J91 -> 362014.36 | O91: =SUMIF($G$8:$G$77,B91,$R$8:$R$77)+H91+J91 -> 428952.71 | P91: =L91-M91 -> -53437.506 | Q91: =L91-N91 -> -78797.328 | R91: =L91-O91 -> -145735.68
B92: 9 | C92: =COUNTIF($G$8:$G$77,B92) -> 6 | D92: =COUNTIFS($G$8:$G$77,B92,$F$8:$F$77,1) -> 2 | E92: =COUNTIFS($G$8:$G$77,B92,$F$8:$F$77,2) -> 2 | F92: =COUNTIFS($G$8:$G$77,B92,$F$8:$F$77,3) -> 2 | G92: =COUNTIFS($G$8:$G$77,B92,$F$8:$F$77,4) -> 0 | H92: =IF(C92=0,0,INDEX(Simulador!$E$72:$E$78,MIN(C92,6)+1)) -> 0 | I92: =IF(C92=0,0,INDEX(Simulador!$F$72:$F$78,MIN(C92,6)+1)) -> 0 | J92: =IF(AND(C92>0,Simulador!$C$16="Mensual fijo"),Simulador!$C$14/Simulador!$C$7,0) -> 16216.216 | K92: Sep | L92: =SUMIF($G$8:$G$77,B92,$L$8:$L$77) -> 543412.05 | M92: =SUMIF($G$8:$G$77,B92,$Q$8:$Q$77)+H92+J92 -> 464474.84 | N92: =SUMIF($G$8:$G$77,B92,$T$8:$T$77)+I92+J92 -> 469982.54 | O92: =SUMIF($G$8:$G$77,B92,$R$8:$R$77)+H92+J92 -> 633020.89 | P92: =L92-M92 -> 78937.215 | Q92: =L92-N92 -> 73429.511 | R92: =L92-O92 -> -89608.837
B93: 10 | C93: =COUNTIF($G$8:$G$77,B93) -> 6 | D93: =COUNTIFS($G$8:$G$77,B93,$F$8:$F$77,1) -> 3 | E93: =COUNTIFS($G$8:$G$77,B93,$F$8:$F$77,2) -> 0 | F93: =COUNTIFS($G$8:$G$77,B93,$F$8:$F$77,3) -> 3 | G93: =COUNTIFS($G$8:$G$77,B93,$F$8:$F$77,4) -> 0 | H93: =IF(C93=0,0,INDEX(Simulador!$E$72:$E$78,MIN(C93,6)+1)) -> 0 | I93: =IF(C93=0,0,INDEX(Simulador!$F$72:$F$78,MIN(C93,6)+1)) -> 0 | J93: =IF(AND(C93>0,Simulador!$C$16="Mensual fijo"),Simulador!$C$14/Simulador!$C$7,0) -> 16216.216 | K93: Oct | L93: =SUMIF($G$8:$G$77,B93,$L$8:$L$77) -> 516696.65 | M93: =SUMIF($G$8:$G$77,B93,$Q$8:$Q$77)+H93+J93 -> 419923.06 | N93: =SUMIF($G$8:$G$77,B93,$T$8:$T$77)+I93+J93 -> 430840.95 | O93: =SUMIF($G$8:$G$77,B93,$R$8:$R$77)+H93+J93 -> 592552.1 | P93: =L93-M93 -> 96773.59 | Q93: =L93-N93 -> 85855.7 | R93: =L93-O93 -> -75855.453
B94: 11 | C94: =COUNTIF($G$8:$G$77,B94) -> 3 | D94: =COUNTIFS($G$8:$G$77,B94,$F$8:$F$77,1) -> 0 | E94: =COUNTIFS($G$8:$G$77,B94,$F$8:$F$77,2) -> 2 | F94: =COUNTIFS($G$8:$G$77,B94,$F$8:$F$77,3) -> 1 | G94: =COUNTIFS($G$8:$G$77,B94,$F$8:$F$77,4) -> 0 | H94: =IF(C94=0,0,INDEX(Simulador!$E$72:$E$78,MIN(C94,6)+1)) -> 69757.611 | I94: =IF(C94=0,0,INDEX(Simulador!$F$72:$F$78,MIN(C94,6)+1)) -> 90527.009 | J94: =IF(AND(C94>0,Simulador!$C$16="Mensual fijo"),Simulador!$C$14/Simulador!$C$7,0) -> 16216.216 | K94: Nov | L94: =SUMIF($G$8:$G$77,B94,$L$8:$L$77) -> 295132.43 | M94: =SUMIF($G$8:$G$77,B94,$Q$8:$Q$77)+H94+J94 -> 342967.33 | N94: =SUMIF($G$8:$G$77,B94,$T$8:$T$77)+I94+J94 -> 359477.23 | O94: =SUMIF($G$8:$G$77,B94,$R$8:$R$77)+H94+J94 -> 424602.49 | P94: =L94-M94 -> -47834.899 | Q94: =L94-N94 -> -64344.795 | R94: =L94-O94 -> -129470.06
B95: Total | C95: =SUM(C84:C94) -> 70 | D95: =SUM(D84:D94) -> 23 | E95: =SUM(E84:E94) -> 29 | F95: =SUM(F84:F94) -> 14 | G95: =SUM(G84:G94) -> 4 | H95: =SUM(H84:H94) -> 139515.22 | I95: =SUM(I84:I94) -> 181054.02 | J95: =SUM(J84:J94) -> 178378.38 | L95: =SUM(L84:L94) -> 6424357.4 | M95: =SUM(M84:M94) -> 5288334.2 | N95: =SUM(N84:N94) -> 5427732.6 | O95: =SUM(O84:O94) -> 7397509.5 | P95: =SUM(P84:P94) -> 1136023.3 | Q95: =SUM(Q84:Q94) -> 996624.87 | R95: =SUM(R84:R94) -> -973152.06

Sheet Real 2025
B1: Campaña real 2025 · taladro GRS 110 · cómo habría funcionado cada modelo
B2: Movimientos de Movilizaciones_2025.xlsx (detalle, columnas D, C, F, G, H), en orden de fecha. Los meses sin registro no se cuentan (campaña parada). Parámetros y tarifas vienen de la hoja Simulador (verde). Columnas M–P usan las horas del Excel; Q–T, las horas reales del log. Ahorro positivo = el tercerizado cuesta menos.
W3: Modelo | X3: Costo con horas Excel (USD) | Y3: Ahorro con horas Excel (USD) | Z3: Costo con horas reales (USD) | AA3: Ahorro con horas reales (USD)
B4: Resumen | W4: Work Order | X4: =L54 -> 4266318 | Z4: =L54 -> 4266318
W5: Petro Star tarifa normal | X5: =M54+$H$68+$J$68 -> 4105470.6 | Y5: =$X$4-X5 -> 160847.46 | Z5: =Q54+$H$68+$J$68 -> 4337147.8 | AA5: =$Z$4-Z5 -> -70829.783
W6: Petro Star Lump Sum | X6: =N54+$H$68+$J$68 -> 5483328 | Y6: =$X$4-X6 -> -1217010 | Z6: =R54+$H$68+$J$68 -> 5715005.2 | AA6: =$Z$4-Z6 -> -1448687.2
B7: Fecha | C7: Pozo | D7: Km | E7: Rango (log) | F7: Rango nº | G7: Mes | H7: Nº en el mes | I7: Horas reales | J7: Horas Excel | K7: Sobretiempo (h) | L7: Work Order (USD) | M7: Petro Star tarifa normal, horas Excel (USD) | N7: Petro Star Lump Sum, horas Excel (USD) | O7: Lump Sum con descuento (referencia), horas Excel (USD) | P7: Ecotransur, horas Excel (USD) | Q7: Petro Star tarifa normal, horas reales (USD) | R7: Petro Star Lump Sum, horas reales (USD) | S7: Lump Sum con descuento (referencia), horas reales (USD) | T7: Ecotransur, horas reales (USD) | U7: Nota | W7: Lump Sum con descuento (ref.) | X7: =O54+$H$68+$J$68 -> 5186468.1 | Y7: =$X$4-X7 -> -920150.09 | Z7: =S54+$H$68+$J$68 -> 5418145.4 | AA7: =$Z$4-Z7 -> -1151827.3
B8: 45701 | C8: INFA4562 | D8: 12 | E8: 10+ km | F8: =MATCH(E8,{"Misma locación","0.15 - 5 km","5 - 10 km","10+ km"},0) -> 4 | G8: =MONTH(B8) -> 2 | H8: =COUNTIF($G$8:G8,G8) -> 1 | I8: 60 | J8: =INDEX(Simulador!$C$39:$F$39,F8) -> 28 | K8: =IF(I8="","",I8-J8) -> 32 | L8: =INDEX(Simulador!$C$51:$F$51,F8) -> 110984.81 | M8: =IF(H8>=Simulador!$C$19,INDEX(Simulador!$C$63:$F$63,F8),INDEX(Simulador!$C$62:$F$62,F8)) -> 107379.62 | N8: =INDEX(Simulador!$C$64:$F$64,F8) -> 152876.36 | O8: =IF(H8>=Simulador!$C$19,INDEX(Simulador!$C$65:$F$65,F8),INDEX(Simulador!$C$64:$F$64,F8)) -> 152876.36 | P8: =IF(H8>=Simulador!$C$19,INDEX(Simulador!$C$67:$F$67,F8),INDEX(Simulador!$C$66:$F$66,F8)) -> 109162.6 | Q8: =M8+(IF(I8="",J8+INDEX(Simulador!$C$40:$F$40,F8),I8)-J8-INDEX(Simulador!$C$40:$F$40,F8))*Simulador!$C$9-INDEX(Simulador!$C$69:$F$69,F8)+IF(Simulador!$N$7="Sí",MAX(0,IF(I8="",J8+INDEX(Simulador!$C$40:$F$40,F8),I8)-INDEX(Simulador!$C$41:$F$41,F8))*(INDEX(Simulador!$C$68:$F$68,F8)+Simulador!$N$8)/Simulador!$C$7,0) -> 186543.51 | R8: =N8+(IF(I8="",J8+INDEX(Simulador!$C$40:$F$40,F8),I8)-J8-INDEX(Simulador!$C$40:$F$40,F8))*Simulador!$C$9-INDEX(Simulador!$C$69:$F$69,F8)+IF(Simulador!$N$7="Sí",MAX(0,IF(I8="",J8+INDEX(Simulador!$C$40:$F$40,F8),I8)-INDEX(Simulador!$C$41:$F$41,F8))*(INDEX(Simulador!$C$68:$F$68,F8)+Simulador!$N$8)/Simulador!$C$7,0) -> 232040.25 | S8: =O8+(IF(I8="",J8+INDEX(Simulador!$C$40:$F$40,F8),I8)-J8-INDEX(Simulador!$C$40:$F$40,F8))*Simulador!$C$9-INDEX(Simulador!$C$69:$F$69,F8)+IF(Simulador!$N$7="Sí",MAX(0,IF(I8="",J8+INDEX(Simulador!$C$40:$F$40,F8),I8)-INDEX(Simulador!$C$41:$F$41,F8))*(INDEX(Simulador!$C$68:$F$68,F8)+Simulador!$N$8)/Simulador!$C$7,0) -> 232040.25 | T8: =P8+(IF(I8="",J8+INDEX(Simulador!$C$40:$F$40,F8),I8)-J8-INDEX(Simulador!$C$40:$F$40,F8))*Simulador!$C$9-INDEX(Simulador!$C$69:$F$69,F8)+IF(Simulador!$N$7="Sí",MAX(0,IF(I8="",J8+INDEX(Simulador!$C$40:$F$40,F8),I8)-INDEX(Simulador!$C$41:$F$41,F8))*(INDEX(Simulador!$C$68:$F$68,F8)+Simulador!$N$8)/Simulador!$C$7,0) -> 188326.49 | W8: Ecotransur | X8: =P54+$I$68+$J$68 -> 4113803.7 | Y8: =$X$4-X8 -> 152514.34 | Z8: =T54+$I$68+$J$68 -> 4345480.9 | AA8: =$Z$4-Z8 -> -79162.904
B9: 45725 | C9: CIRA5216 | D9: 13.5 | E9: 10+ km | F9: =MATCH(E9,{"Misma locación","0.15 - 5 km","5 - 10 km","10+ km"},0) -> 4 | G9: =MONTH(B9) -> 3 | H9: =COUNTIF($G$8:G9,G9) -> 1 | I9: 41.25 | J9: =INDEX(Simulador!$C$39:$F$39,F9) -> 28 | K9: =IF(I9="","",I9-J9) -> 13.25 | L9: =INDEX(Simulador!$C$51:$F$51,F9) -> 110984.81 | M9: =IF(H9>=Simulador!$C$19,INDEX(Simulador!$C$63:$F$63,F9),INDEX(Simulador!$C$62:$F$62,F9)) -> 107379.62 | N9: =INDEX(Simulador!$C$64:$F$64,F9) -> 152876.36 | O9: =IF(H9>=Simulador!$C$19,INDEX(Simulador!$C$65:$F$65,F9),INDEX(Simulador!$C$64:$F$64,F9)) -> 152876.36 | P9: =IF(H9>=Simulador!$C$19,INDEX(Simulador!$C$67:$F$67,F9),INDEX(Simulador!$C$66:$F$66,F9)) -> 109162.6 | Q9: =M9+(IF(I9="",J9+INDEX(Simulador!$C$40:$F$40,F9),I9)-J9-INDEX(Simulador!$C$40:$F$40,F9))*Simulador!$C$9-INDEX(Simulador!$C$69:$F$69,F9)+IF(Simulador!$N$7="Sí",MAX(0,IF(I9="",J9+INDEX(Simulador!$C$40:$F$40,F9),I9)-INDEX(Simulador!$C$41:$F$41,F9))*(INDEX(Simulador!$C$68:$F$68,F9)+Simulador!$N$8)/Simulador!$C$7,0) -> 133796.72 | R9: =N9+(IF(I9="",J9+INDEX(Simulador!$C$40:$F$40,F9),I9)-J9-INDEX(Simulador!$C$40:$F$40,F9))*Simulador!$C$9-INDEX(Simulador!$C$69:$F$69,F9)+IF(Simulador!$N$7="Sí",MAX(0,IF(I9="",J9+INDEX(Simulador!$C$40:$F$40,F9),I9)-INDEX(Simulador!$C$41:$F$41,F9))*(INDEX(Simulador!$C$68:$F$68,F9)+Simulador!$N$8)/Simulador!$C$7,0) -> 179293.46 | S9: =O9+(IF(I9="",J9+INDEX(Simulador!$C$40:$F$40,F9),I9)-J9-INDEX(Simulador!$C$40:$F$40,F9))*Simulador!$C$9-INDEX(Simulador!$C$69:$F$69,F9)+IF(Simulador!$N$7="Sí",MAX(0,IF(I9="",J9+INDEX(Simulador!$C$40:$F$40,F9),I9)-INDEX(Simulador!$C$41:$F$41,F9))*(INDEX(Simulador!$C$68:$F$68,F9)+Simulador!$N$8)/Simulador!$C$7,0) -> 179293.46 | T9: =P9+(IF(I9="",J9+INDEX(Simulador!$C$40:$F$40,F9),I9)-J9-INDEX(Simulador!$C$40:$F$40,F9))*Simulador!$C$9-INDEX(Simulador!$C$69:$F$69,F9)+IF(Simulador!$N$7="Sí",MAX(0,IF(I9="",J9+INDEX(Simulador!$C$40:$F$40,F9),I9)-INDEX(Simulador!$C$41:$F$41,F9))*(INDEX(Simulador!$C$68:$F$68,F9)+Simulador!$N$8)/Simulador!$C$7,0) -> 135579.7 | W9: Movilizaciones | X9: =COUNT(B8:B52) -> 45
B10: 45738 | C10: CIRA5260 | D10: 2.4 | E10: 0.15 - 5 km | F10: =MATCH(E10,{"Misma locación","0.15 - 5 km","5 - 10 km","10+ km"},0) -> 2 | G10: =MONTH(B10) -> 3 | H10: =COUNTIF($G$8:G10,G10) -> 2 | I10: 25.5 | J10: =INDEX(Simulador!$C$39:$F$39,F10) -> 18 | K10: =IF(I10="","",I10-J10) -> 7.5 | L10: =INDEX(Simulador!$C$51:$F$51,F10) -> 99473.811 | M10: =IF(H10>=Simulador!$C$19,INDEX(Simulador!$C$63:$F$63,F10),INDEX(Simulador!$C$62:$F$62,F10)) -> 85898.023 | N10: =INDEX(Simulador!$C$64:$F$64,F10) -> 108447.11 | O10: =IF(H10>=Simulador!$C$19,INDEX(Simulador!$C$65:$F$65,F10),INDEX(Simulador!$C$64:$F$64,F10)) -> 108447.11 | P10: =IF(H10>=Simulador!$C$19,INDEX(Simulador!$C$67:$F$67,F10),INDEX(Simulador!$C$66:$F$66,F10)) -> 82343.946 | Q10: =M10+(IF(I10="",J10+INDEX(Simulador!$C$40:$F$40,F10),I10)-J10-INDEX(Simulador!$C$40:$F$40,F10))*Simulador!$C$9-INDEX(Simulador!$C$69:$F$69,F10)+IF(Simulador!$N$7="Sí",MAX(0,IF(I10="",J10+INDEX(Simulador!$C$40:$F$40,F10),I10)-INDEX(Simulador!$C$41:$F$41,F10))*(INDEX(Simulador!$C$68:$F$68,F10)+Simulador!$N$8)/Simulador!$C$7,0) -> 98853.766 | R10: =N10+(IF(I10="",J10+INDEX(Simulador!$C$40:$F$40,F10),I10)-J10-INDEX(Simulador!$C$40:$F$40,F10))*Simulador!$C$9-INDEX(Simulador!$C$69:$F$69,F10)+IF(Simulador!$N$7="Sí",MAX(0,IF(I10="",J10+INDEX(Simulador!$C$40:$F$40,F10),I10)-INDEX(Simulador!$C$41:$F$41,F10))*(INDEX(Simulador!$C$68:$F$68,F10)+Simulador!$N$8)/Simulador!$C$7,0) -> 121402.85 | S10: =O10+(IF(I10="",J10+INDEX(Simulador!$C$40:$F$40,F10),I10)-J10-INDEX(Simulador!$C$40:$F$40,F10))*Simulador!$C$9-INDEX(Simulador!$C$69:$F$69,F10)+IF(Simulador!$N$7="Sí",MAX(0,IF(I10="",J10+INDEX(Simulador!$C$40:$F$40,F10),I10)-INDEX(Simulador!$C$41:$F$41,F10))*(INDEX(Simulador!$C$68:$F$68,F10)+Simulador!$N$8)/Simulador!$C$7,0) -> 121402.85 | T10: =P10+(IF(I10="",J10+INDEX(Simulador!$C$40:$F$40,F10),I10)-J10-INDEX(Simulador!$C$40:$F$40,F10))*Simulador!$C$9-INDEX(Simulador!$C$69:$F$69,F10)+IF(Simulador!$N$7="Sí",MAX(0,IF(I10="",J10+INDEX(Simulador!$C$40:$F$40,F10),I10)-INDEX(Simulador!$C$41:$F$41,F10))*(INDEX(Simulador!$C$68:$F$68,F10)+Simulador!$N$8)/Simulador!$C$7,0) -> 95299.69 | W10: Meses con movilizaciones | X10: =COUNTIF(C59:C67,">0") -> 9
B11: 45743 | C11: CIRA5131 | D11: 0.0064007998 | E11: Misma locación | F11: =MATCH(E11,{"Misma locación","0.15 - 5 km","5 - 10 km","10+ km"},0) -> 1 | G11: =MONTH(B11) -> 3 | H11: =COUNTIF($G$8:G11,G11) -> 3 | I11: 11.75 | J11: =INDEX(Simulador!$C$39:$F$39,F11) -> 12 | K11: =IF(I11="","",I11-J11) -> -0.25 | L11: =INDEX(Simulador!$C$51:$F$51,F11) -> 76047.405 | M11: =IF(H11>=Simulador!$C$19,INDEX(Simulador!$C$63:$F$63,F11),INDEX(Simulador!$C$62:$F$62,F11)) -> 55414.011 | N11: =INDEX(Simulador!$C$64:$F$64,F11) -> 65678.455 | O11: =IF(H11>=Simulador!$C$19,INDEX(Simulador!$C$65:$F$65,F11),INDEX(Simulador!$C$64:$F$64,F11)) -> 65678.455 | P11: =IF(H11>=Simulador!$C$19,INDEX(Simulador!$C$67:$F$67,F11),INDEX(Simulador!$C$66:$F$66,F11)) -> 55372.811 | Q11: =M11+(IF(I11="",J11+INDEX(Simulador!$C$40:$F$40,F11),I11)-J11-INDEX(Simulador!$C$40:$F$40,F11))*Simulador!$C$9-INDEX(Simulador!$C$69:$F$69,F11)+IF(Simulador!$N$7="Sí",MAX(0,IF(I11="",J11+INDEX(Simulador!$C$40:$F$40,F11),I11)-INDEX(Simulador!$C$41:$F$41,F11))*(INDEX(Simulador!$C$68:$F$68,F11)+Simulador!$N$8)/Simulador!$C$7,0) -> 55050.011 | R11: =N11+(IF(I11="",J11+INDEX(Simulador!$C$40:$F$40,F11),I11)-J11-INDEX(Simulador!$C$40:$F$40,F11))*Simulador!$C$9-INDEX(Simulador!$C$69:$F$69,F11)+IF(Simulador!$N$7="Sí",MAX(0,IF(I11="",J11+INDEX(Simulador!$C$40:$F$40,F11),I11)-INDEX(Simulador!$C$41:$F$41,F11))*(INDEX(Simulador!$C$68:$F$68,F11)+Simulador!$N$8)/Simulador!$C$7,0) -> 65314.455 | S11: =O11+(IF(I11="",J11+INDEX(Simulador!$C$40:$F$40,F11),I11)-J11-INDEX(Simulador!$C$40:$F$40,F11))*Simulador!$C$9-INDEX(Simulador!$C$69:$F$69,F11)+IF(Simulador!$N$7="Sí",MAX(0,IF(I11="",J11+INDEX(Simulador!$C$40:$F$40,F11),I11)-INDEX(Simulador!$C$41:$F$41,F11))*(INDEX(Simulador!$C$68:$F$68,F11)+Simulador!$N$8)/Simulador!$C$7,0) -> 65314.455 | T11: =P11+(IF(I11="",J11+INDEX(Simulador!$C$40:$F$40,F11),I11)-J11-INDEX(Simulador!$C$40:$F$40,F11))*Simulador!$C$9-INDEX(Simulador!$C$69:$F$69,F11)+IF(Simulador!$N$7="Sí",MAX(0,IF(I11="",J11+INDEX(Simulador!$C$40:$F$40,F11),I11)-INDEX(Simulador!$C$41:$F$41,F11))*(INDEX(Simulador!$C$68:$F$68,F11)+Simulador!$N$8)/Simulador!$C$7,0) -> 55008.811 | W11: Promedio movs/mes (meses activos) | X11: =X9/X10 -> 5
B12: 45747 | C12: CIRA5087 | D12: 0.6 | E12: 0.15 - 5 km | F12: =MATCH(E12,{"Misma locación","0.15 - 5 km","5 - 10 km","10+ km"},0) -> 2 | G12: =MONTH(B12) -> 3 | H12: =COUNTIF($G$8:G12,G12) -> 4 | I12: 19.5 | J12: =INDEX(Simulador!$C$39:$F$39,F12) -> 18 | K12: =IF(I12="","",I12-J12) -> 1.5 | L12: =INDEX(Simulador!$C$51:$F$51,F12) -> 99473.811 | M12: =IF(H12>=Simulador!$C$19,INDEX(Simulador!$C$63:$F$63,F12),INDEX(Simulador!$C$62:$F$62,F12)) -> 85898.023 | N12: =INDEX(Simulador!$C$64:$F$64,F12) -> 108447.11 | O12: =IF(H12>=Simulador!$C$19,INDEX(Simulador!$C$65:$F$65,F12),INDEX(Simulador!$C$64:$F$64,F12)) -> 108447.11 | P12: =IF(H12>=Simulador!$C$19,INDEX(Simulador!$C$67:$F$67,F12),INDEX(Simulador!$C$66:$F$66,F12)) -> 82343.946 | Q12: =M12+(IF(I12="",J12+INDEX(Simulador!$C$40:$F$40,F12),I12)-J12-INDEX(Simulador!$C$40:$F$40,F12))*Simulador!$C$9-INDEX(Simulador!$C$69:$F$69,F12)+IF(Simulador!$N$7="Sí",MAX(0,IF(I12="",J12+INDEX(Simulador!$C$40:$F$40,F12),I12)-INDEX(Simulador!$C$41:$F$41,F12))*(INDEX(Simulador!$C$68:$F$68,F12)+Simulador!$N$8)/Simulador!$C$7,0) -> 88082.023 | R12: =N12+(IF(I12="",J12+INDEX(Simulador!$C$40:$F$40,F12),I12)-J12-INDEX(Simulador!$C$40:$F$40,F12))*Simulador!$C$9-INDEX(Simulador!$C$69:$F$69,F12)+IF(Simulador!$N$7="Sí",MAX(0,IF(I12="",J12+INDEX(Simulador!$C$40:$F$40,F12),I12)-INDEX(Simulador!$C$41:$F$41,F12))*(INDEX(Simulador!$C$68:$F$68,F12)+Simulador!$N$8)/Simulador!$C$7,0) -> 110631.11 | S12: =O12+(IF(I12="",J12+INDEX(Simulador!$C$40:$F$40,F12),I12)-J12-INDEX(Simulador!$C$40:$F$40,F12))*Simulador!$C$9-INDEX(Simulador!$C$69:$F$69,F12)+IF(Simulador!$N$7="Sí",MAX(0,IF(I12="",J12+INDEX(Simulador!$C$40:$F$40,F12),I12)-INDEX(Simulador!$C$41:$F$41,F12))*(INDEX(Simulador!$C$68:$F$68,F12)+Simulador!$N$8)/Simulador!$C$7,0) -> 110631.11 | T12: =P12+(IF(I12="",J12+INDEX(Simulador!$C$40:$F$40,F12),I12)-J12-INDEX(Simulador!$C$40:$F$40,F12))*Simulador!$C$9-INDEX(Simulador!$C$69:$F$69,F12)+IF(Simulador!$N$7="Sí",MAX(0,IF(I12="",J12+INDEX(Simulador!$C$40:$F$40,F12),I12)-INDEX(Simulador!$C$41:$F$41,F12))*(INDEX(Simulador!$C$68:$F$68,F12)+Simulador!$N$8)/Simulador!$C$7,0) -> 84527.946 | W12: Meses con 6 o más movilizaciones | X12: =COUNTIF(C59:C67,">=6") -> 4
B13: 45752 | C13: CIRA5116 | D13: 0.58 | E13: 0.15 - 5 km | F13: =MATCH(E13,{"Misma locación","0.15 - 5 km","5 - 10 km","10+ km"},0) -> 2 | G13: =MONTH(B13) -> 4 | H13: =COUNTIF($G$8:G13,G13) -> 1 | I13: 15.75 | J13: =INDEX(Simulador!$C$39:$F$39,F13) -> 18 | K13: =IF(I13="","",I13-J13) -> -2.25 | L13: =INDEX(Simulador!$C$51:$F$51,F13) -> 99473.811 | M13: =IF(H13>=Simulador!$C$19,INDEX(Simulador!$C$63:$F$63,F13),INDEX(Simulador!$C$62:$F$62,F13)) -> 85898.023 | N13: =INDEX(Simulador!$C$64:$F$64,F13) -> 108447.11 | O13: =IF(H13>=Simulador!$C$19,INDEX(Simulador!$C$65:$F$65,F13),INDEX(Simulador!$C$64:$F$64,F13)) -> 108447.11 | P13: =IF(H13>=Simulador!$C$19,INDEX(Simulador!$C$67:$F$67,F13),INDEX(Simulador!$C$66:$F$66,F13)) -> 82343.946 | Q13: =M13+(IF(I13="",J13+INDEX(Simulador!$C$40:$F$40,F13),I13)-J13-INDEX(Simulador!$C$40:$F$40,F13))*Simulador!$C$9-INDEX(Simulador!$C$69:$F$69,F13)+IF(Simulador!$N$7="Sí",MAX(0,IF(I13="",J13+INDEX(Simulador!$C$40:$F$40,F13),I13)-INDEX(Simulador!$C$41:$F$41,F13))*(INDEX(Simulador!$C$68:$F$68,F13)+Simulador!$N$8)/Simulador!$C$7,0) -> 82622.023 | R13: =N13+(IF(I13="",J13+INDEX(Simulador!$C$40:$F$40,F13),I13)-J13-INDEX(Simulador!$C$40:$F$40,F13))*Simulador!$C$9-INDEX(Simulador!$C$69:$F$69,F13)+IF(Simulador!$N$7="Sí",MAX(0,IF(I13="",J13+INDEX(Simulador!$C$40:$F$40,F13),I13)-INDEX(Simulador!$C$41:$F$41,F13))*(INDEX(Simulador!$C$68:$F$68,F13)+Simulador!$N$8)/Simulador!$C$7,0) -> 105171.11 | S13: =O13+(IF(I13="",J13+INDEX(Simulador!$C$40:$F$40,F13),I13)-J13-INDEX(Simulador!$C$40:$F$40,F13))*Simulador!$C$9-INDEX(Simulador!$C$69:$F$69,F13)+IF(Simulador!$N$7="Sí",MAX(0,IF(I13="",J13+INDEX(Simulador!$C$40:$F$40,F13),I13)-INDEX(Simulador!$C$41:$F$41,F13))*(INDEX(Simulador!$C$68:$F$68,F13)+Simulador!$N$8)/Simulador!$C$7,0) -> 105171.11 | T13: =P13+(IF(I13="",J13+INDEX(Simulador!$C$40:$F$40,F13),I13)-J13-INDEX(Simulador!$C$40:$F$40,F13))*Simulador!$C$9-INDEX(Simulador!$C$69:$F$69,F13)+IF(Simulador!$N$7="Sí",MAX(0,IF(I13="",J13+INDEX(Simulador!$C$40:$F$40,F13),I13)-INDEX(Simulador!$C$41:$F$41,F13))*(INDEX(Simulador!$C$68:$F$68,F13)+Simulador!$N$8)/Simulador!$C$7,0) -> 79067.946 | W13: Meses con menos de 5 movilizaciones | X13: =COUNTIF(C59:C67,"<5") -> 3
B14: 45756 | C14: CIRA5822 | D14: 0.0128016 | E14: Misma locación | F14: =MATCH(E14,{"Misma locación","0.15 - 5 km","5 - 10 km","10+ km"},0) -> 1 | G14: =MONTH(B14) -> 4 | H14: =COUNTIF($G$8:G14,G14) -> 2 | I14: 15.5 | J14: =INDEX(Simulador!$C$39:$F$39,F14) -> 12 | K14: =IF(I14="","",I14-J14) -> 3.5 | L14: =INDEX(Simulador!$C$51:$F$51,F14) -> 76047.405 | M14: =IF(H14>=Simulador!$C$19,INDEX(Simulador!$C$63:$F$63,F14),INDEX(Simulador!$C$62:$F$62,F14)) -> 55414.011 | N14: =INDEX(Simulador!$C$64:$F$64,F14) -> 65678.455 | O14: =IF(H14>=Simulador!$C$19,INDEX(Simulador!$C$65:$F$65,F14),INDEX(Simulador!$C$64:$F$64,F14)) -> 65678.455 | P14: =IF(H14>=Simulador!$C$19,INDEX(Simulador!$C$67:$F$67,F14),INDEX(Simulador!$C$66:$F$66,F14)) -> 55372.811 | Q14: =M14+(IF(I14="",J14+INDEX(Simulador!$C$40:$F$40,F14),I14)-J14-INDEX(Simulador!$C$40:$F$40,F14))*Simulador!$C$9-INDEX(Simulador!$C$69:$F$69,F14)+IF(Simulador!$N$7="Sí",MAX(0,IF(I14="",J14+INDEX(Simulador!$C$40:$F$40,F14),I14)-INDEX(Simulador!$C$41:$F$41,F14))*(INDEX(Simulador!$C$68:$F$68,F14)+Simulador!$N$8)/Simulador!$C$7,0) -> 65260.079 | R14: =N14+(IF(I14="",J14+INDEX(Simulador!$C$40:$F$40,F14),I14)-J14-INDEX(Simulador!$C$40:$F$40,F14))*Simulador!$C$9-INDEX(Simulador!$C$69:$F$69,F14)+IF(Simulador!$N$7="Sí",MAX(0,IF(I14="",J14+INDEX(Simulador!$C$40:$F$40,F14),I14)-INDEX(Simulador!$C$41:$F$41,F14))*(INDEX(Simulador!$C$68:$F$68,F14)+Simulador!$N$8)/Simulador!$C$7,0) -> 75524.523 | S14: =O14+(IF(I14="",J14+INDEX(Simulador!$C$40:$F$40,F14),I14)-J14-INDEX(Simulador!$C$40:$F$40,F14))*Simulador!$C$9-INDEX(Simulador!$C$69:$F$69,F14)+IF(Simulador!$N$7="Sí",MAX(0,IF(I14="",J14+INDEX(Simulador!$C$40:$F$40,F14),I14)-INDEX(Simulador!$C$41:$F$41,F14))*(INDEX(Simulador!$C$68:$F$68,F14)+Simulador!$N$8)/Simulador!$C$7,0) -> 75524.523 | T14: =P14+(IF(I14="",J14+INDEX(Simulador!$C$40:$F$40,F14),I14)-J14-INDEX(Simulador!$C$40:$F$40,F14))*Simulador!$C$9-INDEX(Simulador!$C$69:$F$69,F14)+IF(Simulador!$N$7="Sí",MAX(0,IF(I14="",J14+INDEX(Simulador!$C$40:$F$40,F14),I14)-INDEX(Simulador!$C$41:$F$41,F14))*(INDEX(Simulador!$C$68:$F$68,F14)+Simulador!$N$8)/Simulador!$C$7,0) -> 65218.879
B15: 45759 | C15: CIRA5297 | D15: 8.2 | E15: 5 - 10 km | F15: =MATCH(E15,{"Misma locación","0.15 - 5 km","5 - 10 km","10+ km"},0) -> 3 | G15: =MONTH(B15) -> 4 | H15: =COUNTIF($G$8:G15,G15) -> 3 | I15: 20 | J15: =INDEX(Simulador!$C$39:$F$39,F15) -> 24 | K15: =IF(I15="","",I15-J15) -> -4 | L15: =INDEX(Simulador!$C$51:$F$51,F15) -> 96184.811 | M15: =IF(H15>=Simulador!$C$19,INDEX(Simulador!$C$63:$F$63,F15),INDEX(Simulador!$C$62:$F$62,F15)) -> 99393.459 | N15: =INDEX(Simulador!$C$64:$F$64,F15) -> 135930.45 | O15: =IF(H15>=Simulador!$C$19,INDEX(Simulador!$C$65:$F$65,F15),INDEX(Simulador!$C$64:$F$64,F15)) -> 135930.45 | P15: =IF(H15>=Simulador!$C$19,INDEX(Simulador!$C$67:$F$67,F15),INDEX(Simulador!$C$66:$F$66,F15)) -> 102242.11 | Q15: =M15+(IF(I15="",J15+INDEX(Simulador!$C$40:$F$40,F15),I15)-J15-INDEX(Simulador!$C$40:$F$40,F15))*Simulador!$C$9-INDEX(Simulador!$C$69:$F$69,F15)+IF(Simulador!$N$7="Sí",MAX(0,IF(I15="",J15+INDEX(Simulador!$C$40:$F$40,F15),I15)-INDEX(Simulador!$C$41:$F$41,F15))*(INDEX(Simulador!$C$68:$F$68,F15)+Simulador!$N$8)/Simulador!$C$7,0) -> 93569.459 | R15: =N15+(IF(I15="",J15+INDEX(Simulador!$C$40:$F$40,F15),I15)-J15-INDEX(Simulador!$C$40:$F$40,F15))*Simulador!$C$9-INDEX(Simulador!$C$69:$F$69,F15)+IF(Simulador!$N$7="Sí",MAX(0,IF(I15="",J15+INDEX(Simulador!$C$40:$F$40,F15),I15)-INDEX(Simulador!$C$41:$F$41,F15))*(INDEX(Simulador!$C$68:$F$68,F15)+Simulador!$N$8)/Simulador!$C$7,0) -> 130106.45 | S15: =O15+(IF(I15="",J15+INDEX(Simulador!$C$40:$F$40,F15),I15)-J15-INDEX(Simulador!$C$40:$F$40,F15))*Simulador!$C$9-INDEX(Simulador!$C$69:$F$69,F15)+IF(Simulador!$N$7="Sí",MAX(0,IF(I15="",J15+INDEX(Simulador!$C$40:$F$40,F15),I15)-INDEX(Simulador!$C$41:$F$41,F15))*(INDEX(Simulador!$C$68:$F$68,F15)+Simulador!$N$8)/Simulador!$C$7,0) -> 130106.45 | T15: =P15+(IF(I15="",J15+INDEX(Simulador!$C$40:$F$40,F15),I15)-J15-INDEX(Simulador!$C$40:$F$40,F15))*Simulador!$C$9-INDEX(Simulador!$C$69:$F$69,F15)+IF(Simulador!$N$7="Sí",MAX(0,IF(I15="",J15+INDEX(Simulador!$C$40:$F$40,F15),I15)-INDEX(Simulador!$C$41:$F$41,F15))*(INDEX(Simulador!$C$68:$F$68,F15)+Simulador!$N$8)/Simulador!$C$7,0) -> 96418.109
B16: 45763 | C16: CIRA5293 | D16: 0.038404799 | E16: Misma locación | F16: =MATCH(E16,{"Misma locación","0.15 - 5 km","5 - 10 km","10+ km"},0) -> 1 | G16: =MONTH(B16) -> 4 | H16: =COUNTIF($G$8:G16,G16) -> 4 | I16: 13.5 | J16: =INDEX(Simulador!$C$39:$F$39,F16) -> 12 | K16: =IF(I16="","",I16-J16) -> 1.5 | L16: =INDEX(Simulador!$C$51:$F$51,F16) -> 76047.405 | M16: =IF(H16>=Simulador!$C$19,INDEX(Simulador!$C$63:$F$63,F16),INDEX(Simulador!$C$62:$F$62,F16)) -> 55414.011 | N16: =INDEX(Simulador!$C$64:$F$64,F16) -> 65678.455 | O16: =IF(H16>=Simulador!$C$19,INDEX(Simulador!$C$65:$F$65,F16),INDEX(Simulador!$C$64:$F$64,F16)) -> 65678.455 | P16: =IF(H16>=Simulador!$C$19,INDEX(Simulador!$C$67:$F$67,F16),INDEX(Simulador!$C$66:$F$66,F16)) -> 55372.811 | Q16: =M16+(IF(I16="",J16+INDEX(Simulador!$C$40:$F$40,F16),I16)-J16-INDEX(Simulador!$C$40:$F$40,F16))*Simulador!$C$9-INDEX(Simulador!$C$69:$F$69,F16)+IF(Simulador!$N$7="Sí",MAX(0,IF(I16="",J16+INDEX(Simulador!$C$40:$F$40,F16),I16)-INDEX(Simulador!$C$41:$F$41,F16))*(INDEX(Simulador!$C$68:$F$68,F16)+Simulador!$N$8)/Simulador!$C$7,0) -> 59633.754 | R16: =N16+(IF(I16="",J16+INDEX(Simulador!$C$40:$F$40,F16),I16)-J16-INDEX(Simulador!$C$40:$F$40,F16))*Simulador!$C$9-INDEX(Simulador!$C$69:$F$69,F16)+IF(Simulador!$N$7="Sí",MAX(0,IF(I16="",J16+INDEX(Simulador!$C$40:$F$40,F16),I16)-INDEX(Simulador!$C$41:$F$41,F16))*(INDEX(Simulador!$C$68:$F$68,F16)+Simulador!$N$8)/Simulador!$C$7,0) -> 69898.199 | S16: =O16+(IF(I16="",J16+INDEX(Simulador!$C$40:$F$40,F16),I16)-J16-INDEX(Simulador!$C$40:$F$40,F16))*Simulador!$C$9-INDEX(Simulador!$C$69:$F$69,F16)+IF(Simulador!$N$7="Sí",MAX(0,IF(I16="",J16+INDEX(Simulador!$C$40:$F$40,F16),I16)-INDEX(Simulador!$C$41:$F$41,F16))*(INDEX(Simulador!$C$68:$F$68,F16)+Simulador!$N$8)/Simulador!$C$7,0) -> 69898.199 | T16: =P16+(IF(I16="",J16+INDEX(Simulador!$C$40:$F$40,F16),I16)-J16-INDEX(Simulador!$C$40:$F$40,F16))*Simulador!$C$9-INDEX(Simulador!$C$69:$F$69,F16)+IF(Simulador!$N$7="Sí",MAX(0,IF(I16="",J16+INDEX(Simulador!$C$40:$F$40,F16),I16)-INDEX(Simulador!$C$41:$F$41,F16))*(INDEX(Simulador!$C$68:$F$68,F16)+Simulador!$N$8)/Simulador!$C$7,0) -> 59592.555
B17: 45767 | C17: CIRA5107 | D17: 0.4 | E17: 0.15 - 5 km | F17: =MATCH(E17,{"Misma locación","0.15 - 5 km","5 - 10 km","10+ km"},0) -> 2 | G17: =MONTH(B17) -> 4 | H17: =COUNTIF($G$8:G17,G17) -> 5 | I17: 15 | J17: =INDEX(Simulador!$C$39:$F$39,F17) -> 18 | K17: =IF(I17="","",I17-J17) -> -3 | L17: =INDEX(Simulador!$C$51:$F$51,F17) -> 99473.811 | M17: =IF(H17>=Simulador!$C$19,INDEX(Simulador!$C$63:$F$63,F17),INDEX(Simulador!$C$62:$F$62,F17)) -> 85898.023 | N17: =INDEX(Simulador!$C$64:$F$64,F17) -> 108447.11 | O17: =IF(H17>=Simulador!$C$19,INDEX(Simulador!$C$65:$F$65,F17),INDEX(Simulador!$C$64:$F$64,F17)) -> 108447.11 | P17: =IF(H17>=Simulador!$C$19,INDEX(Simulador!$C$67:$F$67,F17),INDEX(Simulador!$C$66:$F$66,F17)) -> 82343.946 | Q17: =M17+(IF(I17="",J17+INDEX(Simulador!$C$40:$F$40,F17),I17)-J17-INDEX(Simulador!$C$40:$F$40,F17))*Simulador!$C$9-INDEX(Simulador!$C$69:$F$69,F17)+IF(Simulador!$N$7="Sí",MAX(0,IF(I17="",J17+INDEX(Simulador!$C$40:$F$40,F17),I17)-INDEX(Simulador!$C$41:$F$41,F17))*(INDEX(Simulador!$C$68:$F$68,F17)+Simulador!$N$8)/Simulador!$C$7,0) -> 81530.023 | R17: =N17+(IF(I17="",J17+INDEX(Simulador!$C$40:$F$40,F17),I17)-J17-INDEX(Simulador!$C$40:$F$40,F17))*Simulador!$C$9-INDEX(Simulador!$C$69:$F$69,F17)+IF(Simulador!$N$7="Sí",MAX(0,IF(I17="",J17+INDEX(Simulador!$C$40:$F$40,F17),I17)-INDEX(Simulador!$C$41:$F$41,F17))*(INDEX(Simulador!$C$68:$F$68,F17)+Simulador!$N$8)/Simulador!$C$7,0) -> 104079.11 | S17: =O17+(IF(I17="",J17+INDEX(Simulador!$C$40:$F$40,F17),I17)-J17-INDEX(Simulador!$C$40:$F$40,F17))*Simulador!$C$9-INDEX(Simulador!$C$69:$F$69,F17)+IF(Simulador!$N$7="Sí",MAX(0,IF(I17="",J17+INDEX(Simulador!$C$40:$F$40,F17),I17)-INDEX(Simulador!$C$41:$F$41,F17))*(INDEX(Simulador!$C$68:$F$68,F17)+Simulador!$N$8)/Simulador!$C$7,0) -> 104079.11 | T17: =P17+(IF(I17="",J17+INDEX(Simulador!$C$40:$F$40,F17),I17)-J17-INDEX(Simulador!$C$40:$F$40,F17))*Simulador!$C$9-INDEX(Simulador!$C$69:$F$69,F17)+IF(Simulador!$N$7="Sí",MAX(0,IF(I17="",J17+INDEX(Simulador!$C$40:$F$40,F17),I17)-INDEX(Simulador!$C$41:$F$41,F17))*(INDEX(Simulador!$C$68:$F$68,F17)+Simulador!$N$8)/Simulador!$C$7,0) -> 77975.946
B18: 45770 | C18: CIRA5885 | D18: 0.1072896 | E18: Misma locación | F18: =MATCH(E18,{"Misma locación","0.15 - 5 km","5 - 10 km","10+ km"},0) -> 1 | G18: =MONTH(B18) -> 4 | H18: =COUNTIF($G$8:G18,G18) -> 6 | I18: 13.5 | J18: =INDEX(Simulador!$C$39:$F$39,F18) -> 12 | K18: =IF(I18="","",I18-J18) -> 1.5 | L18: =INDEX(Simulador!$C$51:$F$51,F18) -> 76047.405 | M18: =IF(H18>=Simulador!$C$19,INDEX(Simulador!$C$63:$F$63,F18),INDEX(Simulador!$C$62:$F$62,F18)) -> 36443.006 | N18: =INDEX(Simulador!$C$64:$F$64,F18) -> 65678.455 | O18: =IF(H18>=Simulador!$C$19,INDEX(Simulador!$C$65:$F$65,F18),INDEX(Simulador!$C$64:$F$64,F18)) -> 41575.228 | P18: =IF(H18>=Simulador!$C$19,INDEX(Simulador!$C$67:$F$67,F18),INDEX(Simulador!$C$66:$F$66,F18)) -> 50763.892 | Q18: =M18+(IF(I18="",J18+INDEX(Simulador!$C$40:$F$40,F18),I18)-J18-INDEX(Simulador!$C$40:$F$40,F18))*Simulador!$C$9-INDEX(Simulador!$C$69:$F$69,F18)+IF(Simulador!$N$7="Sí",MAX(0,IF(I18="",J18+INDEX(Simulador!$C$40:$F$40,F18),I18)-INDEX(Simulador!$C$41:$F$41,F18))*(INDEX(Simulador!$C$68:$F$68,F18)+Simulador!$N$8)/Simulador!$C$7,0) -> 40662.749 | R18: =N18+(IF(I18="",J18+INDEX(Simulador!$C$40:$F$40,F18),I18)-J18-INDEX(Simulador!$C$40:$F$40,F18))*Simulador!$C$9-INDEX(Simulador!$C$69:$F$69,F18)+IF(Simulador!$N$7="Sí",MAX(0,IF(I18="",J18+INDEX(Simulador!$C$40:$F$40,F18),I18)-INDEX(Simulador!$C$41:$F$41,F18))*(INDEX(Simulador!$C$68:$F$68,F18)+Simulador!$N$8)/Simulador!$C$7,0) -> 69898.199 | S18: =O18+(IF(I18="",J18+INDEX(Simulador!$C$40:$F$40,F18),I18)-J18-INDEX(Simulador!$C$40:$F$40,F18))*Simulador!$C$9-INDEX(Simulador!$C$69:$F$69,F18)+IF(Simulador!$N$7="Sí",MAX(0,IF(I18="",J18+INDEX(Simulador!$C$40:$F$40,F18),I18)-INDEX(Simulador!$C$41:$F$41,F18))*(INDEX(Simulador!$C$68:$F$68,F18)+Simulador!$N$8)/Simulador!$C$7,0) -> 45794.971 | T18: =P18+(IF(I18="",J18+INDEX(Simulador!$C$40:$F$40,F18),I18)-J18-INDEX(Simulador!$C$40:$F$40,F18))*Simulador!$C$9-INDEX(Simulador!$C$69:$F$69,F18)+IF(Simulador!$N$7="Sí",MAX(0,IF(I18="",J18+INDEX(Simulador!$C$40:$F$40,F18),I18)-INDEX(Simulador!$C$41:$F$41,F18))*(INDEX(Simulador!$C$68:$F$68,F18)+Simulador!$N$8)/Simulador!$C$7,0) -> 54983.635
B19: 45774 | C19: CIRA5234 | D19: 7.2 | E19: 5 - 10 km | F19: =MATCH(E19,{"Misma locación","0.15 - 5 km","5 - 10 km","10+ km"},0) -> 3 | G19: =MONTH(B19) -> 4 | H19: =COUNTIF($G$8:G19,G19) -> 7 | I19: 27 | J19: =INDEX(Simulador!$C$39:$F$39,F19) -> 24 | K19: =IF(I19="","",I19-J19) -> 3 | L19: =INDEX(Simulador!$C$51:$F$51,F19) -> 96184.811 | M19: =IF(H19>=Simulador!$C$19,INDEX(Simulador!$C$63:$F$63,F19),INDEX(Simulador!$C$62:$F$62,F19)) -> 67168.729 | N19: =INDEX(Simulador!$C$64:$F$64,F19) -> 135930.45 | O19: =IF(H19>=Simulador!$C$19,INDEX(Simulador!$C$65:$F$65,F19),INDEX(Simulador!$C$64:$F$64,F19)) -> 85437.226 | P19: =IF(H19>=Simulador!$C$19,INDEX(Simulador!$C$67:$F$67,F19),INDEX(Simulador!$C$66:$F$66,F19)) -> 72512.919 | Q19: =M19+(IF(I19="",J19+INDEX(Simulador!$C$40:$F$40,F19),I19)-J19-INDEX(Simulador!$C$40:$F$40,F19))*Simulador!$C$9-INDEX(Simulador!$C$69:$F$69,F19)+IF(Simulador!$N$7="Sí",MAX(0,IF(I19="",J19+INDEX(Simulador!$C$40:$F$40,F19),I19)-INDEX(Simulador!$C$41:$F$41,F19))*(INDEX(Simulador!$C$68:$F$68,F19)+Simulador!$N$8)/Simulador!$C$7,0) -> 71536.729 | R19: =N19+(IF(I19="",J19+INDEX(Simulador!$C$40:$F$40,F19),I19)-J19-INDEX(Simulador!$C$40:$F$40,F19))*Simulador!$C$9-INDEX(Simulador!$C$69:$F$69,F19)+IF(Simulador!$N$7="Sí",MAX(0,IF(I19="",J19+INDEX(Simulador!$C$40:$F$40,F19),I19)-INDEX(Simulador!$C$41:$F$41,F19))*(INDEX(Simulador!$C$68:$F$68,F19)+Simulador!$N$8)/Simulador!$C$7,0) -> 140298.45 | S19: =O19+(IF(I19="",J19+INDEX(Simulador!$C$40:$F$40,F19),I19)-J19-INDEX(Simulador!$C$40:$F$40,F19))*Simulador!$C$9-INDEX(Simulador!$C$69:$F$69,F19)+IF(Simulador!$N$7="Sí",MAX(0,IF(I19="",J19+INDEX(Simulador!$C$40:$F$40,F19),I19)-INDEX(Simulador!$C$41:$F$41,F19))*(INDEX(Simulador!$C$68:$F$68,F19)+Simulador!$N$8)/Simulador!$C$7,0) -> 89805.226 | T19: =P19+(IF(I19="",J19+INDEX(Simulador!$C$40:$F$40,F19),I19)-J19-INDEX(Simulador!$C$40:$F$40,F19))*Simulador!$C$9-INDEX(Simulador!$C$69:$F$69,F19)+IF(Simulador!$N$7="Sí",MAX(0,IF(I19="",J19+INDEX(Simulador!$C$40:$F$40,F19),I19)-INDEX(Simulador!$C$41:$F$41,F19))*(INDEX(Simulador!$C$68:$F$68,F19)+Simulador!$N$8)/Simulador!$C$7,0) -> 76880.919
B20: 45781 | C20: CIRA5139 | D20: 5.9 | E20: 5 - 10 km | F20: =MATCH(E20,{"Misma locación","0.15 - 5 km","5 - 10 km","10+ km"},0) -> 3 | G20: =MONTH(B20) -> 5 | H20: =COUNTIF($G$8:G20,G20) -> 1 | I20: 19.25 | J20: =INDEX(Simulador!$C$39:$F$39,F20) -> 24 | K20: =IF(I20="","",I20-J20) -> -4.75 | L20: =INDEX(Simulador!$C$51:$F$51,F20) -> 96184.811 | M20: =IF(H20>=Simulador!$C$19,INDEX(Simulador!$C$63:$F$63,F20),INDEX(Simulador!$C$62:$F$62,F20)) -> 99393.459 | N20: =INDEX(Simulador!$C$64:$F$64,F20) -> 135930.45 | O20: =IF(H20>=Simulador!$C$19,INDEX(Simulador!$C$65:$F$65,F20),INDEX(Simulador!$C$64:$F$64,F20)) -> 135930.45 | P20: =IF(H20>=Simulador!$C$19,INDEX(Simulador!$C$67:$F$67,F20),INDEX(Simulador!$C$66:$F$66,F20)) -> 102242.11 | Q20: =M20+(IF(I20="",J20+INDEX(Simulador!$C$40:$F$40,F20),I20)-J20-INDEX(Simulador!$C$40:$F$40,F20))*Simulador!$C$9-INDEX(Simulador!$C$69:$F$69,F20)+IF(Simulador!$N$7="Sí",MAX(0,IF(I20="",J20+INDEX(Simulador!$C$40:$F$40,F20),I20)-INDEX(Simulador!$C$41:$F$41,F20))*(INDEX(Simulador!$C$68:$F$68,F20)+Simulador!$N$8)/Simulador!$C$7,0) -> 92477.459 | R20: =N20+(IF(I20="",J20+INDEX(Simulador!$C$40:$F$40,F20),I20)-J20-INDEX(Simulador!$C$40:$F$40,F20))*Simulador!$C$9-INDEX(Simulador!$C$69:$F$69,F20)+IF(Simulador!$N$7="Sí",MAX(0,IF(I20="",J20+INDEX(Simulador!$C$40:$F$40,F20),I20)-INDEX(Simulador!$C$41:$F$41,F20))*(INDEX(Simulador!$C$68:$F$68,F20)+Simulador!$N$8)/Simulador!$C$7,0) -> 129014.45 | S20: =O20+(IF(I20="",J20+INDEX(Simulador!$C$40:$F$40,F20),I20)-J20-INDEX(Simulador!$C$40:$F$40,F20))*Simulador!$C$9-INDEX(Simulador!$C$69:$F$69,F20)+IF(Simulador!$N$7="Sí",MAX(0,IF(I20="",J20+INDEX(Simulador!$C$40:$F$40,F20),I20)-INDEX(Simulador!$C$41:$F$41,F20))*(INDEX(Simulador!$C$68:$F$68,F20)+Simulador!$N$8)/Simulador!$C$7,0) -> 129014.45 | T20: =P20+(IF(I20="",J20+INDEX(Simulador!$C$40:$F$40,F20),I20)-J20-INDEX(Simulador!$C$40:$F$40,F20))*Simulador!$C$9-INDEX(Simulador!$C$69:$F$69,F20)+IF(Simulador!$N$7="Sí",MAX(0,IF(I20="",J20+INDEX(Simulador!$C$40:$F$40,F20),I20)-INDEX(Simulador!$C$41:$F$41,F20))*(INDEX(Simulador!$C$68:$F$68,F20)+Simulador!$N$8)/Simulador!$C$7,0) -> 95326.109
B21: 45786 | C21: CIRA5038 | D21: 1.3 | E21: 0.15 - 5 km | F21: =MATCH(E21,{"Misma locación","0.15 - 5 km","5 - 10 km","10+ km"},0) -> 2 | G21: =MONTH(B21) -> 5 | H21: =COUNTIF($G$8:G21,G21) -> 2 | I21: 46 | J21: =INDEX(Simulador!$C$39:$F$39,F21) -> 18 | K21: =IF(I21="","",I21-J21) -> 28 | L21: =INDEX(Simulador!$C$51:$F$51,F21) -> 99473.811 | M21: =IF(H21>=Simulador!$C$19,INDEX(Simulador!$C$63:$F$63,F21),INDEX(Simulador!$C$62:$F$62,F21)) -> 85898.023 | N21: =INDEX(Simulador!$C$64:$F$64,F21) -> 108447.11 | O21: =IF(H21>=Simulador!$C$19,INDEX(Simulador!$C$65:$F$65,F21),INDEX(Simulador!$C$64:$F$64,F21)) -> 108447.11 | P21: =IF(H21>=Simulador!$C$19,INDEX(Simulador!$C$67:$F$67,F21),INDEX(Simulador!$C$66:$F$66,F21)) -> 82343.946 | Q21: =M21+(IF(I21="",J21+INDEX(Simulador!$C$40:$F$40,F21),I21)-J21-INDEX(Simulador!$C$40:$F$40,F21))*Simulador!$C$9-INDEX(Simulador!$C$69:$F$69,F21)+IF(Simulador!$N$7="Sí",MAX(0,IF(I21="",J21+INDEX(Simulador!$C$40:$F$40,F21),I21)-INDEX(Simulador!$C$41:$F$41,F21))*(INDEX(Simulador!$C$68:$F$68,F21)+Simulador!$N$8)/Simulador!$C$7,0) -> 156523.59 | R21: =N21+(IF(I21="",J21+INDEX(Simulador!$C$40:$F$40,F21),I21)-J21-INDEX(Simulador!$C$40:$F$40,F21))*Simulador!$C$9-INDEX(Simulador!$C$69:$F$69,F21)+IF(Simulador!$N$7="Sí",MAX(0,IF(I21="",J21+INDEX(Simulador!$C$40:$F$40,F21),I21)-INDEX(Simulador!$C$41:$F$41,F21))*(INDEX(Simulador!$C$68:$F$68,F21)+Simulador!$N$8)/Simulador!$C$7,0) -> 179072.67 | S21: =O21+(IF(I21="",J21+INDEX(Simulador!$C$40:$F$40,F21),I21)-J21-INDEX(Simulador!$C$40:$F$40,F21))*Simulador!$C$9-INDEX(Simulador!$C$69:$F$69,F21)+IF(Simulador!$N$7="Sí",MAX(0,IF(I21="",J21+INDEX(Simulador!$C$40:$F$40,F21),I21)-INDEX(Simulador!$C$41:$F$41,F21))*(INDEX(Simulador!$C$68:$F$68,F21)+Simulador!$N$8)/Simulador!$C$7,0) -> 179072.67 | T21: =P21+(IF(I21="",J21+INDEX(Simulador!$C$40:$F$40,F21),I21)-J21-INDEX(Simulador!$C$40:$F$40,F21))*Simulador!$C$9-INDEX(Simulador!$C$69:$F$69,F21)+IF(Simulador!$N$7="Sí",MAX(0,IF(I21="",J21+INDEX(Simulador!$C$40:$F$40,F21),I21)-INDEX(Simulador!$C$41:$F$41,F21))*(INDEX(Simulador!$C$68:$F$68,F21)+Simulador!$N$8)/Simulador!$C$7,0) -> 152969.51
B22: 45793 | C22: CIRA2715 | D22: 4.2 | E22: 0.15 - 5 km | F22: =MATCH(E22,{"Misma locación","0.15 - 5 km","5 - 10 km","10+ km"},0) -> 2 | G22: =MONTH(B22) -> 5 | H22: =COUNTIF($G$8:G22,G22) -> 3 | I22: 15.5 | J22: =INDEX(Simulador!$C$39:$F$39,F22) -> 18 | K22: =IF(I22="","",I22-J22) -> -2.5 | L22: =INDEX(Simulador!$C$51:$F$51,F22) -> 99473.811 | M22: =IF(H22>=Simulador!$C$19,INDEX(Simulador!$C$63:$F$63,F22),INDEX(Simulador!$C$62:$F$62,F22)) -> 85898.023 | N22: =INDEX(Simulador!$C$64:$F$64,F22) -> 108447.11 | O22: =IF(H22>=Simulador!$C$19,INDEX(Simulador!$C$65:$F$65,F22),INDEX(Simulador!$C$64:$F$64,F22)) -> 108447.11 | P22: =IF(H22>=Simulador!$C$19,INDEX(Simulador!$C$67:$F$67,F22),INDEX(Simulador!$C$66:$F$66,F22)) -> 82343.946 | Q22: =M22+(IF(I22="",J22+INDEX(Simulador!$C$40:$F$40,F22),I22)-J22-INDEX(Simulador!$C$40:$F$40,F22))*Simulador!$C$9-INDEX(Simulador!$C$69:$F$69,F22)+IF(Simulador!$N$7="Sí",MAX(0,IF(I22="",J22+INDEX(Simulador!$C$40:$F$40,F22),I22)-INDEX(Simulador!$C$41:$F$41,F22))*(INDEX(Simulador!$C$68:$F$68,F22)+Simulador!$N$8)/Simulador!$C$7,0) -> 82258.023 | R22: =N22+(IF(I22="",J22+INDEX(Simulador!$C$40:$F$40,F22),I22)-J22-INDEX(Simulador!$C$40:$F$40,F22))*Simulador!$C$9-INDEX(Simulador!$C$69:$F$69,F22)+IF(Simulador!$N$7="Sí",MAX(0,IF(I22="",J22+INDEX(Simulador!$C$40:$F$40,F22),I22)-INDEX(Simulador!$C$41:$F$41,F22))*(INDEX(Simulador!$C$68:$F$68,F22)+Simulador!$N$8)/Simulador!$C$7,0) -> 104807.11 | S22: =O22+(IF(I22="",J22+INDEX(Simulador!$C$40:$F$40,F22),I22)-J22-INDEX(Simulador!$C$40:$F$40,F22))*Simulador!$C$9-INDEX(Simulador!$C$69:$F$69,F22)+IF(Simulador!$N$7="Sí",MAX(0,IF(I22="",J22+INDEX(Simulador!$C$40:$F$40,F22),I22)-INDEX(Simulador!$C$41:$F$41,F22))*(INDEX(Simulador!$C$68:$F$68,F22)+Simulador!$N$8)/Simulador!$C$7,0) -> 104807.11 | T22: =P22+(IF(I22="",J22+INDEX(Simulador!$C$40:$F$40,F22),I22)-J22-INDEX(Simulador!$C$40:$F$40,F22))*Simulador!$C$9-INDEX(Simulador!$C$69:$F$69,F22)+IF(Simulador!$N$7="Sí",MAX(0,IF(I22="",J22+INDEX(Simulador!$C$40:$F$40,F22),I22)-INDEX(Simulador!$C$41:$F$41,F22))*(INDEX(Simulador!$C$68:$F$68,F22)+Simulador!$N$8)/Simulador!$C$7,0) -> 78703.946
B23: 45799 | C23: CIRA3921 | D23: 5.7 | E23: 5 - 10 km | F23: =MATCH(E23,{"Misma locación","0.15 - 5 km","5 - 10 km","10+ km"},0) -> 3 | G23: =MONTH(B23) -> 5 | H23: =COUNTIF($G$8:G23,G23) -> 4 | I23: 23.25 | J23: =INDEX(Simulador!$C$39:$F$39,F23) -> 24 | K23: =IF(I23="","",I23-J23) -> -0.75 | L23: =INDEX(Simulador!$C$51:$F$51,F23) -> 96184.811 | M23: =IF(H23>=Simulador!$C$19,INDEX(Simulador!$C$63:$F$63,F23),INDEX(Simulador!$C$62:$F$62,F23)) -> 99393.459 | N23: =INDEX(Simulador!$C$64:$F$64,F23) -> 135930.45 | O23: =IF(H23>=Simulador!$C$19,INDEX(Simulador!$C$65:$F$65,F23),INDEX(Simulador!$C$64:$F$64,F23)) -> 135930.45 | P23: =IF(H23>=Simulador!$C$19,INDEX(Simulador!$C$67:$F$67,F23),INDEX(Simulador!$C$66:$F$66,F23)) -> 102242.11 | Q23: =M23+(IF(I23="",J23+INDEX(Simulador!$C$40:$F$40,F23),I23)-J23-INDEX(Simulador!$C$40:$F$40,F23))*Simulador!$C$9-INDEX(Simulador!$C$69:$F$69,F23)+IF(Simulador!$N$7="Sí",MAX(0,IF(I23="",J23+INDEX(Simulador!$C$40:$F$40,F23),I23)-INDEX(Simulador!$C$41:$F$41,F23))*(INDEX(Simulador!$C$68:$F$68,F23)+Simulador!$N$8)/Simulador!$C$7,0) -> 98301.459 | R23: =N23+(IF(I23="",J23+INDEX(Simulador!$C$40:$F$40,F23),I23)-J23-INDEX(Simulador!$C$40:$F$40,F23))*Simulador!$C$9-INDEX(Simulador!$C$69:$F$69,F23)+IF(Simulador!$N$7="Sí",MAX(0,IF(I23="",J23+INDEX(Simulador!$C$40:$F$40,F23),I23)-INDEX(Simulador!$C$41:$F$41,F23))*(INDEX(Simulador!$C$68:$F$68,F23)+Simulador!$N$8)/Simulador!$C$7,0) -> 134838.45 | S23: =O23+(IF(I23="",J23+INDEX(Simulador!$C$40:$F$40,F23),I23)-J23-INDEX(Simulador!$C$40:$F$40,F23))*Simulador!$C$9-INDEX(Simulador!$C$69:$F$69,F23)+IF(Simulador!$N$7="Sí",MAX(0,IF(I23="",J23+INDEX(Simulador!$C$40:$F$40,F23),I23)-INDEX(Simulador!$C$41:$F$41,F23))*(INDEX(Simulador!$C$68:$F$68,F23)+Simulador!$N$8)/Simulador!$C$7,0) -> 134838.45 | T23: =P23+(IF(I23="",J23+INDEX(Simulador!$C$40:$F$40,F23),I23)-J23-INDEX(Simulador!$C$40:$F$40,F23))*Simulador!$C$9-INDEX(Simulador!$C$69:$F$69,F23)+IF(Simulador!$N$7="Sí",MAX(0,IF(I23="",J23+INDEX(Simulador!$C$40:$F$40,F23),I23)-INDEX(Simulador!$C$41:$F$41,F23))*(INDEX(Simulador!$C$68:$F$68,F23)+Simulador!$N$8)/Simulador!$C$7,0) -> 101150.11
B24: 45807 | C24: CIRA 5844 | D24: 4.4 | E24: 0.15 - 5 km | F24: =MATCH(E24,{"Misma locación","0.15 - 5 km","5 - 10 km","10+ km"},0) -> 2 | G24: =MONTH(B24) -> 5 | H24: =COUNTIF($G$8:G24,G24) -> 5 | I24: 19.5 | J24: =INDEX(Simulador!$C$39:$F$39,F24) -> 18 | K24: =IF(I24="","",I24-J24) -> 1.5 | L24: =INDEX(Simulador!$C$51:$F$51,F24) -> 99473.811 | M24: =IF(H24>=Simulador!$C$19,INDEX(Simulador!$C$63:$F$63,F24),INDEX(Simulador!$C$62:$F$62,F24)) -> 85898.023 | N24: =INDEX(Simulador!$C$64:$F$64,F24) -> 108447.11 | O24: =IF(H24>=Simulador!$C$19,INDEX(Simulador!$C$65:$F$65,F24),INDEX(Simulador!$C$64:$F$64,F24)) -> 108447.11 | P24: =IF(H24>=Simulador!$C$19,INDEX(Simulador!$C$67:$F$67,F24),INDEX(Simulador!$C$66:$F$66,F24)) -> 82343.946 | Q24: =M24+(IF(I24="",J24+INDEX(Simulador!$C$40:$F$40,F24),I24)-J24-INDEX(Simulador!$C$40:$F$40,F24))*Simulador!$C$9-INDEX(Simulador!$C$69:$F$69,F24)+IF(Simulador!$N$7="Sí",MAX(0,IF(I24="",J24+INDEX(Simulador!$C$40:$F$40,F24),I24)-INDEX(Simulador!$C$41:$F$41,F24))*(INDEX(Simulador!$C$68:$F$68,F24)+Simulador!$N$8)/Simulador!$C$7,0) -> 88082.023 | R24: =N24+(IF(I24="",J24+INDEX(Simulador!$C$40:$F$40,F24),I24)-J24-INDEX(Simulador!$C$40:$F$40,F24))*Simulador!$C$9-INDEX(Simulador!$C$69:$F$69,F24)+IF(Simulador!$N$7="Sí",MAX(0,IF(I24="",J24+INDEX(Simulador!$C$40:$F$40,F24),I24)-INDEX(Simulador!$C$41:$F$41,F24))*(INDEX(Simulador!$C$68:$F$68,F24)+Simulador!$N$8)/Simulador!$C$7,0) -> 110631.11 | S24: =O24+(IF(I24="",J24+INDEX(Simulador!$C$40:$F$40,F24),I24)-J24-INDEX(Simulador!$C$40:$F$40,F24))*Simulador!$C$9-INDEX(Simulador!$C$69:$F$69,F24)+IF(Simulador!$N$7="Sí",MAX(0,IF(I24="",J24+INDEX(Simulador!$C$40:$F$40,F24),I24)-INDEX(Simulador!$C$41:$F$41,F24))*(INDEX(Simulador!$C$68:$F$68,F24)+Simulador!$N$8)/Simulador!$C$7,0) -> 110631.11 | T24: =P24+(IF(I24="",J24+INDEX(Simulador!$C$40:$F$40,F24),I24)-J24-INDEX(Simulador!$C$40:$F$40,F24))*Simulador!$C$9-INDEX(Simulador!$C$69:$F$69,F24)+IF(Simulador!$N$7="Sí",MAX(0,IF(I24="",J24+INDEX(Simulador!$C$40:$F$40,F24),I24)-INDEX(Simulador!$C$41:$F$41,F24))*(INDEX(Simulador!$C$68:$F$68,F24)+Simulador!$N$8)/Simulador!$C$7,0) -> 84527.946
B25: 45812 | C25: CIRA 5665 | D25: 0.0064007998 | E25: Misma locación | F25: =MATCH(E25,{"Misma locación","0.15 - 5 km","5 - 10 km","10+ km"},0) -> 1 | G25: =MONTH(B25) -> 6 | H25: =COUNTIF($G$8:G25,G25) -> 1 | I25: 15.75 | J25: =INDEX(Simulador!$C$39:$F$39,F25) -> 12 | K25: =IF(I25="","",I25-J25) -> 3.75 | L25: =INDEX(Simulador!$C$51:$F$51,F25) -> 76047.405 | M25: =IF(H25>=Simulador!$C$19,INDEX(Simulador!$C$63:$F$63,F25),INDEX(Simulador!$C$62:$F$62,F25)) -> 55414.011 | N25: =INDEX(Simulador!$C$64:$F$64,F25) -> 65678.455 | O25: =IF(H25>=Simulador!$C$19,INDEX(Simulador!$C$65:$F$65,F25),INDEX(Simulador!$C$64:$F$64,F25)) -> 65678.455 | P25: =IF(H25>=Simulador!$C$19,INDEX(Simulador!$C$67:$F$67,F25),INDEX(Simulador!$C$66:$F$66,F25)) -> 55372.811 | Q25: =M25+(IF(I25="",J25+INDEX(Simulador!$C$40:$F$40,F25),I25)-J25-INDEX(Simulador!$C$40:$F$40,F25))*Simulador!$C$9-INDEX(Simulador!$C$69:$F$69,F25)+IF(Simulador!$N$7="Sí",MAX(0,IF(I25="",J25+INDEX(Simulador!$C$40:$F$40,F25),I25)-INDEX(Simulador!$C$41:$F$41,F25))*(INDEX(Simulador!$C$68:$F$68,F25)+Simulador!$N$8)/Simulador!$C$7,0) -> 65963.369 | R25: =N25+(IF(I25="",J25+INDEX(Simulador!$C$40:$F$40,F25),I25)-J25-INDEX(Simulador!$C$40:$F$40,F25))*Simulador!$C$9-INDEX(Simulador!$C$69:$F$69,F25)+IF(Simulador!$N$7="Sí",MAX(0,IF(I25="",J25+INDEX(Simulador!$C$40:$F$40,F25),I25)-INDEX(Simulador!$C$41:$F$41,F25))*(INDEX(Simulador!$C$68:$F$68,F25)+Simulador!$N$8)/Simulador!$C$7,0) -> 76227.814 | S25: =O25+(IF(I25="",J25+INDEX(Simulador!$C$40:$F$40,F25),I25)-J25-INDEX(Simulador!$C$40:$F$40,F25))*Simulador!$C$9-INDEX(Simulador!$C$69:$F$69,F25)+IF(Simulador!$N$7="Sí",MAX(0,IF(I25="",J25+INDEX(Simulador!$C$40:$F$40,F25),I25)-INDEX(Simulador!$C$41:$F$41,F25))*(INDEX(Simulador!$C$68:$F$68,F25)+Simulador!$N$8)/Simulador!$C$7,0) -> 76227.814 | T25: =P25+(IF(I25="",J25+INDEX(Simulador!$C$40:$F$40,F25),I25)-J25-INDEX(Simulador!$C$40:$F$40,F25))*Simulador!$C$9-INDEX(Simulador!$C$69:$F$69,F25)+IF(Simulador!$N$7="Sí",MAX(0,IF(I25="",J25+INDEX(Simulador!$C$40:$F$40,F25),I25)-INDEX(Simulador!$C$41:$F$41,F25))*(INDEX(Simulador!$C$68:$F$68,F25)+Simulador!$N$8)/Simulador!$C$7,0) -> 65922.169
... B52: 45943 | C52: INFA 3340 | D52: 14.6 | E52: 10+ km | F52: =MATCH(E52,{"Misma locación","0.15 - 5 km","5 - 10 km","10+ km"},0) -> 4 | G52: =MONTH(B52) -> 10 | H52: =COUNTIF($G$8:G52,G52) -> 3 | I52: 34 | J52: =INDEX(Simulador!$C$39:$F$39,F52) -> 28 | K52: =IF(I52="","",I52-J52) -> 6 | L52: =INDEX(Simulador!$C$51:$F$51,F52) -> 110984.81 | M52: =IF(H52>=Simulador!$C$19,INDEX(Simulador!$C$63:$F$63,F52),INDEX(Simulador!$C$62:$F$62,F52)) -> 107379.62 | N52: =INDEX(Simulador!$C$64:$F$64,F52) -> 152876.36 | O52: =IF(H52>=Simulador!$C$19,INDEX(Simulador!$C$65:$F$65,F52),INDEX(Simulador!$C$64:$F$64,F52)) -> 152876.36 | P52: =IF(H52>=Simulador!$C$19,INDEX(Simulador!$C$67:$F$67,F52),INDEX(Simulador!$C$66:$F$66,F52)) -> 109162.6 | Q52: =M52+(IF(I52="",J52+INDEX(Simulador!$C$40:$F$40,F52),I52)-J52-INDEX(Simulador!$C$40:$F$40,F52))*Simulador!$C$9-INDEX(Simulador!$C$69:$F$69,F52)+IF(Simulador!$N$7="Sí",MAX(0,IF(I52="",J52+INDEX(Simulador!$C$40:$F$40,F52),I52)-INDEX(Simulador!$C$41:$F$41,F52))*(INDEX(Simulador!$C$68:$F$68,F52)+Simulador!$N$8)/Simulador!$C$7,0) -> 116115.62 | R52: =N52+(IF(I52="",J52+INDEX(Simulador!$C$40:$F$40,F52),I52)-J52-INDEX(Simulador!$C$40:$F$40,F52))*Simulador!$C$9-INDEX(Simulador!$C$69:$F$69,F52)+IF(Simulador!$N$7="Sí",MAX(0,IF(I52="",J52+INDEX(Simulador!$C$40:$F$40,F52),I52)-INDEX(Simulador!$C$41:$F$41,F52))*(INDEX(Simulador!$C$68:$F$68,F52)+Simulador!$N$8)/Simulador!$C$7,0) -> 161612.36 | S52: =O52+(IF(I52="",J52+INDEX(Simulador!$C$40:$F$40,F52),I52)-J52-INDEX(Simulador!$C$40:$F$40,F52))*Simulador!$C$9-INDEX(Simulador!$C$69:$F$69,F52)+IF(Simulador!$N$7="Sí",MAX(0,IF(I52="",J52+INDEX(Simulador!$C$40:$F$40,F52),I52)-INDEX(Simulador!$C$41:$F$41,F52))*(INDEX(Simulador!$C$68:$F$68,F52)+Simulador!$N$8)/Simulador!$C$7,0) -> 161612.36 | T52: =P52+(IF(I52="",J52+INDEX(Simulador!$C$40:$F$40,F52),I52)-J52-INDEX(Simulador!$C$40:$F$40,F52))*Simulador!$C$9-INDEX(Simulador!$C$69:$F$69,F52)+IF(Simulador!$N$7="Sí",MAX(0,IF(I52="",J52+INDEX(Simulador!$C$40:$F$40,F52),I52)-INDEX(Simulador!$C$41:$F$41,F52))*(INDEX(Simulador!$C$68:$F$68,F52)+Simulador!$N$8)/Simulador!$C$7,0) -> 117898.6
B54: Totales por movimiento (sin cargo fijo) | L54: =SUM(L8:L52) -> 4266318 | M54: =SUM(M8:M52) -> 3617645.4 | N54: =SUM(N8:N52) -> 4995502.8 | O54: =SUM(O8:O52) -> 4698643 | P54: =SUM(P8:P52) -> 3651013.2 | Q54: =SUM(Q8:Q52) -> 3849322.7 | R54: =SUM(R8:R52) -> 5227180.1 | S54: =SUM(S8:S52) -> 4930320.2 | T54: =SUM(T8:T52) -> 3882690.5
B57: Meses con movilizaciones
B58: Mes | C58: Movilizaciones | D58: Misma localización | E58: 0,1–5 km | F58: 5–10 km | G58: Más de 10 km | H58: Cargo fijo Petro Star (USD) | I58: Cargo fijo Ecotransur (USD) | J58: Truck Manager mensual (USD) | K58: Mes | L58: Work Order (USD) | M58: Petro Star tarifa normal, horas reales (USD) | N58: Ecotransur, horas reales (USD) | O58: Petro Star Lump Sum, horas reales (USD) | P58: Ahorro Petro Star tarifa normal (USD) | Q58: Ahorro Ecotransur (USD) | R58: Ahorro Petro Star Lump Sum (USD)
B59: 2 | C59: =COUNTIF($G$8:$G$52,B59) -> 1 | D59: =COUNTIFS($G$8:$G$52,B59,$F$8:$F$52,1) -> 0 | E59: =COUNTIFS($G$8:$G$52,B59,$F$8:$F$52,2) -> 0 | F59: =COUNTIFS($G$8:$G$52,B59,$F$8:$F$52,3) -> 0 | G59: =COUNTIFS($G$8:$G$52,B59,$F$8:$F$52,4) -> 1 | H59: =IF(C59=0,0,INDEX(Simulador!$E$72:$E$78,MIN(C59,6)+1)) -> 133751.22 | I59: =IF(C59=0,0,INDEX(Simulador!$F$72:$F$78,MIN(C59,6)+1)) -> 181054.02 | J59: =IF(AND(C59>0,Simulador!$C$16="Mensual fijo"),Simulador!$C$14/Simulador!$C$7,0) -> 16216.216 | K59: Feb | L59: =SUMIF($G$8:$G$52,B59,$L$8:$L$52) -> 110984.81 | M59: =SUMIF($G$8:$G$52,B59,$Q$8:$Q$52)+H59+J59 -> 336510.95 | N59: =SUMIF($G$8:$G$52,B59,$T$8:$T$52)+I59+J59 -> 385596.72 | O59: =SUMIF($G$8:$G$52,B59,$R$8:$R$52)+H59+J59 -> 382007.69 | P59: =L59-M59 -> -225526.14 | Q59: =L59-N59 -> -274611.91 | R59: =L59-O59 -> -271022.88
B60: 3 | C60: =COUNTIF($G$8:$G$52,B60) -> 4 | D60: =COUNTIFS($G$8:$G$52,B60,$F$8:$F$52,1) -> 1 | E60: =COUNTIFS($G$8:$G$52,B60,$F$8:$F$52,2) -> 2 | F60: =COUNTIFS($G$8:$G$52,B60,$F$8:$F$52,3) -> 0 | G60: =COUNTIFS($G$8:$G$52,B60,$F$8:$F$52,4) -> 1 | H60: =IF(C60=0,0,INDEX(Simulador!$E$72:$E$78,MIN(C60,6)+1)) -> 56465.288 | I60: =IF(C60=0,0,INDEX(Simulador!$F$72:$F$78,MIN(C60,6)+1)) -> 45263.505 | J60: =IF(AND(C60>0,Simulador!$C$16="Mensual fijo"),Simulador!$C$14/Simulador!$C$7,0) -> 16216.216 | K60: Mar | L60: =SUMIF($G$8:$G$52,B60,$L$8:$L$52) -> 385979.84 | M60: =SUMIF($G$8:$G$52,B60,$Q$8:$Q$52)+H60+J60 -> 448464.03 | N60: =SUMIF($G$8:$G$52,B60,$T$8:$T$52)+I60+J60 -> 431895.86 | O60: =SUMIF($G$8:$G$52,B60,$R$8:$R$52)+H60+J60 -> 549323.37 | P60: =L60-M60 -> -62484.189 | Q60: =L60-N60 -> -45916.027 | R60: =L60-O60 -> -163343.54
B61: 4 | C61: =COUNTIF($G$8:$G$52,B61) -> 7 | D61: =COUNTIFS($G$8:$G$52,B61,$F$8:$F$52,1) -> 3 | E61: =COUNTIFS($G$8:$G$52,B61,$F$8:$F$52,2) -> 2 | F61: =COUNTIFS($G$8:$G$52,B61,$F$8:$F$52,3) -> 2 | G61: =COUNTIFS($G$8:$G$52,B61,$F$8:$F$52,4) -> 0 | H61: =IF(C61=0,0,INDEX(Simulador!$E$72:$E$78,MIN(C61,6)+1)) -> 0 | I61: =IF(C61=0,0,INDEX(Simulador!$F$72:$F$78,MIN(C61,6)+1)) -> 0 | J61: =IF(AND(C61>0,Simulador!$C$16="Mensual fijo"),Simulador!$C$14/Simulador!$C$7,0) -> 16216.216 | K61: Abr | L61: =SUMIF($G$8:$G$52,B61,$L$8:$L$52) -> 619459.46 | M61: =SUMIF($G$8:$G$52,B61,$Q$8:$Q$52)+H61+J61 -> 511031.03 | N61: =SUMIF($G$8:$G$52,B61,$T$8:$T$52)+I61+J61 -> 526354.21 | O61: =SUMIF($G$8:$G$52,B61,$R$8:$R$52)+H61+J61 -> 711192.25 | P61: =L61-M61 -> 108428.43 | Q61: =L61-N61 -> 93105.254 | R61: =L61-O61 -> -91732.793
B62: 5 | C62: =COUNTIF($G$8:$G$52,B62) -> 5 | D62: =COUNTIFS($G$8:$G$52,B62,$F$8:$F$52,1) -> 0 | E62: =COUNTIFS($G$8:$G$52,B62,$F$8:$F$52,2) -> 3 | F62: =COUNTIFS($G$8:$G$52,B62,$F$8:$F$52,3) -> 2 | G62: =COUNTIFS($G$8:$G$52,B62,$F$8:$F$52,4) -> 0 | H62: =IF(C62=0,0,INDEX(Simulador!$E$72:$E$78,MIN(C62,6)+1)) -> 40952.538 | I62: =IF(C62=0,0,INDEX(Simulador!$F$72:$F$78,MIN(C62,6)+1)) -> 0 | J62: =IF(AND(C62>0,Simulador!$C$16="Mensual fijo"),Simulador!$C$14/Simulador!$C$7,0) -> 16216.216 | K62: May | L62: =SUMIF($G$8:$G$52,B62,$L$8:$L$52) -> 490791.05 | M62: =SUMIF($G$8:$G$52,B62,$Q$8:$Q$52)+H62+J62 -> 574811.31 | N62: =SUMIF($G$8:$G$52,B62,$T$8:$T$52)+I62+J62 -> 528893.84 | O62: =SUMIF($G$8:$G$52,B62,$R$8:$R$52)+H62+J62 -> 715532.54 | P62: =L62-M62 -> -84020.254 | Q62: =L62-N62 -> -38102.786 | R62: =L62-O62 -> -224741.49
B63: 6 | C63: =COUNTIF($G$8:$G$52,B63) -> 6 | D63: =COUNTIFS($G$8:$G$52,B63,$F$8:$F$52,1) -> 1 | E63: =COUNTIFS($G$8:$G$52,B63,$F$8:$F$52,2) -> 3 | F63: =COUNTIFS($G$8:$G$52,B63,$F$8:$F$52,3) -> 1 | G63: =COUNTIFS($G$8:$G$52,B63,$F$8:$F$52,4) -> 1 | H63: =IF(C63=0,0,INDEX(Simulador!$E$72:$E$78,MIN(C63,6)+1)) -> 0 | I63: =IF(C63=0,0,INDEX(Simulador!$F$72:$F$78,MIN(C63,6)+1)) -> 0 | J63: =IF(AND(C63>0,Simulador!$C$16="Mensual fijo"),Simulador!$C$14/Simulador!$C$7,0) -> 16216.216 | K63: Jun | L63: =SUMIF($G$8:$G$52,B63,$L$8:$L$52) -> 581638.46 | M63: =SUMIF($G$8:$G$52,B63,$Q$8:$Q$52)+H63+J63 -> 487132.92 | N63: =SUMIF($G$8:$G$52,B63,$T$8:$T$52)+I63+J63 -> 491122.33 | O63: =SUMIF($G$8:$G$52,B63,$R$8:$R$52)+H63+J63 -> 680384.16 | P63: =L63-M63 -> 94505.536 | Q63: =L63-N63 -> 90516.126 | R63: =L63-O63 -> -98745.698
B64: 7 | C64: =COUNTIF($G$8:$G$52,B64) -> 7 | D64: =COUNTIFS($G$8:$G$52,B64,$F$8:$F$52,1) -> 0 | E64: =COUNTIFS($G$8:$G$52,B64,$F$8:$F$52,2) -> 3 | F64: =COUNTIFS($G$8:$G$52,B64,$F$8:$F$52,3) -> 3 | G64: =COUNTIFS($G$8:$G$52,B64,$F$8:$F$52,4) -> 1 | H64: =IF(C64=0,0,INDEX(Simulador!$E$72:$E$78,MIN(C64,6)+1)) -> 0 | I64: =IF(C64=0,0,INDEX(Simulador!$F$72:$F$78,MIN(C64,6)+1)) -> 0 | J64: =IF(AND(C64>0,Simulador!$C$16="Mensual fijo"),Simulador!$C$14/Simulador!$C$7,0) -> 16216.216 | K64: Jul | L64: =SUMIF($G$8:$G$52,B64,$L$8:$L$52) -> 697960.68 | M64: =SUMIF($G$8:$G$52,B64,$Q$8:$Q$52)+H64+J64 -> 606480.54 | N64: =SUMIF($G$8:$G$52,B64,$T$8:$T$52)+I64+J64 -> 615643.73 | O64: =SUMIF($G$8:$G$52,B64,$R$8:$R$52)+H64+J64 -> 891305.25 | P64: =L64-M64 -> 91480.134 | Q64: =L64-N64 -> 82316.943 | R64: =L64-O64 -> -193344.57
B65: 8 | C65: =COUNTIF($G$8:$G$52,B65) -> 7 | D65: =COUNTIFS($G$8:$G$52,B65,$F$8:$F$52,1) -> 4 | E65: =COUNTIFS($G$8:$G$52,B65,$F$8:$F$52,2) -> 1 | F65: =COUNTIFS($G$8:$G$52,B65,$F$8:$F$52,3) -> 1 | G65: =COUNTIFS($G$8:$G$52,B65,$F$8:$F$52,4) -> 1 | H65: =IF(C65=0,0,INDEX(Simulador!$E$72:$E$78,MIN(C65,6)+1)) -> 0 | I65: =IF(C65=0,0,INDEX(Simulador!$F$72:$F$78,MIN(C65,6)+1)) -> 0 | J65: =IF(AND(C65>0,Simulador!$C$16="Mensual fijo"),Simulador!$C$14/Simulador!$C$7,0) -> 16216.216 | K65: Ago | L65: =SUMIF($G$8:$G$52,B65,$L$8:$L$52) -> 610833.05 | M65: =SUMIF($G$8:$G$52,B65,$Q$8:$Q$52)+H65+J65 -> 532038.36 | N65: =SUMIF($G$8:$G$52,B65,$T$8:$T$52)+I65+J65 -> 549808.73 | O65: =SUMIF($G$8:$G$52,B65,$R$8:$R$52)+H65+J65 -> 728874.68 | P65: =L65-M65 -> 78794.696 | Q65: =L65-N65 -> 61024.322 | R65: =L65-O65 -> -118041.63
B66: 9 | C66: =COUNTIF($G$8:$G$52,B66) -> 5 | D66: =COUNTIFS($G$8:$G$52,B66,$F$8:$F$52,1) -> 2 | E66: =COUNTIFS($G$8:$G$52,B66,$F$8:$F$52,2) -> 1 | F66: =COUNTIFS($G$8:$G$52,B66,$F$8:$F$52,3) -> 1 | G66: =COUNTIFS($G$8:$G$52,B66,$F$8:$F$52,4) -> 1 | H66: =IF(C66=0,0,INDEX(Simulador!$E$72:$E$78,MIN(C66,6)+1)) -> 40952.538 | I66: =IF(C66=0,0,INDEX(Simulador!$F$72:$F$78,MIN(C66,6)+1)) -> 0 | J66: =IF(AND(C66>0,Simulador!$C$16="Mensual fijo"),Simulador!$C$14/Simulador!$C$7,0) -> 16216.216 | K66: Sep | L66: =SUMIF($G$8:$G$52,B66,$L$8:$L$52) -> 458738.24 | M66: =SUMIF($G$8:$G$52,B66,$Q$8:$Q$52)+H66+J66 -> 462789.18 | N66: =SUMIF($G$8:$G$52,B66,$T$8:$T$52)+I66+J66 -> 422831.79 | O66: =SUMIF($G$8:$G$52,B66,$R$8:$R$52)+H66+J66 -> 587900.88 | P66: =L66-M66 -> -4050.9332 | Q66: =L66-N66 -> 35906.457 | R66: =L66-O66 -> -129162.64
B67: 10 | C67: =COUNTIF($G$8:$G$52,B67) -> 3 | D67: =COUNTIFS($G$8:$G$52,B67,$F$8:$F$52,1) -> 0 | E67: =COUNTIFS($G$8:$G$52,B67,$F$8:$F$52,2) -> 2 | F67: =COUNTIFS($G$8:$G$52,B67,$F$8:$F$52,3) -> 0 | G67: =COUNTIFS($G$8:$G$52,B67,$F$8:$F$52,4) -> 1 | H67: =IF(C67=0,0,INDEX(Simulador!$E$72:$E$78,MIN(C67,6)+1)) -> 69757.611 | I67: =IF(C67=0,0,INDEX(Simulador!$F$72:$F$78,MIN(C67,6)+1)) -> 90527.009 | J67: =IF(AND(C67>0,Simulador!$C$16="Mensual fijo"),Simulador!$C$14/Simulador!$C$7,0) -> 16216.216 | K67: Oct | L67: =SUMIF($G$8:$G$52,B67,$L$8:$L$52) -> 309932.43 | M67: =SUMIF($G$8:$G$52,B67,$Q$8:$Q$52)+H67+J67 -> 377889.49 | N67: =SUMIF($G$8:$G$52,B67,$T$8:$T$52)+I67+J67 -> 393333.71 | O67: =SUMIF($G$8:$G$52,B67,$R$8:$R$52)+H67+J67 -> 468484.4 | P67: =L67-M67 -> -67957.062 | Q67: =L67-N67 -> -83401.281 | R67: =L67-O67 -> -158551.96
B68: Total | C68: =SUM(C59:C67) -> 45 | D68: =SUM(D59:D67) -> 11 | E68: =SUM(E59:E67) -> 17 | F68: =SUM(F59:F67) -> 10 | G68: =SUM(G59:G67) -> 7 | H68: =SUM(H59:H67) -> 341879.2 | I68: =SUM(I59:I67) -> 316844.53 | J68: =SUM(J59:J67) -> 145945.95 | L68: =SUM(L59:L67) -> 4266318 | M68: =SUM(M59:M67) -> 4337147.8 | N68: =SUM(N59:N67) -> 4345480.9 | O68: =SUM(O59:O67) -> 5715005.2 | P68: =SUM(P59:P67) -> -70829.783 | Q68: =SUM(Q59:Q67) -> -79162.904 | R68: =SUM(R59:R67) -> -1448687.2

Sheet Reconciliación
B1: Reconciliación: de dónde sale cada parámetro
B2: Valor en simulador = enlace vivo (verde). Valor en fuente = copiado del archivo original. Control = OK si coinciden; el control solo es válido con los valores por defecto del simulador.
B4: Parámetro | C4: Valor en simulador | D4: Valor en fuente | E4: Control | F4: Fuente (archivo · celda o página) | G4: Clase
B5: TRM (COP/USD) | C5: =Simulador!C7 -> 3700 | D5: 3700 | E5: =IF(ABS(C5-D5)<0.005,"OK","DIFERENCIA") -> OK | F5: Tarifas.xlsx · E3 | G5: Medido
B6: Taladro (USD/día) | C6: =Simulador!C8 -> 34944 | D6: 34944 | E6: =IF(ABS(C6-D6)<0.005,"OK","DIFERENCIA") -> OK | F6: Tarifas.xlsx · E5 | G6: Medido
B7: Taladro (USD/h) | C7: =Simulador!C9 -> 1456 | D7: 1456 | E7: =IF(ABS(C7-D7)<0.005,"OK","DIFERENCIA") -> OK | F7: Tarifas.xlsx · E6 | G7: Medido
B8: Adicionales base (%) | C8: =Simulador!C11 -> 0 | D8: 0 | E8: =IF(ABS(C8-D8)<0.005,"OK","DIFERENCIA") -> OK | F8: Tarifas.xlsx · E7 | G8: Premisa
B9: Adicionales Lump Sum (%) | C9: =Simulador!C12 -> 0 | D9: 0 | E9: =IF(ABS(C9-D9)<0.005,"OK","DIFERENCIA") -> OK | F9: Tarifas.xlsx · E8 | G9: Premisa
B10: Truck Manager prorrateado a 6 movs (USD) = 60 M COP / TRM / 6 | C10: =Simulador!C14/Simulador!C7/Simulador!C15 -> 2702.7027 | D10: 2702.7027 | E10: =IF(ABS(C10-D10)<0.005,"OK","DIFERENCIA") -> OK | F10: Tarifas.xlsx · C29 | G10: Medido
B11: Horas rango 1 | C11: =Simulador!C39 -> 12 | D11: 12 | E11: =IF(ABS(C11-D11)<0.005,"OK","DIFERENCIA") -> OK | F11: Tarifas.xlsx · C26 | G11: Dato Excel
B12: Horas rango 2 | C12: =Simulador!D39 -> 18 | D12: 18 | E12: =IF(ABS(C12-D12)<0.005,"OK","DIFERENCIA") -> OK | F12: Tarifas.xlsx · C52 | G12: Dato Excel
B13: Horas rango 3 | C13: =Simulador!E39 -> 24 | D13: 24 | E13: =IF(ABS(C13-D13)<0.005,"OK","DIFERENCIA") -> OK | F13: Tarifas.xlsx · C78 | G13: Dato Excel
B14: Horas rango 4 | C14: =Simulador!F39 -> 28 | D14: 28 | E14: =IF(ABS(C14-D14)<0.005,"OK","DIFERENCIA") -> OK | F14: Tarifas.xlsx · C104 | G14: Dato Excel
B15: WO base rango 1 (USD) | C15: =Simulador!C43 -> 75642 | D15: 75642 | E15: =IF(ABS(C15-D15)<0.005,"OK","DIFERENCIA") -> OK | F15: Tarifas.xlsx · K4 (dato SierraCol) | G15: Premisa
B16: WO base rango 2 (USD) | C16: =Simulador!D43 -> 98663 | D16: 98663 | E16: =IF(ABS(C16-D16)<0.005,"OK","DIFERENCIA") -> OK | F16: Tarifas.xlsx · K5 (dato SierraCol) | G16: Premisa
B17: WO base rango 3 (USD) | C17: =Simulador!E43 -> 95374 | D17: 95374 | E17: =IF(ABS(C17-D17)<0.005,"OK","DIFERENCIA") -> OK | F17: Tarifas.xlsx · K6 (dato SierraCol) | G17: Premisa
B18: WO base rango 4 (USD) | C18: =Simulador!F43 -> 110174 | D18: 110174 | E18: =IF(ABS(C18-D18)<0.005,"OK","DIFERENCIA") -> OK | F18: Tarifas.xlsx · K7 (dato SierraCol) | G18: Premisa
B19: Petro Star normal rango 1 (COP) | C19: =Simulador!C44 -> 140385441 | D19: 140385441 | E19: =IF(ABS(C19-D19)<0.005,"OK","DIFERENCIA") -> OK | F19: Tarifas.xlsx · E25 | G19: Medido
B20: Lump Sum rango 1 (COP) | C20: =Simulador!C45 -> 178363885 | D20: 178363885 | E20: =IF(ABS(C20-D20)<0.005,"OK","DIFERENCIA") -> OK | F20: Tarifas.xlsx · F25 (≠ Cot. 1255 p.1–2) | G20: Medido
B21: Ecotransur rango 1 (COP) | C21: =Simulador!C46 -> 140233002 | D21: 140233002 | E21: =IF(ABS(C21-D21)<0.005,"OK","DIFERENCIA") -> OK | F21: Tarifas.xlsx · G25 | G21: Medido
B22: Petro Star normal rango 2 (COP) | C22: =Simulador!D44 -> 220853084 | D22: 220853084 | E22: =IF(ABS(C22-D22)<0.005,"OK","DIFERENCIA") -> OK | F22: Tarifas.xlsx · E51 | G22: Medido
B23: Lump Sum rango 2 (COP) | C23: =Simulador!D45 -> 304284690 | D23: 304284690 | E23: =IF(ABS(C23-D23)<0.005,"OK","DIFERENCIA") -> OK | F23: Tarifas.xlsx · F51 (≠ Cot. 1255 p.1–2) | G23: Medido
B24: Ecotransur rango 2 (COP) | C24: =Simulador!D46 -> 207703002 | D24: 207703002 | E24: =IF(ABS(C24-D24)<0.005,"OK","DIFERENCIA") -> OK | F24: Tarifas.xlsx · G51 | G24: Medido
B25: Petro Star normal rango 3 (COP) | C25: =Simulador!E44 -> 238462998 | D25: 238462998 | E25: =IF(ABS(C25-D25)<0.005,"OK","DIFERENCIA") -> OK | F25: Tarifas.xlsx · E77 | G25: Medido
B26: Lump Sum rango 3 (COP) | C26: =Simulador!E45 -> 373649874 | D26: 373649874 | E26: =IF(ABS(C26-D26)<0.005,"OK","DIFERENCIA") -> OK | F26: Tarifas.xlsx · F77 (≠ Cot. 1255 p.1–2) | G26: Medido
B27: Ecotransur rango 3 (COP) | C27: =Simulador!E46 -> 249003002 | D27: 249003002 | E27: =IF(ABS(C27-D27)<0.005,"OK","DIFERENCIA") -> OK | F27: Tarifas.xlsx · G77 | G27: Medido
B28: Petro Star normal rango 4 (COP) | C28: =Simulador!F44 -> 246462998 | D28: 246462998 | E28: =IF(ABS(C28-D28)<0.005,"OK","DIFERENCIA") -> OK | F28: Tarifas.xlsx · E103 | G28: Medido
B29: Lump Sum rango 4 (COP) | C29: =Simulador!F45 -> 414800928 | D29: 414800928 | E29: =IF(ABS(C29-D29)<0.005,"OK","DIFERENCIA") -> OK | F29: Tarifas.xlsx · F103 (≠ Cot. 1255 p.1–2) | G29: Medido
B30: Ecotransur rango 4 (COP) | C30: =Simulador!F46 -> 253060002 | D30: 253060002 | E30: =IF(ABS(C30-D30)<0.005,"OK","DIFERENCIA") -> OK | F30: Tarifas.xlsx · G103 | G30: Medido
B31: Señalizador turno 12 h (COP) | C31: =Simulador!C21 -> 375000 | D31: 375000 | E31: =IF(ABS(C31-D31)<0.005,"OK","DIFERENCIA") -> OK | F31: Cot. 1255 p. 5 | G31: Medido
B32: Recargo señalizadoras misma loc. (USD) | C32: =Simulador!C50 -> 405.40541 | D32: 405.40541 | E32: =IF(ABS(C32-D32)<0.005,"OK","DIFERENCIA") -> OK | F32: Tarifas.xlsx · K11 (verificado) | G32: Cálculo
B33: Recargo señalizadoras otros rangos (USD) | C33: =Simulador!D50 -> 810.81081 | D33: 810.81081 | E33: =IF(ABS(C33-D33)<0.005,"OK","DIFERENCIA") -> OK | F33: Tarifas.xlsx · L11 (verificado) | G33: Cálculo
B34: Costo Suma Global PS rango 1 (USD) | C34: =Simulador!C62-Simulador!C69+IF(Simulador!$C$16="Mensual fijo",Simulador!$C$14/Simulador!$C$7/Simulador!$C$15,0) -> 58116.714 | D34: 58116.714 | E34: =IF(ABS(C34-D34)<0.005,"OK","DIFERENCIA") -> OK | F34: Tarifas.xlsx · E31 (fila amarilla; se suma el TM prorrateado si es mensual) | G34: Control
B35: Costo Suma Global PS rango 2 (USD) | C35: =Simulador!D62-Simulador!D69+IF(Simulador!$C$16="Mensual fijo",Simulador!$C$14/Simulador!$C$7/Simulador!$C$15,0) -> 88600.725 | D35: 88600.725 | E35: =IF(ABS(C35-D35)<0.005,"OK","DIFERENCIA") -> OK | F35: Tarifas.xlsx · E57 (fila amarilla; se suma el TM prorrateado si es mensual) | G35: Control
B36: Costo Suma Global PS rango 3 (USD) | C36: =Simulador!E62-Simulador!E69+IF(Simulador!$C$16="Mensual fijo",Simulador!$C$14/Simulador!$C$7/Simulador!$C$15,0) -> 102096.16 | D36: 102096.16 | E36: =IF(ABS(C36-D36)<0.005,"OK","DIFERENCIA") -> OK | F36: Tarifas.xlsx · E83 (fila amarilla; se suma el TM prorrateado si es mensual) | G36: Control
B37: Costo Suma Global PS rango 4 (USD) | C37: =Simulador!F62-Simulador!F69+IF(Simulador!$C$16="Mensual fijo",Simulador!$C$14/Simulador!$C$7/Simulador!$C$15,0) -> 110082.32 | D37: 110082.32 | E37: =IF(ABS(C37-D37)<0.005,"OK","DIFERENCIA") -> OK | F37: Tarifas.xlsx · E109 (fila amarilla; se suma el TM prorrateado si es mensual) | G37: Control
B38: Costo Suma Global LS rango 1 (USD) | C38: =Simulador!C64-Simulador!C69+IF(Simulador!$C$16="Mensual fijo",Simulador!$C$14/Simulador!$C$7/Simulador!$C$15,0) -> 68381.158 | D38: 68381.158 | E38: =IF(ABS(C38-D38)<0.005,"OK","DIFERENCIA") -> OK | F38: Tarifas.xlsx · F31 (fila amarilla; se suma el TM prorrateado si es mensual) | G38: Control
B39: Costo Suma Global LS rango 2 (USD) | C39: =Simulador!D64-Simulador!D69+IF(Simulador!$C$16="Mensual fijo",Simulador!$C$14/Simulador!$C$7/Simulador!$C$15,0) -> 111149.81 | D39: 111149.81 | E39: =IF(ABS(C39-D39)<0.005,"OK","DIFERENCIA") -> OK | F39: Tarifas.xlsx · F57 (fila amarilla; se suma el TM prorrateado si es mensual) | G39: Control
B40: Costo Suma Global LS rango 3 (USD) | C40: =Simulador!E64-Simulador!E69+IF(Simulador!$C$16="Mensual fijo",Simulador!$C$14/Simulador!$C$7/Simulador!$C$15,0) -> 138633.16 | D40: 138633.16 | E40: =IF(ABS(C40-D40)<0.005,"OK","DIFERENCIA") -> OK | F40: Tarifas.xlsx · F83 (fila amarilla; se suma el TM prorrateado si es mensual) | G40: Control
B41: Costo Suma Global LS rango 4 (USD) | C41: =Simulador!F64-Simulador!F69+IF(Simulador!$C$16="Mensual fijo",Simulador!$C$14/Simulador!$C$7/Simulador!$C$15,0) -> 155579.06 | D41: 155579.06 | E41: =IF(ABS(C41-D41)<0.005,"OK","DIFERENCIA") -> OK | F41: Tarifas.xlsx · F109 (fila amarilla; se suma el TM prorrateado si es mensual) | G41: Control
B42: Costo Suma Global EC rango 1 (USD) | C42: =Simulador!C66-Simulador!C69+IF(Simulador!$C$16="Mensual fijo",Simulador!$C$14/Simulador!$C$7/Simulador!$C$15,0) -> 58075.514 | D42: 58075.514 | E42: =IF(ABS(C42-D42)<0.005,"OK","DIFERENCIA") -> OK | F42: Tarifas.xlsx · G31 (fila amarilla; se suma el TM prorrateado si es mensual) | G42: Control
B43: Costo Suma Global EC rango 2 (USD) | C43: =Simulador!D66-Simulador!D69+IF(Simulador!$C$16="Mensual fijo",Simulador!$C$14/Simulador!$C$7/Simulador!$C$15,0) -> 85046.649 | D43: 85046.649 | E43: =IF(ABS(C43-D43)<0.005,"OK","DIFERENCIA") -> OK | F43: Tarifas.xlsx · G57 (fila amarilla; se suma el TM prorrateado si es mensual) | G43: Control
B44: Costo Suma Global EC rango 3 (USD) | C44: =Simulador!E66-Simulador!E69+IF(Simulador!$C$16="Mensual fijo",Simulador!$C$14/Simulador!$C$7/Simulador!$C$15,0) -> 104944.81 | D44: 104944.81 | E44: =IF(ABS(C44-D44)<0.005,"OK","DIFERENCIA") -> OK | F44: Tarifas.xlsx · G83 (fila amarilla; se suma el TM prorrateado si es mensual) | G44: Control
B45: Costo Suma Global EC rango 4 (USD) | C45: =Simulador!F66-Simulador!F69+IF(Simulador!$C$16="Mensual fijo",Simulador!$C$14/Simulador!$C$7/Simulador!$C$15,0) -> 111865.3 | D45: 111865.3 | E45: =IF(ABS(C45-D45)<0.005,"OK","DIFERENCIA") -> OK | F45: Tarifas.xlsx · G109 (fila amarilla; se suma el TM prorrateado si es mensual) | G45: Control
B46: WO de la campaña 15+20 (USD) | C46: =Simulador!C83 -> 3130187.3 | D46: 3130187.3 | E46: =IF(ABS(C46-D46)<0.005,"OK","DIFERENCIA") -> OK | F46: Tarifas.xlsx · M18 (la nota J55 dice 3.107.890) | G46: Control
B48: Cargos fijos mensuales: Simulador C72:D78 transcritos de Cot. 1255 p. 4 (nómina + disponibilidad) y Ecotransur p. 2–3 (nómina + stand-by). Equipos Ecotransur 6ª+: p. 3–4. Perfiles de frecuencia: logs C11:C21 (2024) y C11:C19 (2025).

Sheet Medido y supuesto
B1: Lo medido y lo supuesto, separados
B2: Los supuestos van en amarillo en el Simulador y se tratan aparte de los datos medidos.
B4: MEDIDO | C4: Fuente | D4: Nota
B5: Bloqueos durante movilización 2025: 22,25 h social/escolar en fase 01MIRU (4 movs con paro, 3 con restricción escolar) | C5: Evaluacion_Drilling_IM_Jul_2026_v5.xlsx · NPT Social 2025 (OpenWells) | D5: Los bloqueos largos (17–72 h) cayeron en perforación: ambos modelos pagan igual.
B6: Tarifas de las tres ofertas por rango | C6: Tarifas.xlsx E/F/G | D6: Precios tal cual SCM los pasó (F no coincide con la Cot. 1255).
B7: TRM y tarifa del taladro | C7: Tarifas.xlsx E3, E5
B8: Cargo fijo mensual por número de movilizaciones | C8: Cot. 1255 p. 4 · Ecotransur p. 2–3
B9: Descuento desde la 6ª (Petro Star 50 %; Ecotransur solo equipos) | C9: Cot. 1255 p. 2 · Ecotransur p. 3–4
B10: Tarifa del señalizador (375.000 COP/turno) | C10: Cot. 1255 p. 5
B11: Frecuencia mensual 2024 y 2025 | C11: Logs, tabla por mes | D11: Dos observaciones independientes; no se promedian.
B12: Mezcla por rango 2024 (23/29/14/4) y 2025 (11/17/10/7) | C12: Logs, resumen por rango
B13: Horas reales por movilización | C13: Logs, columna Tiempo mov hr | D13: Pozo 5136 sin horas.
B14: Horas totales declaradas por Petro Star (12/24/36/36) | C14: Cot. 1255 p. 1–2 | D14: Referencia; el simulador usa las del Excel.
B15: Cláusula de demoras no atribuibles (Petro Star) | C15: Cot. 1255 p. 5, condición 7 | D15: Ecotransur no la trae.
B18: SUPUESTO O PREMISA | C18: Origen | D18: Nota
B19: Work Order base y 12 señalizadoras | C19: Premisa SierraCol | D19: No está en los archivos.
B20: Adicionales 0 % en ambos modelos | C20: Premisa SierraCol | D20: Sensibilidad: +5 % solo en tercerizado.
B21: Truck Manager mensual: 60 M COP por mes de campaña | C21: Premisa SierraCol (evaluación v5) | D21: El prorrateo del Excel (2.702,70 USD por movilización) queda solo como sensibilidad.
B22: Campaña 15 misma loc. + 20 otra loc. | C22: Premisa SierraCol | D22: No sale de los logs.
B23: Rango de los 20 pozos: 0,1–5 km | C23: Premisa SierraCol | D23: Confirmado por SierraCol.
B24: Frecuencia esperada 5–6 movs/mes | C24: Premisa SierraCol | D24: Sensibilidad de 4 a 8 movs/mes.
B25: TRM 3.700 | C25: Premisa SierraCol | D25: Fija para el ejercicio.
B26: Tiempo estipulado de Ecotransur = el de Petro Star (12/24/36/36 h) y mismas tarifas por hora | C26: Supuesto | D26: Su carta no declara tiempos ni tarifas horarias.
... B36: Más de 20 km se paga con la tarifa de 10–20 km | C36: Supuesto | D36: 1 movimiento en 2024.
B37: IVA fuera del análisis | C37: Premisa SierraCol

Sheet Sensibilidad
B1: Sensibilidad: de qué depende que haya o no ahorro
B2: Ahorro = costo WO − costo tercerizado (USD); positivo = el tercerizado cuesta menos. Campaña 15 misma loc. + 20 en 0,1–5 km, TRM 3.700, 17,3 h de bloqueo social en movilización (OpenWells 2025). Valores fijos calculados con el mismo modelo del Simulador; no cambian al editar el Simulador.
B4: 1. FRECUENCIA: AHORRO DE LA CAMPAÑA SEGÚN MOVILIZACIONES POR MES (esperado 5–6)
B5: Movs/mes | C5: Petro Star tarifa normal · horas Excel | D5: Petro Star Lump Sum · horas Excel | E5: Ecotransur · horas Excel | F5: Petro Star tarifa normal · horas cotizadas | G5: Petro Star Lump Sum · horas cotizadas | H5: Ecotransur · horas cotizadas
B6: 4 | C6: -135092.52 | D6: -740040.84 | E6: 5451.8713 | F6: -309812.52 | G6: -914760.84 | H6: -169268.13
B7: 4,5 | C7: -2580.4417 | D7: -607528.76 | E7: 247985.61 | F7: -177300.44 | G7: -782248.76 | H7: 73265.611
B8: 5 | C8: 132152.06 | D8: -472796.26 | E8: 490519.35 | F8: -42567.937 | G8: -647516.26 | H8: 315799.35
B9: 5,5 | C9: 279484.05 | D9: -404125.29 | E9: 405025.86 | F9: 104764.05 | G9: -578845.29 | H9: 230305.86
B10: 6 | C10: 521560.55 | D10: -210864.81 | E10: 584485.57 | F10: 346840.55 | G10: -385584.81 | H10: 409765.57
B11: 6,5 | C11: 541571.5 | D11: -239669.88 | E11: 521411.53 | F11: 366851.5 | G11: -414389.88 | H11: 346691.53
B12: 7 | C12: 695332.35 | D12: -153696.06 | E12: 660216.65 | F12: 520612.35 | G12: -328416.06 | H12: 485496.65
B13: 8 | C13: 696138.76 | D13: -223453.67 | E13: 633612.89 | F13: 521418.76 | G13: -398173.67 | H13: 458892.89
B14: Horas cotizadas = 12/24/36/36 h (Cot. 1255). Con frecuencias no enteras se alternan meses (p. ej. 5,5 = meses de 6 y de 5). El último mes de la campaña puede quedar corto y pagar cargo fijo: por eso la curva sube y baja.
B16: 2. PUNTOS DE QUIEBRE: CUÁNTO AGUANTA EL AHORRO ANTES DE DESAPARECER
B17: Movs/mes | C17: Oferta | D17: Ahorro campaña (USD) | E17: Ahorro por pozo (USD) | F17: % del costo de un pozo (600 k) | G17: Horas extra de taladro por movilización que lo anulan | H17: Horas sobre el tiempo estipulado que lo anulan (taladro + equipos) | I17: Días de taladro de demora en toda la campaña que lo anulan | J17: Meses bloqueados que lo anulan | K17: Horas de bloqueo en movilización que lo anulan (campaña)
B18: 5 | C18: Petro Star normal | D18: 132152.06 | E18: 3775.7732 | F18: 0.0062929554 | G18: 2.5932508 | H18: 1.3421811 | I18: 3.7818241 | J18: 0.74675865 | K18: 46.97634
B19: 5 | C19: Ecotransur | D19: 490519.35 | E19: 14014.839 | F19: 0.023358064 | G19: 9.6255759 | H19: 4.9818808 | I19: 14.037298 | J19: 2.0224788 | K19: 174.36583
B20: 6 | C20: Petro Star normal | D20: 521560.55 | E20: 14901.73 | F20: 0.024836217 | G20: 10.234705 | H20: 5.2971458 | I20: 14.925611 | J20: 2.9472098 | K20: 185.4001
B21: 6 | C21: Ecotransur | D21: 584485.57 | E21: 16699.588 | F21: 0.027832646 | G21: 11.469497 | H21: 5.9362336 | I21: 16.72635 | J21: 2.4099145 | K21: 207.76818
B22: Hora excedida en el tercerizado: taladro 1.456 + equipos y señalizadores 1.357 = 2.813 USD/h (Cot. 1255 p. 5). En el Work Order cuesta 0. Un mes bloqueado: Petro Star 176.968 · Ecotransur 242.534 USD.
B24: 3. LO QUE PASÓ CON LAS HORAS REALES (logs): campañas 2024 y 2025 repetidas con cada modelo
B25: Año | C25: Oferta | D25: Ahorro con horas Excel | E25: Ahorro con horas reales (solo taladro) | F25: Ahorro con horas reales + equipos por hora excedida | G25: Movilizaciones que exceden el tiempo estipulado | H25: Horas excedidas | I25: Equipos y señalizadores (USD) | J25: Taladro en esas horas (USD)
B26: 2024 | C26: Petro Star normal | D26: 1045536.9 | E26: 1225935.3 | F26: 1136023.3 | G26: 10 | H26: 66.25 | I26: 89911.993 | J26: 96460
B27: 2024 | C27: Ecotransur | D27: 906138.47 | E27: 1086536.9 | F27: 996624.87 | G27: 10 | H27: 66.25 | I27: 89911.993 | J27: 96460
B28: 2024 | C28: Lump Sum | D28: -1063638.5 | E28: -883240.07 | F28: -973152.06 | G28: 10 | H28: 66.25 | I28: 89911.993 | J28: 96460
B29: 2025 | C29: Petro Star normal | D29: 160847.46 | E29: 56743.46 | F29: -70829.783 | G29: 15 | H29: 94 | I29: 127573.24 | J29: 136864
B30: 2025 | C30: Ecotransur | D30: 152514.34 | E30: 48410.339 | F30: -79162.904 | G30: 15 | H30: 94 | I30: 127573.24 | J30: 136864
B31: 2025 | C31: Lump Sum | D31: -1217010 | E31: -1321114 | F31: -1448687.2 | G31: 15 | H31: 94 | I31: 127573.24 | J31: 136864
B32: Horas reales: el taladro se paga por las horas reales (más o menos que el Excel). Las horas por encima de 12/24/36/36 h se cobran además en equipos y señalizadores (Cot. 1255 p. 5; Ecotransur con las mismas tarifas, supuesto).
B34: 4. TORNADO · Petro Star tarifa normal · 5 movs/mes · ahorro base 132.152 USD
B35: Variable | C35: Clase | D35: Valor base | E35: Extremo que mejora | F35: Ahorro (USD) | G35: Extremo que empeora | H35: Ahorro (USD) | I35: Efecto (USD)
B36: Frecuencia mensual | C36: Premisa (5–6) | D36: 5/mes | E36: 6/mes | F36: 521560.55 | G36: 5/mes | H36: 132152.06 | I36: 389408.49
B37: Horas por encima del tiempo estipulado (taladro + equipos) | C37: Medido (logs) | D37: 0 h | E37: 0 h | F37: 132152.06 | G37: +2 h sobre 12/24/36/36 | H37: -239489.29 | I37: 371641.35
B38: Cargo fijo de Petro Star con 5 movs/mes | C38: Medido (la cotización dice mínimo 5, pero la tabla p. 4 cobra con 5) | D38: se cobra (p. 4) | E38: no se cobra | F38: 418819.83 | G38: se cobra | H38: 132152.06 | I38: 286667.77
B39: NPT de perforación (baja la frecuencia) | C39: Sin dato: barrido | D39: 0 % | E39: 0 % | F39: 132152.06 | G39: 20 % | H39: -135092.52 | I39: 267244.58
B40: Sobretiempo en cada movilización (solo taladro) | C40: Medido (logs) | D40: 0 h | E40: 0 h | F40: 132152.06 | G40: +3,5 h | H40: -117458.95 | I40: 249611.01
B41: Meses bloqueados (contrato vigente) | C41: Riesgo operativo | D41: 0 | E41: 0 | F41: 132152.06 | G41: 1 mes | H41: -44815.505 | I41: 176967.57
B42: Horas de taladro por movilización | C42: Dato Excel vs cotización | D42: Excel 12/18/24/28 | E42: Excel 12/18/24/28 | F42: 132152.06 | G42: Petro Star 12/24/36/36 | H42: -42567.937 | I42: 174720
B43: Tarifa del taladro | C43: Medido | D43: 34.944 USD/día | E43: −10 % | F43: 213295.75 | G43: +10 % | H43: 51008.374 | I43: 162287.38
B44: Tarifa WO en movilizaciones lentas (bajo el tope) | C44: Premisa SierraCol (tope) | D44: tope | E44: tope | F44: 132152.06 | G44: −5 % al WO | H44: -23242.437 | I44: 155394.5
B45: Bloqueo social/escolar durante movilizaciones (h por campaña) | C45: Medido (OpenWells 2025) | D45: 17,3 h | E45: 0 h | F45: 180835.4 | G45: 34,6 h (el doble) | H45: 83468.729 | I45: 97366.668
B46: Adicionales: ¿se cancelan entre modelos? | C46: Premisa SierraCol | D46: 0 % / 0 % | E46: se cancelan | F46: 132152.06 | G46: +5 % solo en tercerizado | H46: 44005.532 | I46: 88146.531
B47: Recargo de señalizadoras al WO | C47: Premisa SierraCol | D47: se carga | E47: se carga | F47: 132152.06 | G47: no se carga | H47: 109854.77 | I47: 22297.297
B48: Truck Manager | C48: Premisa SierraCol | D48: 60 M COP por mes | E48: 2.702,70 USD por movilización (Excel) | F48: 151070.98 | G48: 60 M COP por mes | H48: 132152.06 | I48: 18918.919
B50: 4. TORNADO · Petro Star Lump Sum (sin descuento) · 5 movs/mes · ahorro base -472.796 USD
B51: Variable | C51: Clase | D51: Valor base | E51: Extremo que mejora | F51: Ahorro (USD) | G51: Extremo que empeora | H51: Ahorro (USD) | I51: Efecto (USD)
B52: Horas por encima del tiempo estipulado (taladro + equipos) | C52: Medido (logs) | D52: 0 h | E52: 0 h | F52: -472796.26 | G52: +2 h sobre 12/24/36/36 | H52: -844437.61 | I52: 371641.35
B53: Cargo fijo de Petro Star con 5 movs/mes | C53: Medido (la cotización dice mínimo 5, pero la tabla p. 4 cobra con 5) | D53: se cobra (p. 4) | E53: no se cobra | F53: -186128.49 | G53: se cobra | H53: -472796.26 | I53: 286667.77
B54: NPT de perforación (baja la frecuencia) | C54: Sin dato: barrido | D54: 0 % | E54: 0 % | F54: -472796.26 | G54: 20 % | H54: -740040.84 | I54: 267244.58
B55: Frecuencia mensual | C55: Premisa (5–6) | D55: 5/mes | E55: 6/mes | F55: -210864.81 | G55: 5/mes | H55: -472796.26 | I55: 261931.44
B56: Sobretiempo en cada movilización (solo taladro) | C56: Medido (logs) | D56: 0 h | E56: 0 h | F56: -472796.26 | G56: +3,5 h | H56: -722407.27 | I56: 249611.01
B57: Meses bloqueados (contrato vigente) | C57: Riesgo operativo | D57: 0 | E57: 0 | F57: -472796.26 | G57: 1 mes | H57: -649763.82 | I57: 176967.57
B58: Horas de taladro por movilización | C58: Dato Excel vs cotización | D58: Excel 12/18/24/28 | E58: Excel 12/18/24/28 | F58: -472796.26 | G58: Petro Star 12/24/36/36 | H58: -647516.26 | I58: 174720
B59: Tarifa del taladro | C59: Medido | D59: 34.944 USD/día | E59: −10 % | F59: -391652.57 | G59: +10 % | H59: -553939.95 | I59: 162287.38
B60: Tarifa WO en movilizaciones lentas (bajo el tope) | C60: Premisa SierraCol (tope) | D60: tope | E60: tope | F60: -472796.26 | G60: −5 % al WO | H60: -628190.76 | I60: 155394.5
B61: Adicionales: ¿se cancelan entre modelos? | C61: Premisa SierraCol | D61: 0 % / 0 % | E61: se cancelan | F61: -472796.26 | G61: +5 % solo en tercerizado | H61: -591190.2 | I61: 118393.95
B62: Bloqueo social/escolar durante movilizaciones (h por campaña) | C62: Medido (OpenWells 2025) | D62: 17,3 h | E62: 0 h | F62: -424112.92 | G62: 34,6 h (el doble) | H62: -521479.59 | I62: 97366.668
B63: Recargo de señalizadoras al WO | C63: Premisa SierraCol | D63: se carga | E63: se carga | F63: -472796.26 | G63: no se carga | H63: -495093.55 | I63: 22297.297
B64: Truck Manager | C64: Premisa SierraCol | D64: 60 M COP por mes | E64: 2.702,70 USD por movilización (Excel) | F64: -453877.34 | G64: 60 M COP por mes | H64: -472796.26 | I64: 18918.919
B66: 4. TORNADO · Ecotransur · 5 movs/mes · ahorro base 490.519 USD
B67: Variable | C67: Clase | D67: Valor base | E67: Extremo que mejora | F67: Ahorro (USD) | G67: Extremo que empeora | H67: Ahorro (USD) | I67: Efecto (USD)
B68: NPT de perforación (baja la frecuencia) | C68: Sin dato: barrido | D68: 0 % | E68: 0 % | F68: 490519.35 | G68: 20 % | H68: 5451.8713 | I68: 485067.48
B69: Horas por encima del tiempo estipulado (taladro + equipos) | C69: Medido (logs) | D69: 0 h | E69: 0 h | F69: 490519.35 | G69: +2 h sobre 12/24/36/36 | H69: 118878 | I69: 371641.35
B70: Sobretiempo en cada movilización (solo taladro) | C70: Medido (logs) | D70: 0 h | E70: 0 h | F70: 490519.35 | G70: +3,5 h | H70: 240908.34 | I70: 249611.01
B71: Meses bloqueados (contrato vigente) | C71: Riesgo operativo | D71: 0 | E71: 0 | F71: 490519.35 | G71: 1 mes | H71: 247985.61 | I71: 242533.74
B72: Horas de taladro por movilización | C72: Dato Excel vs cotización | D72: Excel 12/18/24/28 | E72: Excel 12/18/24/28 | F72: 490519.35 | G72: Petro Star 12/24/36/36 | H72: 315799.35 | I72: 174720
B73: Tarifa del taladro | C73: Medido | D73: 34.944 USD/día | E73: −10 % | F73: 571663.04 | G73: +10 % | H73: 409375.66 | I73: 162287.38
B74: Tarifa WO en movilizaciones lentas (bajo el tope) | C74: Premisa SierraCol (tope) | D74: tope | E74: tope | F74: 490519.35 | G74: −5 % al WO | H74: 335124.85 | I74: 155394.5
B75: Bloqueo social/escolar durante movilizaciones (h por campaña) | C75: Medido (OpenWells 2025) | D75: 17,3 h | E75: 0 h | F75: 539202.68 | G75: 34,6 h (el doble) | H75: 441836.02 | I75: 97366.668
B76: Frecuencia mensual | C76: Premisa (5–6) | D76: 5/mes | E76: 6/mes | F76: 584485.57 | G76: 5/mes | H76: 490519.35 | I76: 93966.219
B77: Adicionales: ¿se cancelan entre modelos? | C77: Premisa SierraCol | D77: 0 % / 0 % | E77: se cancelan | F77: 490519.35 | G77: +5 % solo en tercerizado | H77: 405957.79 | I77: 84561.555
B78: Recargo de señalizadoras al WO | C78: Premisa SierraCol | D78: se carga | E78: se carga | F78: 490519.35 | G78: no se carga | H78: 468222.05 | I78: 22297.297
B79: Truck Manager | C79: Premisa SierraCol | D79: 60 M COP por mes | E79: 2.702,70 USD por movilización (Excel) | F79: 509438.27 | G79: 60 M COP por mes | H79: 490519.35 | I79: 18918.919
B81: 4. TORNADO · Petro Star tarifa normal · 6 movs/mes · ahorro base 521.561 USD
B82: Variable | C82: Clase | D82: Valor base | E82: Extremo que mejora | F82: Ahorro (USD) | G82: Extremo que empeora | H82: Ahorro (USD) | I82: Efecto (USD)
B83: NPT de perforación (baja la frecuencia) | C83: Sin dato: barrido | D83: 0 % | E83: 0 % | F83: 521560.55 | G83: 20 % | H83: -10228.843 | I83: 531789.4
B84: Frecuencia mensual | C84: Premisa (5–6) | D84: 6/mes | E84: 6/mes | F84: 521560.55 | G84: 5/mes | H84: 132152.06 | I84: 389408.49
B85: Horas por encima del tiempo estipulado (taladro + equipos) | C85: Medido (logs) | D85: 0 h | E85: 0 h | F85: 521560.55 | G85: +2 h sobre 12/24/36/36 | H85: 149919.2 | I85: 371641.35
B86: Sobretiempo en cada movilización (solo taladro) | C86: Medido (logs) | D86: 0 h | E86: 0 h | F86: 521560.55 | G86: +3,5 h | H86: 271949.54 | I86: 249611.01
B87: Meses bloqueados (contrato vigente) | C87: Riesgo operativo | D87: 0 | E87: 0 | F87: 521560.55 | G87: 1 mes | H87: 344592.99 | I87: 176967.57
B88: Horas de taladro por movilización | C88: Dato Excel vs cotización | D88: Excel 12/18/24/28 | E88: Excel 12/18/24/28 | F88: 521560.55 | G88: Petro Star 12/24/36/36 | H88: 346840.55 | I88: 174720
B89: Tarifa del taladro | C89: Medido | D89: 34.944 USD/día | E89: −10 % | F89: 602704.24 | G89: +10 % | H89: 440416.86 | I89: 162287.38
B90: Tarifa WO en movilizaciones lentas (bajo el tope) | C90: Premisa SierraCol (tope) | D90: tope | E90: tope | F90: 521560.55 | G90: −5 % al WO | H90: 366166.05 | I90: 155394.5
B91: Bloqueo social/escolar durante movilizaciones (h por campaña) | C91: Medido (OpenWells 2025) | D91: 17,3 h | E91: 0 h | F91: 570243.89 | G91: 34,6 h (el doble) | H91: 472877.22 | I91: 97366.668
B92: Adicionales: ¿se cancelan entre modelos? | C92: Premisa SierraCol | D92: 0 % / 0 % | E92: se cancelan | F92: 521560.55 | G92: +5 % solo en tercerizado | H92: 439787.87 | I92: 81772.679
B93: Orden de los pozos dentro del mes | C93: Supuesto | D93: intercalado | E93: misma loc. primero | F93: 543308.56 | G93: otra loc. primero | H93: 488938.54 | I93: 54370.029
B94: Cargo fijo de Petro Star con 5 movs/mes | C94: Medido (la cotización dice mínimo 5, pero la tabla p. 4 cobra con 5) | D94: se cobra (p. 4) | E94: no se cobra | F94: 562513.09 | G94: se cobra | H94: 521560.55 | I94: 40952.538
... B96: Truck Manager | C96: Premisa SierraCol | D96: 60 M COP por mes | E96: 2.702,70 USD por movilización (Excel) | F96: 524263.26 | G96: 60 M COP por mes | H96: 521560.55 | I96: 2702.7027
B98: 4. TORNADO · Petro Star Lump Sum (sin descuento) · 6 movs/mes · ahorro base -210.865 USD
B99: Variable | C99: Clase | D99: Valor base | E99: Extremo que mejora | F99: Ahorro (USD) | G99: Extremo que empeora | H99: Ahorro (USD) | I99: Efecto (USD)
B100: NPT de perforación (baja la frecuencia) | C100: Sin dato: barrido | D100: 0 % | E100: 0 % | F100: -210864.81 | G100: 20 % | H100: -615177.16 | I100: 404312.35
B101: Horas por encima del tiempo estipulado (taladro + equipos) | C101: Medido (logs) | D101: 0 h | E101: 0 h | F101: -210864.81 | G101: +2 h sobre 12/24/36/36 | H101: -582506.16 | I101: 371641.35
B102: Frecuencia mensual | C102: Premisa (5–6) | D102: 6/mes | E102: 6/mes | F102: -210864.81 | G102: 5/mes | H102: -472796.26 | I102: 261931.44
B103: Sobretiempo en cada movilización (solo taladro) | C103: Medido (logs) | D103: 0 h | E103: 0 h | F103: -210864.81 | G103: +3,5 h | H103: -460475.82 | I103: 249611.01
